Workbook
Name asiCOM: Parametros!$C$1146:$J$1172
Name cfgEmpresa: Parametros!$B$2:$L$121
Name ComprobantesCOM: Parametros!$C$190:$C$218
Name ComprobantesEXP: Parametros!$C$155:$C$162
Name ComprobantesVEN: Parametros!$C$166:$C$186
Name Distritos: Parametros!$C$1049:$C$1063
Name gruContableGAS: Parametros!$C$1146:$C$1172
Name gruContableING: Parametros!$C$1138:$C$1142
Name ingExterior: Parametros!$C$1067:$C$1106
Name IVAs: Parametros!$C$125:$C$134
Name LIQ_PER: LIQ_IMPUESTOS!$C$5:$C$16
Name ListaActividades: Parametros!$C$138:$C$150
Name meses_103: '103'!$C$5:$N$5
Name meses_104: '104'!$C$4:$N$4
Name NumDocs: Parametros!$C$52:$J$62
Name pagos: Parametros!$C$243:$C$264
Name paises: Parametros!$C$411:$C$670
Name paises17a: Parametros!$C$674:$C$763
Name paises17b: Parametros!$G$674:$G$763
Name paisesEXP: Parametros!$C$767:$C$1025
Name Regimen: Parametros!$D$39
Name Regimenes: Parametros!$C$1029:$C$1038
Name Retenciones: Parametros!$C$268:$C$407
Name sustentos: Parametros!$C$222:$C$239
Name tarifasIVA: Parametros!$E$128:$E$133
Name tbIBPs: Parametros!$C$1125:$J$1126
Name tbIBPs2: Parametros!$D$1125:$D$1126
Name tbICEs: Parametros!$C$1110:$J$1121
Name tbICEs2: Parametros!$D$1110:$D$1121
Name tbl_Empre: Parametros!$N$5:$Q$10
Name tbl_NegPop: Parametros!$S$5:$U$9
Name TipoPagos: Parametros!$C$243:$J$264
Name tiposexp: Parametros!$C$1042:$C$1045
Name XLSperiodo: Parametros!$D$20
Name XLSversion: Parametros!$D$100

Sheet Diario
A1: CONTABILIDAD - DETALLE DE ASIENTOS DE DIARIO CONTABLE
A6: Autocodigo Secuencial | B6: Numero de Transaccion | C6: Fecha Transaccion | D6: Tipo Transaccion | E6: Autocodigo Modulo | F6: Cuenta Contable | G6: Descripcion Cuenta | H6: Valor DEBE | I6: Valor HABER | J6: ND | K6: Observaciones | L6: Nota Explicativa NIIFs | M6: Glosa

Sheet Tesoreria
A1: TESORERIA - DETALLE DE COBROS Y PAGOS
A6: Autocodigo TESORERIA | B6: Autocodigo Modulo | C6: Fecha Movimiento | D6: Autocodigo Documentos | E6: Tipo Transaccion | F6: Modulo | G6: FORMA DE COBRO/PAGO | H6: Valor Transaccion | I6: No. de documento Cheque/Voucher/Ret. | J6: Nombre y/o Institucion | K6: Observaciones | L6: No. Asiento Contable | M6: No. ID / RUC | N6: Razon Social Contribuyente | O6: No. Documento / Factura SRI

Sheet Detalles
A1: DETALLE DE DOCUMENTOS EMITIDOS
A6: Autocodigo DETALLE | B6: Modulo | C6: Autocodigo Documentos | D6: Fecha Movimiento | E6: ID Articulo | F6: Codigo Principal | G6: Codigo Auxiliar | H6: Descripcion | I6: Unidad de Medida | J6: Cantidad | K6: Precio | L6: PVP Sin Subsidio | M6: Base Imponible | N6: Tipo Impuesto | O6: (%) Descto. | P6: Descuento Valor | Q6: Grava ICE | R6: ICE CODIGO | S6: ICE (%) | T6: ICE Valor Base | U6: ICE Valor Impuesto | V6: ICE EN IVA | W6: Grava IRBPNR | X6: IRBPNR CODIGO | Y6: IRBPNR (%) | Z6: IRBPNR Valor Base | AA6: IRBPNR Valor Impuesto | AB6: Valor IVA | AC6: Valor Subtotal | AD6: Atributos Adicionales | AE6: No. ID / RUC | AF6: Razon Social Contribuyente | AG6: No. Documento / Factura | AH6: Tipo Documento | AI6: Tarifa de IVA

Sheet Articulos
A1: LISTADO DE PRODUCTOS O SERVICIOS
A6: Autocodigo ARTICULOS | B6: Codigo Principal | C6: Codigo Secundario | D6: Descripcion | E6: Grupo | F6: Unidad de Medida | G6: Valor Unitario | H6: PVP sin Subsidio | I6: Impuesto IVA | J6: Descuento (%) | K6: ICE CODIGO | L6: IRBPNR CODIGO | M6: Atributos
A7: HA0000001 | B7: HONO500 | D7: HONORARIOS PROFESIONALES | E7: GENERAL | G7: 500 | H7: 0 | I7: GRAVABLE | J7: 0

Sheet Contribuyentes
A1: LISTADO DE CONTRIBUYENTES
A6: ID | B6: No. de Identificacion | C6: Tipo Identificación | D6: Apellidos y Nombres / Razon Social | E6: Direccion | F6: Tipo Proveedor | G6: Parte Relacionada | H6: Telefono | I6: email | J6: Placa / Matricula | K6: Clasificacion | L6: Cuenta Contable
A7: HC0000001 | B7: 9999999999999 | C7: F-Consumidor Final | D7: CONSUMIDOR FINAL | F7: 01-Persona Natural | G7: NO | K7: CLIENTE

Sheet Parametros
C2: Configuracion y datos de la Empresa | N2: TABLA IMPTO. REGIMEN RIMPE EMPRENDEDOR | S2: TABLA IMPTO. REGIMEN RIMPE NEG.POPULAR
N3: Año 2026 En dólares | S3: Año 2026 En dólares
B4: dt_rucemp | C4: No. de RUC | D4: 0917809451001 | G4: <== modificar por sus datos | K4: S | N4: Limite Inferior | O4: Limite Superior | P4: Imp. Frac. Básica | Q4: Tipo Marginal % | S4: Limite Inferior | T4: Limite Superior | U4: Pago Anual
B5: dt_razsoc | C5: Razon Social | D5: GARCIA RODRIGUEZ CHARLES MILTON | G5: <== modificar por sus datos | K5: S | N5: 0 | O5: 20000 | P5: 0 | Q5: 0 | S5: 0 | T5: 2500 | U5: 0
B6: dt_repleg | C6: Representante Legal | D6: GARCIA RODRIGUEZ CHARLES MILTON | G6: <== modificar por sus datos | K6: S | N6: =O5+0.01 -> 20000.01 | O6: 50000 | P6: 60 | Q6: 0.01 | S6: =T5+0.01 -> 2500.01 | T6: 5000 | U6: 5
B7: dt_cedrep | C7: Cedula Rep. Legal | D7: 0917809451001 | G7: <== modificar por sus datos | K7: S | N7: =O6+0.01 -> 50000.01 | O7: =+O6+25000 -> 75000 | P7: 360 | Q7: 0.0125 | S7: =T6+0.01 -> 5000.01 | T7: 10000 | U7: 15
B8: dt_nomcon | C8: Nombre Contador | D8: ESPINOZA TOALOMBO WILMER OLMEDO | G8: <== modificar por sus datos | K8: S | N8: =O7+0.01 -> 75000.01 | O8: =+O7+25000 -> 100000 | P8: 672.5 | Q8: 0.015 | S8: =T7+0.01 -> 10000.01 | T8: 15000 | U8: 35
B9: dt_ruccon | C9: RUC del Contador | D9: 0916540586001 | G9: <== modificar por sus datos | K9: S | N9: =O8+0.01 -> 100000.01 | O9: 200000 | P9: 1047.5 | Q9: 0.0175 | S9: =T8+0.01 -> 15000.01 | T9: 20000 | U9: 60
B10: dt_est001 | C10: No. Establecimiento_1 | D10: 001 | G10: <== No. de establecimientos ACTIVO # 1 | K10: S | N10: =O9+0.01 -> 200000.01 | O10: 300000 | P10: 2797.52 | Q10: 0.02
B11: dt_est002 | C11: No. Establecimiento_2 | G11: <== No. de establecimientos ACTIVO # 2 | K11: N
B12: dt_est003 | C12: No. Establecimiento_3 | G12: <== No. de establecimientos ACTIVO # 3 | K12: N
B13: dt_est004 | C13: No. Establecimiento_4 | G13: <== No. de establecimientos ACTIVO # 4 | K13: N
B14: dt_est005 | C14: No. Establecimiento_5 | G14: <== No. de establecimientos ACTIVO # 5 | K14: N
B15: dt_est006 | C15: No. Establecimiento_6 | G15: <== No. de establecimientos ACTIVO # 6 | K15: N
B16: dt_est007 | C16: No. Establecimiento_7 | G16: <== No. de establecimientos ACTIVO # 7 | K16: N
B17: dt_est008 | C17: No. Establecimiento_8 | G17: <== No. de establecimientos ACTIVO # 8 | K17: N
B18: dt_est009 | C18: No. Establecimiento_9 | G18: <== No. de establecimientos ACTIVO # 9 | K18: N
B19: dt_est010 | C19: No. Establecimiento_10 | G19: <== No. de establecimientos ACTIVO # 10 | K19: N
B20: dt_percon | C20: Periodo Contable: | D20: 2026 | G20: <== modificar por sus datos | K20: S
B21: dt_tipdec | C21: Tipo de Declaracion Formularios | D21: MENSUAL | G21: <== modificar por sus datos | K21: S
C23: DATOS DE USUARIO EN EL SERVIDOR WEB:
B24: dt_rutserv | C24: URL Servidor Generador ATS: | D24: SERVER_3 | G24: <== NO MODIFICAR | K24: S
B25: dt_maireg | C25: Email de Registro en Sistema: | D25: acfesvalsa@gmail.com | G25: <== cambie por su email | K25: S
B26: dt_licats | C26: Licencia de Generador ATS : | D26: Y364316907 | G26: <== cambie por su clave de generador ATS | K26: S
B27: dt_licele01 | C27: Licencia Emisor FACTURAS: | G27: <== cambie por su clave para emitir FACTURAS electronicas | K27: N
B28: dt_licele03 | C28: Licencia Emisor LIQ.COMPRAS: | G28: <== cambie por su clave para emitir LIQ.COMPRAS electronicas | K28: N
B29: dt_licele07 | C29: Licencia Emisor RETENCIONES: | G29: <== cambie por su clave para emitir RETENCIONES electronicas | K29: N
C32: Configuracion y datos para Emision Documentos Electronicos
C34: INFORMACION COMPLEMENTARIA DEL CONTRIBUYENTE EMISOR:
B35: dt_nomcom | C35: Nombre Comercial | D35: GARCIA RODRIGUEZ CHARLES MILTON | G35: <== modificar por sus datos | K35: N
B36: dt_dirmat | C36: Dirección Matriz | D36: NARANJITO AV. GUAYAQUIL Y GENERAL CORDOVA | G36: <== modificar por sus datos | K36: N
B37: dt_numtel | C37: Telefonos | D37: 0990289948 | G37: <== modificar por sus datos | K37: N
B38: dt_maipri | C38: Email de Contacto Principal | D38: acfesvalespinoza@gmail.com | G38: <== modificar por sus datos | K38: N
B39: dt_tpregi | C39: Tipo de Regimen SRI | D39: GENERAL | G39: <== modificar por sus datos | K39: N
B40: dt_especi | C40: Contribuyente Especial No. | G40: <== modificar por sus datos | K40: N
B41: dt_agente | C41: Agente de Retencion No. | G41: <== modificar por sus datos | K41: N
B42: dt_oblcon | C42: Obligado a llevar Contabilidad | D42: SI | G42: <== modificar por sus datos | K42: N
B43: cf_proleg | C43: Aplica Propina Legal | D43: NO | G43: <== modificar por sus datos | K43: N
B44: cf_propor | C44: Porcentaje de Propina Legal | D44: 10 | G44: <== modificar por sus datos | K44: N
B45: cf_ivapor | C45: Porcentaje de IVA | D45: 15 | G45: <== modificar por sus datos | K45: N
B46: cf_sriamb | C46: SRI - Tipo de Ambiente | D46: 2-PRODUCCION | G46: <== modificar por sus datos | K46: N
C48: NUMERACION Y FORMATOS DE IMPRESIÓN EN DOCUMENTOS ELECTRONICOS:
B49: cf_printform | C49: Formato Impresión Contribuyente => | D49: NORMAL01a | E49: NORMAL03a | F49: NORMAL04a | G49: NORMAL05a | H49: NORMAL07a | I49: NORMAL06a | K49: N
A50: | | B50: cf_printride | C50: Formatos de Impresión RIDE ==>> | D50: RIDE01a | E50: RIDE03a | F50: RIDE04a | G50: RIDE05a | H50: RIDE07a | I50: RIDE06a | K50: N
C51: Estab-Pto.Emision / Descripcion | D51: # Factura | E51: # Liq.Compra | F51: # N/Credito | G51: # N/Debito | H51: # Retencion | I51: # Guia Remision | J51: Parametros
B52: cf_numdo0 | C52: 001-999-MATRIZ | D52: 1 | E52: 1 | F52: 1 | G52: 1 | H52: 1 | I52: 1 | J52: <dire>MANTA</dire><logo>C:\SRIanexos\Imagenes\blank.jpg</logo> | K52: N
B53: cf_numdo1 | D53: 1 | E53: 1 | F53: 1 | G53: 1 | H53: 1 | I53: 1 | K53: N
B54: cf_numdo2 | D54: 1 | E54: 1 | F54: 1 | G54: 1 | H54: 1 | I54: 1 | K54: N
B55: cf_numdo3 | D55: 1 | E55: 1 | F55: 1 | G55: 1 | H55: 1 | I55: 1 | K55: N
B56: cf_numdo4 | D56: 1 | E56: 1 | F56: 1 | G56: 1 | H56: 1 | I56: 1 | K56: N
B57: cf_numdo5 | D57: 1 | E57: 1 | F57: 1 | G57: 1 | H57: 1 | I57: 1 | K57: N
B58: cf_numdo6 | D58: 1 | E58: 1 | F58: 1 | G58: 1 | H58: 1 | I58: 1 | K58: N
B59: cf_numdo7 | D59: 1 | E59: 1 | F59: 1 | G59: 1 | H59: 1 | I59: 1 | K59: N
B60: cf_numdo8 | D60: 1 | E60: 1 | F60: 1 | G60: 1 | H60: 1 | I60: 1 | K60: N
B61: cf_numdo9 | D61: 1 | E61: 1 | F61: 1 | G61: 1 | H61: 1 | I61: 1 | K61: N
C63: CONFIGURACION DEL ENVIO DE EMAILS:
B64: cf_mailSend | C64: Enviar email al Contribuyente: | D64: SI | G64: <== modificar por su preferencia | K64: N
B65: cf_mailServ | C65: Servidor de envio de Correo | D65: MS-OUTLOOK | G65: <== modificar por su preferencia | K65: N
B66: cf_mailCopy | C66: Recibir copia de email | D66: SI | G66: <== modificar por su preferencia | K66: N
B67: cf_mailResp | C67: Email de Respuesta | D67: miemail@hotmail.com | G67: <== modificar por sus datos | K67: N
B68: cf_mailPort | C68: Puerto de Salida SMTP | D68: 587 | G68: <== modificar por sus datos (25 / 465 / 587) | K68: N
B69: cf_mailHost | C69: Nombre Host SMTP | D69: smtp.gmail.com | G69: <== modificar por sus datos | K69: N
B70: cf_mailUser | C70: Nombre de Usuario | D70: miemail@gmail.com | G70: <== modificar por sus datos | K70: N
B71: cf_mailPass | C71: Clave de Usuario | D71: miclaveEmail | G71: <== modificar por sus datos | K71: N
B72: cf_mailConn | C72: Conexion Segura SSL | D72: SI | G72: <== modificar por sus datos | K72: N
B73: cf_mailAsun | C73: <~TipoDocumento~> Electronica de <~NombreEmisor~> - No. <~NumeroDocumento~> | G73: <== NO MODIFICAR | K73: N
B74: cf_mailBody | C74: Estimad@ Cliente: <~NombreReceptor~><br> <br> Adjunto sirvase encontrar el documento electronico emitido con el siguiente detalle:<br> <~TipoDocumento~> No.: <~NumeroDocumento~><br> Fecha de Emision : <~FechaEmision~><br> <br> El documento pdf y xml de su documento se encuentra adjunto a este correo.<br> Gracias por preferirnos.<br> <br> Saludos cordiales<br> <br> <~NombreEmisor~><br> Direccion: <~DireccionEmisor~><br> Telf(s): <~TelefonoEmisor~><br> Email: <~EmailEmisor~><br> <br> NOTA: Este es un correo automatico y NO es necesario responder.<br> | K74: N
C75: CONFIGURACION DE PARAMETROS GENERALES:
B76: cf_numcan | C76: Numero de Decimales (Cantidad) | D76: 2 | G76: <== modificar por su preferencia | K76: N
B77: cf_numpre | C77: Numero de Decimales (Precio) | D77: 2 | G77: <== modificar por su preferencia | K77: N
B78: cf_impride | C78: Impresion Directa - RIDE | D78: Previsualizar | G78: <== modificar por su preferencia | K78: N
B79: cf_impform | C79: Impresion Directa - FORMULARIO | D79: NO | G79: <== modificar por su preferencia | K79: N
B80: cf_clipre | C80: Consumidor Final (Predeterminado) | D80: NO | G80: <== modificar por su preferencia | K80: N
B81: cf_savcli | C81: Guardar datos de Clientes | D81: SI | G81: <== modificar por su preferencia | K81: N
B82: cf_savpro | C82: Guardar datos de Proveedores | D82: SI | G82: <== modificar por su preferencia | K82: N
B83: cf_forcob | C83: Forma de Cobro Predeterminada | D83: 20-OTROS CON UTILIZACION DEL SISTEMA FINANCIERO | G83: <== modificar por su preferencia | K83: N
B84: cf_forpag | C84: Forma de Pago Predeterminada | D84: 20-OTROS CON UTILIZACION DEL SISTEMA FINANCIERO | G84: <== modificar por su preferencia | K84: N
K85: N
C86: DATOS DEL ARCHIVO DE FIRMA ELECTRONICA:
B87: cf_firrut | C87: Ruta firma electronica (P12): | D87: C:\SRIanexos\Electronicos\mifirma.p12 | G87: << click AQUI para cambiar >> | K87: N
B88: cf_fircla | C88: Clave de Archivo firma (P12): | D88: miclavep12 | G88: <== modificar por sus datos | K88: N
K89: N
C90: DIRECTORIOS DE ARCHIVOS EN PC LOCAL:
B91: cf_docrut | C91: Ruta Comprobantes Autorizados | D91: C:\SRIanexos\Documentos\Autorizados | G91: << click AQUI para cambiar >> | K91: N
B92: cf_savgen | C92: Guardar Archivo Generado | D92: NO | G92: <== modificar por su preferencia | K92: N
B93: cf_savfir | C93: Guardar Archivo Firmado | D93: NO | G93: <== modificar por su preferencia | K93: N
B94: cf_saverr | C94: Guardar Archivo de Error | D94: NO | G94: <== modificar por su preferencia | K94: N
C97: Numeracion de Indices para documentos y detalles (NO MODIFICAR)
C99: PARAMETROS DE CONTROL INTERNO DE HOJAS DEL SISTEMA (NO MODIFICAR)
B100: cf_version | C100: Version de Plantilla: | D100: 2024.v01 | K100: N
C101: NUMERACION DETALLE HOJAS: | D101: Ultimo Numero Secuencial | E101: Abreviacion Inicial
B102: cf_filCOM | C102: Hoja COMPRAS | D102: 1 | E102: DC | K102: N
B103: cf_filREE | C103: Hoja REEMBOLSOS | D103: 1 | E103: DR | K103: N
B104: cf_filVEN | C104: Hoja VENTAS | D104: 1 | E104: DV | K104: N
B105: cf_filEXP | C105: Hoja EXPORTACIONES | D105: 1 | E105: DE | K105: N
B106: cf_filANU | C106: Hoja ANULADOS | D106: 1 | E106: DA | K106: N
B107: cf_filGAS | C107: Hoja GASTOS | D107: 1 | E107: DG | K107: N
B108: cf_filGUI | C108: Hoja GUIAS REMISION | D108: 1 | E108: DM | K108: N
B109: cf_filDIA | C109: Hoja Diario | D109: 1 | E109: DD | K109: N
B110: cf_filTES | C110: Hoja Tesoreria | D110: 1 | E110: DT | K110: N
...

Sheet LIQ_IMPUESTOS
B1: =Parametros!D4&" - " & Parametros!D5 -> 0917809451001 - GARCIA RODRIGUEZ CHARLES MILTON | AO1: << INGRESAR VALOR >>
E2: DETALLE DE VENTAS | L2: Retenciones de IVA RECIBIDAS (Ventas) | M2: Retenciones de Impto. a la Renta RECIBIDAS (Ventas) | O2: DETALLE DE COMPRAS | W2: Retenciones de IVA EMITIDAS (Compras) | X2: Retenciones de Impto. a la Renta EMITIDAS (Compras) | Y2: Ret.100% IVA EMITIDAS (Compras) Sector Publico Informati | AA2: Factor proporcional I.V.A. | AB2: I.V.A. en compras utilizado | AC2: I.V.A. Causado x Pagar | AD2: Credito Tributario de I.V.A. por Compras en el presente mes | AE2: Credito Trib. I.V.A. del Periodo Anterior | AG2: Retenciones de IVA en Ventas del Presente Periodo | AH2: Credito Trib. I.V.A. para el mes Siguiente | AK2: Impuesto a pagar en el Periodo como Agente de Percepcion | AL2: Impuesto a pagar en el Periodo como Agente de Retencion | AM2: Total Valor a Pagar formulario 104 | AO2: Formulario 103
B3: Mes | C3: No. declaracion | E3: Base Imponible de Ventas NO Gravables + EXPORTACIONES | F3: Base Imponible de Ventas | G3: Subtotal Base Imponible en Ventas | H3: I.V.A. en ventas por REEMBOLSO | I3: I.V.A. en ventas GRAVABLES | J3: Total de IVA en Ventas | K3: Total de Ventas | O3: Base Imponible de Compras NO Gravable | P3: Base Imponible de Compras Gravable | Q3: Subtotal Base Imponible en Compras | R3: I.V.A. en compras por REEMBOLSO | S3: I.V.A. en compras por GASTO | T3: I.V.A. en compras para CREDITO TRIBUTARIO | U3: Total de IVA en Compras | V3: Total de Compras | AE3: Por Compras | AF3: Por Retenciones | AH3: Por Compras | AI3: Por Retenciones | AO3: En Relacion Dependencia (Casillero 302) | AP3: Valor Retenido (Casillero 352) | AQ3: Total Valor a Pagar
AE4: 0 | AF4: 0 | AG4: <<= Escribir CT del periodo anterior con simbolo negativo
B5: =VALUE("01/01/"&XLSperiodo) -> 46023 | C5: =IF(Parametros!D21="SEMESTRAL","I-Semestre",1) -> 1 | D5: =SUMIF(VENTAS!BE:BE,MONTH(B5),VENTAS!CA:CA) -> 0 | E5: =SUMIF(VENTAS!BE:BE,MONTH(B5),VENTAS!BJ:BJ)+SUMIF(EXPORTACIONES!AL:AL,MONTH(B5),EXPORTACIONES!AF:AF) -> 0 | F5: =SUMIF(VENTAS!BE:BE,MONTH(B5),VENTAS!P:P)+SUMIF(VENTAS!BE:BE,MONTH(B5),VENTAS!S:S)+SUMIF(VENTAS!BE:BE,MONTH(B5),VENTAS!V:V) -> 0 | G5: =E5+F5 -> 0 | H5: =ROUND(SUMIF(VENTAS!BE:BE,MONTH(B5),VENTAS!BK:BK),2) -> 0 | I5: =ROUND(SUMIF(VENTAS!BE:BE,MONTH(B5),VENTAS!BL:BL),2) -> 0 | J5: =SUM(H5:I5) -> 0 | K5: =G5+J5 -> 0 | L5: =SUMIF(VENTAS!BE:BE,MONTH(B5),VENTAS!AR:AR) -> 0 | M5: =SUMIF(VENTAS!BE:BE,MONTH(B5),VENTAS!AS:AS) -> 0 | O5: =SUMIF(COMPRAS!DB:DB,MONTH(B5),COMPRAS!DH:DH) -> 0 | P5: =SUMIF(COMPRAS!DB:DB,MONTH(B5),COMPRAS!X:X)+SUMIF(COMPRAS!DB:DB,MONTH(B5),COMPRAS!AA:AA)+SUMIF(COMPRAS!DB:DB,MONTH(B5),COMPRAS!AD:AD) -> 0 | Q5: =O5+P5 -> 0 | R5: =ROUND(SUMIF(COMPRAS!DB:DB,MONTH(B5),COMPRAS!DI:DI),2) -> 0 | S5: =ROUND(SUMIF(COMPRAS!DB:DB,MONTH(B5),COMPRAS!DJ:DJ),2) -> 0 | T5: =ROUND(SUMIF(COMPRAS!DB:DB,MONTH(B5),COMPRAS!DK:DK),2) -> 0 | U5: =SUM(R5:T5) -> 0 | V5: =Q5+U5 -> 0 | W5: =ROUND(SUMIF(COMPRAS!DB:DB,MONTH(B5),COMPRAS!DL:DL),2) -> 0 | X5: =ROUND(SUMIF(COMPRAS!DB:DB,MONTH(B5),COMPRAS!DN:DN),2) -> 0 | Y5: =ROUND(SUMIF(COMPRAS!DB:DB,MONTH(B5),COMPRAS!DM:DM),2) -> 0 | AA5: =IF(C5<>C6,IF(SUMIF(C$5:C5,C5,I$5:I5)>0,ROUND(((SUMIF(C$5:C5,C5,G$5:G5)-SUMIF(C$5:C5,C5,D$5:D5))/SUMIF(C$5:C5,C5,G$5:G5)),4),1),0) -> 1 | AB5: =IF(C5<>C6,ROUND(SUMIF(C$5:C5,C5,T$5:T5)*AA5,2),0) -> 0 | AC5: =IF(C5<>C6,IF((SUMIF(C$5:C5,C5,I$5:I5)-SUMIF(C$5:C5,C5,AB$5:AB5))>0,(SUMIF(C$5:C5,C5,I$5:I5)-SUMIF(C$5:C5,C5,AB$5:AB5)),0),0) -> 0 | AD5: =IF(C5<>C6,IF((SUMIF(C$5:C5,C5,I$5:I5)-SUMIF(C$5:C5,C5,AB$5:AB5))>0,0,(SUMIF(C$5:C5,C5,I$5:I5)-SUMIF(C$5:C5,C5,AB$5:AB5))),0) -> 0 | AE5: =IF(C5<>C6,AE4,0) -> 0 | AF5: =IF(C5<>C6,AF4,0) -> 0 | AG5: =-IF(C5<>C6,SUMIF(C$5:C5,C5,L$5:L5),0) -> 0 | AH5: =IF(C5<>C6,IF(SUM(AC5:AE5)<0,SUM(AC5:AE5),0),AE4) -> 0 | AI5: =IF(C5<>C6,IF(SUM(AC5:AE5)>0,IF(SUM(AC5:AG5)>0,0,SUM(AC5:AG5)),SUM(AF5:AG5)),AF4) -> 0 | AK5: =IF(C5<>C6,IF(SUM(AC5:AG5)>0,SUM(AC5:AG5),0),0) -> 0 | AL5: =IF(C5<>C6,SUMIF(C$5:C5,C5,W$5:W5),0) -> 0 | AM5: =AK5+AL5 -> 0 | AO5: 0 | AP5: 0 | AQ5: =AP5+X5 -> 0
B6: =VALUE("01/02/"&XLSperiodo) -> 46054 | C6: =IF(ISNUMBER(C5),C5+1,C5) -> 2 | D6: =SUMIF(VENTAS!BE:BE,MONTH(B6),VENTAS!CA:CA) -> 0 | E6: =SUMIF(VENTAS!BE:BE,MONTH(B6),VENTAS!BJ:BJ)+SUMIF(EXPORTACIONES!AL:AL,MONTH(B6),EXPORTACIONES!AF:AF) -> 0 | F6: =SUMIF(VENTAS!BE:BE,MONTH(B6),VENTAS!P:P)+SUMIF(VENTAS!BE:BE,MONTH(B6),VENTAS!S:S)+SUMIF(VENTAS!BE:BE,MONTH(B6),VENTAS!V:V) -> 0 | G6: =E6+F6 -> 0 | H6: =ROUND(SUMIF(VENTAS!BE:BE,MONTH(B6),VENTAS!BK:BK),2) -> 0 | I6: =ROUND(SUMIF(VENTAS!BE:BE,MONTH(B6),VENTAS!BL:BL),2) -> 0 | J6: =SUM(H6:I6) -> 0 | K6: =G6+J6 -> 0 | L6: =SUMIF(VENTAS!BE:BE,MONTH(B6),VENTAS!AR:AR) -> 0 | M6: =SUMIF(VENTAS!BE:BE,MONTH(B6),VENTAS!AS:AS) -> 0 | O6: =SUMIF(COMPRAS!DB:DB,MONTH(B6),COMPRAS!DH:DH) -> 0 | P6: =SUMIF(COMPRAS!DB:DB,MONTH(B6),COMPRAS!X:X)+SUMIF(COMPRAS!DB:DB,MONTH(B6),COMPRAS!AA:AA)+SUMIF(COMPRAS!DB:DB,MONTH(B6),COMPRAS!AD:AD) -> 0 | Q6: =O6+P6 -> 0 | R6: =ROUND(SUMIF(COMPRAS!DB:DB,MONTH(B6),COMPRAS!DI:DI),2) -> 0 | S6: =ROUND(SUMIF(COMPRAS!DB:DB,MONTH(B6),COMPRAS!DJ:DJ),2) -> 0 | T6: =ROUND(SUMIF(COMPRAS!DB:DB,MONTH(B6),COMPRAS!DK:DK),2) -> 0 | U6: =SUM(R6:T6) -> 0 | V6: =Q6+U6 -> 0 | W6: =ROUND(SUMIF(COMPRAS!DB:DB,MONTH(B6),COMPRAS!DL:DL),2) -> 0 | X6: =ROUND(SUMIF(COMPRAS!DB:DB,MONTH(B6),COMPRAS!DN:DN),2) -> 0 | Y6: =ROUND(SUMIF(COMPRAS!DB:DB,MONTH(B6),COMPRAS!DM:DM),2) -> 0 | AA6: =IF(C6<>C7,IF(SUMIF(C$5:C6,C6,I$5:I6)>0,ROUND(((SUMIF(C$5:C6,C6,G$5:G6)-SUMIF(C$5:C6,C6,D$5:D6))/SUMIF(C$5:C6,C6,G$5:G6)),4),1),0) -> 1 | AB6: =IF(C6<>C7,ROUND(SUMIF(C$5:C6,C6,T$5:T6)*AA6,2),0) -> 0 | AC6: =IF(C6<>C7,IF((SUMIF(C$5:C6,C6,I$5:I6)-SUMIF(C$5:C6,C6,AB$5:AB6))>0,(SUMIF(C$5:C6,C6,I$5:I6)-SUMIF(C$5:C6,C6,AB$5:AB6)),0),0) -> 0 | AD6: =IF(C6<>C7,IF((SUMIF(C$5:C6,C6,I$5:I6)-SUMIF(C$5:C6,C6,AB$5:AB6))>0,0,(SUMIF(C$5:C6,C6,I$5:I6)-SUMIF(C$5:C6,C6,AB$5:AB6))),0) -> 0 | AE6: =IF(C6<>C7,IF(AH5<0,AH5,0),0) -> 0 | AF6: =IF(C6<>C7,IF(AI5<0,AI5,0),0) -> 0 | AG6: =-IF(C6<>C7,SUMIF(C$5:C6,C6,L$5:L6),0) -> 0 | AH6: =IF(C6<>C7,IF(SUM(AC6:AE6)<0,SUM(AC6:AE6),0),AH5) -> 0 | AI6: =IF(C6<>C7,IF(SUM(AC6:AE6)>0,IF(SUM(AC6:AG6)>0,0,SUM(AC6:AG6)),SUM(AF6:AG6)),AI5) -> 0 | AK6: =IF(C6<>C7,IF(SUM(AC6:AG6)>0,SUM(AC6:AG6),0),0) -> 0 | AL6: =IF(C6<>C7,SUMIF(C$5:C6,C6,W$5:W6),0) -> 0 | AM6: =AK6+AL6 -> 0 | AO6: 0 | AP6: 0 | AQ6: =AP6+X6 -> 0
B7: =VALUE("01/03/"&XLSperiodo) -> 46082 | C7: =IF(ISNUMBER(C6),C6+1,C6) -> 3 | D7: =SUMIF(VENTAS!BE:BE,MONTH(B7),VENTAS!CA:CA) -> 0 | E7: =SUMIF(VENTAS!BE:BE,MONTH(B7),VENTAS!BJ:BJ)+SUMIF(EXPORTACIONES!AL:AL,MONTH(B7),EXPORTACIONES!AF:AF) -> 0 | F7: =SUMIF(VENTAS!BE:BE,MONTH(B7),VENTAS!P:P)+SUMIF(VENTAS!BE:BE,MONTH(B7),VENTAS!S:S)+SUMIF(VENTAS!BE:BE,MONTH(B7),VENTAS!V:V) -> 0 | G7: =E7+F7 -> 0 | H7: =ROUND(SUMIF(VENTAS!BE:BE,MONTH(B7),VENTAS!BK:BK),2) -> 0 | I7: =ROUND(SUMIF(VENTAS!BE:BE,MONTH(B7),VENTAS!BL:BL),2) -> 0 | J7: =SUM(H7:I7) -> 0 | K7: =G7+J7 -> 0 | L7: =SUMIF(VENTAS!BE:BE,MONTH(B7),VENTAS!AR:AR) -> 0 | M7: =SUMIF(VENTAS!BE:BE,MONTH(B7),VENTAS!AS:AS) -> 0 | O7: =SUMIF(COMPRAS!DB:DB,MONTH(B7),COMPRAS!DH:DH) -> 0 | P7: =SUMIF(COMPRAS!DB:DB,MONTH(B7),COMPRAS!X:X)+SUMIF(COMPRAS!DB:DB,MONTH(B7),COMPRAS!AA:AA)+SUMIF(COMPRAS!DB:DB,MONTH(B7),COMPRAS!AD:AD) -> 0 | Q7: =O7+P7 -> 0 | R7: =ROUND(SUMIF(COMPRAS!DB:DB,MONTH(B7),COMPRAS!DI:DI),2) -> 0 | S7: =ROUND(SUMIF(COMPRAS!DB:DB,MONTH(B7),COMPRAS!DJ:DJ),2) -> 0 | T7: =ROUND(SUMIF(COMPRAS!DB:DB,MONTH(B7),COMPRAS!DK:DK),2) -> 0 | U7: =SUM(R7:T7) -> 0 | V7: =Q7+U7 -> 0 | W7: =ROUND(SUMIF(COMPRAS!DB:DB,MONTH(B7),COMPRAS!DL:DL),2) -> 0 | X7: =ROUND(SUMIF(COMPRAS!DB:DB,MONTH(B7),COMPRAS!DN:DN),2) -> 0 | Y7: =ROUND(SUMIF(COMPRAS!DB:DB,MONTH(B7),COMPRAS!DM:DM),2) -> 0 | AA7: =IF(C7<>C8,IF(SUMIF(C$5:C7,C7,I$5:I7)>0,ROUND(((SUMIF(C$5:C7,C7,G$5:G7)-SUMIF(C$5:C7,C7,D$5:D7))/SUMIF(C$5:C7,C7,G$5:G7)),4),1),0) -> 1 | AB7: =IF(C7<>C8,ROUND(SUMIF(C$5:C7,C7,T$5:T7)*AA7,2),0) -> 0 | AC7: =IF(C7<>C8,IF((SUMIF(C$5:C7,C7,I$5:I7)-SUMIF(C$5:C7,C7,AB$5:AB7))>0,(SUMIF(C$5:C7,C7,I$5:I7)-SUMIF(C$5:C7,C7,AB$5:AB7)),0),0) -> 0 | AD7: =IF(C7<>C8,IF((SUMIF(C$5:C7,C7,I$5:I7)-SUMIF(C$5:C7,C7,AB$5:AB7))>0,0,(SUMIF(C$5:C7,C7,I$5:I7)-SUMIF(C$5:C7,C7,AB$5:AB7))),0) -> 0 | AE7: =IF(C7<>C8,IF(AH6<0,AH6,0),0) -> 0 | AF7: =IF(C7<>C8,IF(AI6<0,AI6,0),0) -> 0 | AG7: =-IF(C7<>C8,SUMIF(C$5:C7,C7,L$5:L7),0) -> 0 | AH7: =IF(C7<>C8,IF(SUM(AC7:AE7)<0,SUM(AC7:AE7),0),AH6) -> 0 | AI7: =IF(C7<>C8,IF(SUM(AC7:AE7)>0,IF(SUM(AC7:AG7)>0,0,SUM(AC7:AG7)),SUM(AF7:AG7)),AI6) -> 0 | AK7: =IF(C7<>C8,IF(SUM(AC7:AG7)>0,SUM(AC7:AG7),0),0) -> 0 | AL7: =IF(C7<>C8,SUMIF(C$5:C7,C7,W$5:W7),0) -> 0 | AM7: =AK7+AL7 -> 0 | AO7: 0 | AP7: 0 | AQ7: =AP7+X7 -> 0
B8: =VALUE("01/04/"&XLSperiodo) -> 46113 | C8: =IF(ISNUMBER(C7),C7+1,C7) -> 4 | D8: =SUMIF(VENTAS!BE:BE,MONTH(B8),VENTAS!CA:CA) -> 0 | E8: =SUMIF(VENTAS!BE:BE,MONTH(B8),VENTAS!BJ:BJ)+SUMIF(EXPORTACIONES!AL:AL,MONTH(B8),EXPORTACIONES!AF:AF) -> 0 | F8: =SUMIF(VENTAS!BE:BE,MONTH(B8),VENTAS!P:P)+SUMIF(VENTAS!BE:BE,MONTH(B8),VENTAS!S:S)+SUMIF(VENTAS!BE:BE,MONTH(B8),VENTAS!V:V) -> 23234.98 | G8: =E8+F8 -> 23234.98 | H8: =ROUND(SUMIF(VENTAS!BE:BE,MONTH(B8),VENTAS!BK:BK),2) -> 0 | I8: =ROUND(SUMIF(VENTAS!BE:BE,MONTH(B8),VENTAS!BL:BL),2) -> 3485.73 | J8: =SUM(H8:I8) -> 3485.73 | K8: =G8+J8 -> 26720.71 | L8: =SUMIF(VENTAS!BE:BE,MONTH(B8),VENTAS!AR:AR) -> 89.29 | M8: =SUMIF(VENTAS!BE:BE,MONTH(B8),VENTAS!AS:AS) -> 25.5 | O8: =SUMIF(COMPRAS!DB:DB,MONTH(B8),COMPRAS!DH:DH) -> 76.76 | P8: =SUMIF(COMPRAS!DB:DB,MONTH(B8),COMPRAS!X:X)+SUMIF(COMPRAS!DB:DB,MONTH(B8),COMPRAS!AA:AA)+SUMIF(COMPRAS!DB:DB,MONTH(B8),COMPRAS!AD:AD) -> 36472.82 | Q8: =O8+P8 -> 36549.58 | R8: =ROUND(SUMIF(COMPRAS!DB:DB,MONTH(B8),COMPRAS!DI:DI),2) -> 0 | S8: =ROUND(SUMIF(COMPRAS!DB:DB,MONTH(B8),COMPRAS!DJ:DJ),2) -> 0 | T8: =ROUND(SUMIF(COMPRAS!DB:DB,MONTH(B8),COMPRAS!DK:DK),2) -> 5200.72 | U8: =SUM(R8:T8) -> 5200.72 | V8: =Q8+U8 -> 41750.3 | W8: =ROUND(SUMIF(COMPRAS!DB:DB,MONTH(B8),COMPRAS!DL:DL),2) -> 1031.35 | X8: =ROUND(SUMIF(COMPRAS!DB:DB,MONTH(B8),COMPRAS!DN:DN),2) -> 353.92 | Y8: =ROUND(SUMIF(COMPRAS!DB:DB,MONTH(B8),COMPRAS!DM:DM),2) -> 0 | AA8: =IF(C8<>C9,IF(SUMIF(C$5:C8,C8,I$5:I8)>0,ROUND(((SUMIF(C$5:C8,C8,G$5:G8)-SUMIF(C$5:C8,C8,D$5:D8))/SUMIF(C$5:C8,C8,G$5:G8)),4),1),0) -> 1 | AB8: =IF(C8<>C9,ROUND(SUMIF(C$5:C8,C8,T$5:T8)*AA8,2),0) -> 5200.72 | AC8: =IF(C8<>C9,IF((SUMIF(C$5:C8,C8,I$5:I8)-SUMIF(C$5:C8,C8,AB$5:AB8))>0,(SUMIF(C$5:C8,C8,I$5:I8)-SUMIF(C$5:C8,C8,AB$5:AB8)),0),0) -> 0 | AD8: =IF(C8<>C9,IF((SUMIF(C$5:C8,C8,I$5:I8)-SUMIF(C$5:C8,C8,AB$5:AB8))>0,0,(SUMIF(C$5:C8,C8,I$5:I8)-SUMIF(C$5:C8,C8,AB$5:AB8))),0) -> -1714.99 | AE8: =IF(C8<>C9,IF(AH7<0,AH7,0),0) -> 0 | AF8: =IF(C8<>C9,IF(AI7<0,AI7,0),0) -> 0 | AG8: =-IF(C8<>C9,SUMIF(C$5:C8,C8,L$5:L8),0) -> -89.29 | AH8: =IF(C8<>C9,IF(SUM(AC8:AE8)<0,SUM(AC8:AE8),0),AH7) -> -1714.99 | AI8: =IF(C8<>C9,IF(SUM(AC8:AE8)>0,IF(SUM(AC8:AG8)>0,0,SUM(AC8:AG8)),SUM(AF8:AG8)),AI7) -> -89.29 | AK8: =IF(C8<>C9,IF(SUM(AC8:AG8)>0,SUM(AC8:AG8),0),0) -> 0 | AL8: =IF(C8<>C9,SUMIF(C$5:C8,C8,W$5:W8),0) -> 1031.35 | AM8: =AK8+AL8 -> 1031.35 | AO8: 0 | AP8: 0 | AQ8: =AP8+X8 -> 353.92
B9: =VALUE("01/05/"&XLSperiodo) -> 46143 | C9: =IF(ISNUMBER(C8),C8+1,C8) -> 5 | D9: =SUMIF(VENTAS!BE:BE,MONTH(B9),VENTAS!CA:CA) -> 0 | E9: =SUMIF(VENTAS!BE:BE,MONTH(B9),VENTAS!BJ:BJ)+SUMIF(EXPORTACIONES!AL:AL,MONTH(B9),EXPORTACIONES!AF:AF) -> 0 | F9: =SUMIF(VENTAS!BE:BE,MONTH(B9),VENTAS!P:P)+SUMIF(VENTAS!BE:BE,MONTH(B9),VENTAS!S:S)+SUMIF(VENTAS!BE:BE,MONTH(B9),VENTAS!V:V) -> 0 | G9: =E9+F9 -> 0 | H9: =ROUND(SUMIF(VENTAS!BE:BE,MONTH(B9),VENTAS!BK:BK),2) -> 0 | I9: =ROUND(SUMIF(VENTAS!BE:BE,MONTH(B9),VENTAS!BL:BL),2) -> 0 | J9: =SUM(H9:I9) -> 0 | K9: =G9+J9 -> 0 | L9: =SUMIF(VENTAS!BE:BE,MONTH(B9),VENTAS!AR:AR) -> 0 | M9: =SUMIF(VENTAS!BE:BE,MONTH(B9),VENTAS!AS:AS) -> 0 | O9: =SUMIF(COMPRAS!DB:DB,MONTH(B9),COMPRAS!DH:DH) -> 0 | P9: =SUMIF(COMPRAS!DB:DB,MONTH(B9),COMPRAS!X:X)+SUMIF(COMPRAS!DB:DB,MONTH(B9),COMPRAS!AA:AA)+SUMIF(COMPRAS!DB:DB,MONTH(B9),COMPRAS!AD:AD) -> 0 | Q9: =O9+P9 -> 0 | R9: =ROUND(SUMIF(COMPRAS!DB:DB,MONTH(B9),COMPRAS!DI:DI),2) -> 0 | S9: =ROUND(SUMIF(COMPRAS!DB:DB,MONTH(B9),COMPRAS!DJ:DJ),2) -> 0 | T9: =ROUND(SUMIF(COMPRAS!DB:DB,MONTH(B9),COMPRAS!DK:DK),2) -> 0 | U9: =SUM(R9:T9) -> 0 | V9: =Q9+U9 -> 0 | W9: =ROUND(SUMIF(COMPRAS!DB:DB,MONTH(B9),COMPRAS!DL:DL),2) -> 0 | X9: =ROUND(SUMIF(COMPRAS!DB:DB,MONTH(B9),COMPRAS!DN:DN),2) -> 0 | Y9: =ROUND(SUMIF(COMPRAS!DB:DB,MONTH(B9),COMPRAS!DM:DM),2) -> 0 | AA9: =IF(C9<>C10,IF(SUMIF(C$5:C9,C9,I$5:I9)>0,ROUND(((SUMIF(C$5:C9,C9,G$5:G9)-SUMIF(C$5:C9,C9,D$5:D9))/SUMIF(C$5:C9,C9,G$5:G9)),4),1),0) -> 1 | AB9: =IF(C9<>C10,ROUND(SUMIF(C$5:C9,C9,T$5:T9)*AA9,2),0) -> 0 | AC9: =IF(C9<>C10,IF((SUMIF(C$5:C9,C9,I$5:I9)-SUMIF(C$5:C9,C9,AB$5:AB9))>0,(SUMIF(C$5:C9,C9,I$5:I9)-SUMIF(C$5:C9,C9,AB$5:AB9)),0),0) -> 0 | AD9: =IF(C9<>C10,IF((SUMIF(C$5:C9,C9,I$5:I9)-SUMIF(C$5:C9,C9,AB$5:AB9))>0,0,(SUMIF(C$5:C9,C9,I$5:I9)-SUMIF(C$5:C9,C9,AB$5:AB9))),0) -> 0 | AE9: =IF(C9<>C10,IF(AH8<0,AH8,0),0) -> -1714.99 | AF9: =IF(C9<>C10,IF(AI8<0,AI8,0),0) -> -89.29 | AG9: =-IF(C9<>C10,SUMIF(C$5:C9,C9,L$5:L9),0) -> 0 | AH9: =IF(C9<>C10,IF(SUM(AC9:AE9)<0,SUM(AC9:AE9),0),AH8) -> -1714.99 | AI9: =IF(C9<>C10,IF(SUM(AC9:AE9)>0,IF(SUM(AC9:AG9)>0,0,SUM(AC9:AG9)),SUM(AF9:AG9)),AI8) -> -89.29 | AK9: =IF(C9<>C10,IF(SUM(AC9:AG9)>0,SUM(AC9:AG9),0),0) -> 0 | AL9: =IF(C9<>C10,SUMIF(C$5:C9,C9,W$5:W9),0) -> 0 | AM9: =AK9+AL9 -> 0 | AO9: 0 | AP9: 0 | AQ9: =AP9+X9 -> 0
B10: =VALUE("01/06/"&XLSperiodo) -> 46174 | C10: =IF(ISNUMBER(C9),C9+1,C9) -> 6 | D10: =SUMIF(VENTAS!BE:BE,MONTH(B10),VENTAS!CA:CA) -> 0 | E10: =SUMIF(VENTAS!BE:BE,MONTH(B10),VENTAS!BJ:BJ)+SUMIF(EXPORTACIONES!AL:AL,MONTH(B10),EXPORTACIONES!AF:AF) -> 0 | F10: =SUMIF(VENTAS!BE:BE,MONTH(B10),VENTAS!P:P)+SUMIF(VENTAS!BE:BE,MONTH(B10),VENTAS!S:S)+SUMIF(VENTAS!BE:BE,MONTH(B10),VENTAS!V:V) -> 0 | G10: =E10+F10 -> 0 | H10: =ROUND(SUMIF(VENTAS!BE:BE,MONTH(B10),VENTAS!BK:BK),2) -> 0 | I10: =ROUND(SUMIF(VENTAS!BE:BE,MONTH(B10),VENTAS!BL:BL),2) -> 0 | J10: =SUM(H10:I10) -> 0 | K10: =G10+J10 -> 0 | L10: =SUMIF(VENTAS!BE:BE,MONTH(B10),VENTAS!AR:AR) -> 0 | M10: =SUMIF(VENTAS!BE:BE,MONTH(B10),VENTAS!AS:AS) -> 0 | O10: =SUMIF(COMPRAS!DB:DB,MONTH(B10),COMPRAS!DH:DH) -> 0 | P10: =SUMIF(COMPRAS!DB:DB,MONTH(B10),COMPRAS!X:X)+SUMIF(COMPRAS!DB:DB,MONTH(B10),COMPRAS!AA:AA)+SUMIF(COMPRAS!DB:DB,MONTH(B10),COMPRAS!AD:AD) -> 0 | Q10: =O10+P10 -> 0 | R10: =ROUND(SUMIF(COMPRAS!DB:DB,MONTH(B10),COMPRAS!DI:DI),2) -> 0 | S10: =ROUND(SUMIF(COMPRAS!DB:DB,MONTH(B10),COMPRAS!DJ:DJ),2) -> 0 | T10: =ROUND(SUMIF(COMPRAS!DB:DB,MONTH(B10),COMPRAS!DK:DK),2) -> 0 | U10: =SUM(R10:T10) -> 0 | V10: =Q10+U10 -> 0 | W10: =ROUND(SUMIF(COMPRAS!DB:DB,MONTH(B10),COMPRAS!DL:DL),2) -> 0 | X10: =ROUND(SUMIF(COMPRAS!DB:DB,MONTH(B10),COMPRAS!DN:DN),2) -> 0 | Y10: =ROUND(SUMIF(COMPRAS!DB:DB,MONTH(B10),COMPRAS!DM:DM),2) -> 0 | AA10: =IF(C10<>C11,IF(SUMIF(C$5:C10,C10,I$5:I10)>0,ROUND(((SUMIF(C$5:C10,C10,G$5:G10)-SUMIF(C$5:C10,C10,D$5:D10))/SUMIF(C$5:C10,C10,G$5:G10)),4),1),0) -> 1 | AB10: =IF(C10<>C11,ROUND(SUMIF(C$5:C10,C10,T$5:T10)*AA10,2),0) -> 0 | AC10: =IF(C10<>C11,IF((SUMIF(C$5:C10,C10,I$5:I10)-SUMIF(C$5:C10,C10,AB$5:AB10))>0,(SUMIF(C$5:C10,C10,I$5:I10)-SUMIF(C$5:C10,C10,AB$5:AB10)),0),0) -> 0 | AD10: =IF(C10<>C11,IF((SUMIF(C$5:C10,C10,I$5:I10)-SUMIF(C$5:C10,C10,AB$5:AB10))>0,0,(SUMIF(C$5:C10,C10,I$5:I10)-SUMIF(C$5:C10,C10,AB$5:AB10))),0) -> 0 | AE10: =IF(C10<>C11,IF(AH9<0,AH9,0),0) -> -1714.99 | AF10: =IF(C10<>C11,IF(AI9<0,AI9,0),0) -> -89.29 | AG10: =-IF(C10<>C11,SUMIF(C$5:C10,C10,L$5:L10),0) -> 0 | AH10: =IF(C10<>C11,IF(SUM(AC10:AE10)<0,SUM(AC10:AE10),0),AH9) -> -1714.99 | AI10: =IF(C10<>C11,IF(SUM(AC10:AE10)>0,IF(SUM(AC10:AG10)>0,0,SUM(AC10:AG10)),SUM(AF10:AG10)),AI9) -> -89.29 | AK10: =IF(C10<>C11,IF(SUM(AC10:AG10)>0,SUM(AC10:AG10),0),0) -> 0 | AL10: =IF(C10<>C11,SUMIF(C$5:C10,C10,W$5:W10),0) -> 0 | AM10: =AK10+AL10 -> 0 | AO10: 0 | AP10: 0 | AQ10: =AP10+X10 -> 0
B11: =VALUE("01/07/"&XLSperiodo) -> 46204 | C11: =IF(Parametros!D21="SEMESTRAL","II-Semestre",7) -> 7 | D11: =SUMIF(VENTAS!BE:BE,MONTH(B11),VENTAS!CA:CA) -> 0 | E11: =SUMIF(VENTAS!BE:BE,MONTH(B11),VENTAS!BJ:BJ)+SUMIF(EXPORTACIONES!AL:AL,MONTH(B11),EXPORTACIONES!AF:AF) -> 0 | F11: =SUMIF(VENTAS!BE:BE,MONTH(B11),VENTAS!P:P)+SUMIF(VENTAS!BE:BE,MONTH(B11),VENTAS!S:S)+SUMIF(VENTAS!BE:BE,MONTH(B11),VENTAS!V:V) -> 0 | G11: =E11+F11 -> 0 | H11: =ROUND(SUMIF(VENTAS!BE:BE,MONTH(B11),VENTAS!BK:BK),2) -> 0 | I11: =ROUND(SUMIF(VENTAS!BE:BE,MONTH(B11),VENTAS!BL:BL),2) -> 0 | J11: =SUM(H11:I11) -> 0 | K11: =G11+J11 -> 0 | L11: =SUMIF(VENTAS!BE:BE,MONTH(B11),VENTAS!AR:AR) -> 0 | M11: =SUMIF(VENTAS!BE:BE,MONTH(B11),VENTAS!AS:AS) -> 0 | O11: =SUMIF(COMPRAS!DB:DB,MONTH(B11),COMPRAS!DH:DH) -> 0 | P11: =SUMIF(COMPRAS!DB:DB,MONTH(B11),COMPRAS!X:X)+SUMIF(COMPRAS!DB:DB,MONTH(B11),COMPRAS!AA:AA)+SUMIF(COMPRAS!DB:DB,MONTH(B11),COMPRAS!AD:AD) -> 0 | Q11: =O11+P11 -> 0 | R11: =ROUND(SUMIF(COMPRAS!DB:DB,MONTH(B11),COMPRAS!DI:DI),2) -> 0 | S11: =ROUND(SUMIF(COMPRAS!DB:DB,MONTH(B11),COMPRAS!DJ:DJ),2) -> 0 | T11: =ROUND(SUMIF(COMPRAS!DB:DB,MONTH(B11),COMPRAS!DK:DK),2) -> 0 | U11: =SUM(R11:T11) -> 0 | V11: =Q11+U11 -> 0 | W11: =ROUND(SUMIF(COMPRAS!DB:DB,MONTH(B11),COMPRAS!DL:DL),2) -> 0 | X11: =ROUND(SUMIF(COMPRAS!DB:DB,MONTH(B11),COMPRAS!DN:DN),2) -> 0 | Y11: =ROUND(SUMIF(COMPRAS!DB:DB,MONTH(B11),COMPRAS!DM:DM),2) -> 0 | AA11: =IF(C11<>C12,IF(SUMIF(C$5:C11,C11,I$5:I11)>0,ROUND(((SUMIF(C$5:C11,C11,G$5:G11)-SUMIF(C$5:C11,C11,D$5:D11))/SUMIF(C$5:C11,C11,G$5:G11)),4),1),0) -> 1 | AB11: =IF(C11<>C12,ROUND(SUMIF(C$5:C11,C11,T$5:T11)*AA11,2),0) -> 0 | AC11: =IF(C11<>C12,IF((SUMIF(C$5:C11,C11,I$5:I11)-SUMIF(C$5:C11,C11,AB$5:AB11))>0,(SUMIF(C$5:C11,C11,I$5:I11)-SUMIF(C$5:C11,C11,AB$5:AB11)),0),0) -> 0 | AD11: =IF(C11<>C12,IF((SUMIF(C$5:C11,C11,I$5:I11)-SUMIF(C$5:C11,C11,AB$5:AB11))>0,0,(SUMIF(C$5:C11,C11,I$5:I11)-SUMIF(C$5:C11,C11,AB$5:AB11))),0) -> 0 | AE11: =IF(C11<>C12,IF(AH10<0,AH10,0),0) -> -1714.99 | AF11: =IF(C11<>C12,IF(AI10<0,AI10,0),0) -> -89.29 | AG11: =-IF(C11<>C12,SUMIF(C$5:C11,C11,L$5:L11),0) -> 0 | AH11: =IF(C11<>C12,IF(SUM(AC11:AE11)<0,SUM(AC11:AE11),0),AH10) -> -1714.99 | AI11: =IF(C11<>C12,IF(SUM(AC11:AE11)>0,IF(SUM(AC11:AG11)>0,0,SUM(AC11:AG11)),SUM(AF11:AG11)),AI10) -> -89.29 | AK11: =IF(C11<>C12,IF(SUM(AC11:AG11)>0,SUM(AC11:AG11),0),0) -> 0 | AL11: =IF(C11<>C12,SUMIF(C$5:C11,C11,W$5:W11),0) -> 0 | AM11: =AK11+AL11 -> 0 | AO11: 0 | AP11: 0 | AQ11: =AP11+X11 -> 0
B12: =VALUE("01/08/"&XLSperiodo) -> 46235 | C12: =IF(ISNUMBER(C11),C11+1,C11) -> 8 | D12: =SUMIF(VENTAS!BE:BE,MONTH(B12),VENTAS!CA:CA) -> 0 | E12: =SUMIF(VENTAS!BE:BE,MONTH(B12),VENTAS!BJ:BJ)+SUMIF(EXPORTACIONES!AL:AL,MONTH(B12),EXPORTACIONES!AF:AF) -> 0 | F12: =SUMIF(VENTAS!BE:BE,MONTH(B12),VENTAS!P:P)+SUMIF(VENTAS!BE:BE,MONTH(B12),VENTAS!S:S)+SUMIF(VENTAS!BE:BE,MONTH(B12),VENTAS!V:V) -> 0 | G12: =E12+F12 -> 0 | H12: =ROUND(SUMIF(VENTAS!BE:BE,MONTH(B12),VENTAS!BK:BK),2) -> 0 | I12: =ROUND(SUMIF(VENTAS!BE:BE,MONTH(B12),VENTAS!BL:BL),2) -> 0 | J12: =SUM(H12:I12) -> 0 | K12: =G12+J12 -> 0 | L12: =SUMIF(VENTAS!BE:BE,MONTH(B12),VENTAS!AR:AR) -> 0 | M12: =SUMIF(VENTAS!BE:BE,MONTH(B12),VENTAS!AS:AS) -> 0 | O12: =SUMIF(COMPRAS!DB:DB,MONTH(B12),COMPRAS!DH:DH) -> 0 | P12: =SUMIF(COMPRAS!DB:DB,MONTH(B12),COMPRAS!X:X)+SUMIF(COMPRAS!DB:DB,MONTH(B12),COMPRAS!AA:AA)+SUMIF(COMPRAS!DB:DB,MONTH(B12),COMPRAS!AD:AD) -> 0 | Q12: =O12+P12 -> 0 | R12: =ROUND(SUMIF(COMPRAS!DB:DB,MONTH(B12),COMPRAS!DI:DI),2) -> 0 | S12: =ROUND(SUMIF(COMPRAS!DB:DB,MONTH(B12),COMPRAS!DJ:DJ),2) -> 0 | T12: =ROUND(SUMIF(COMPRAS!DB:DB,MONTH(B12),COMPRAS!DK:DK),2) -> 0 | U12: =SUM(R12:T12) -> 0 | V12: =Q12+U12 -> 0 | W12: =ROUND(SUMIF(COMPRAS!DB:DB,MONTH(B12),COMPRAS!DL:DL),2) -> 0 | X12: =ROUND(SUMIF(COMPRAS!DB:DB,MONTH(B12),COMPRAS!DN:DN),2) -> 0 | Y12: =ROUND(SUMIF(COMPRAS!DB:DB,MONTH(B12),COMPRAS!DM:DM),2) -> 0 | AA12: =IF(C12<>C13,IF(SUMIF(C$5:C12,C12,I$5:I12)>0,ROUND(((SUMIF(C$5:C12,C12,G$5:G12)-SUMIF(C$5:C12,C12,D$5:D12))/SUMIF(C$5:C12,C12,G$5:G12)),4),1),0) -> 1 | AB12: =IF(C12<>C13,ROUND(SUMIF(C$5:C12,C12,T$5:T12)*AA12,2),0) -> 0 | AC12: =IF(C12<>C13,IF((SUMIF(C$5:C12,C12,I$5:I12)-SUMIF(C$5:C12,C12,AB$5:AB12))>0,(SUMIF(C$5:C12,C12,I$5:I12)-SUMIF(C$5:C12,C12,AB$5:AB12)),0),0) -> 0 | AD12: =IF(C12<>C13,IF((SUMIF(C$5:C12,C12,I$5:I12)-SUMIF(C$5:C12,C12,AB$5:AB12))>0,0,(SUMIF(C$5:C12,C12,I$5:I12)-SUMIF(C$5:C12,C12,AB$5:AB12))),0) -> 0 | AE12: =IF(C12<>C13,IF(AH11<0,AH11,0),0) -> -1714.99 | AF12: =IF(C12<>C13,IF(AI11<0,AI11,0),0) -> -89.29 | AG12: =-IF(C12<>C13,SUMIF(C$5:C12,C12,L$5:L12),0) -> 0 | AH12: =IF(C12<>C13,IF(SUM(AC12:AE12)<0,SUM(AC12:AE12),0),AH11) -> -1714.99 | AI12: =IF(C12<>C13,IF(SUM(AC12:AE12)>0,IF(SUM(AC12:AG12)>0,0,SUM(AC12:AG12)),SUM(AF12:AG12)),AI11) -> -89.29 | AK12: =IF(C12<>C13,IF(SUM(AC12:AG12)>0,SUM(AC12:AG12),0),0) -> 0 | AL12: =IF(C12<>C13,SUMIF(C$5:C12,C12,W$5:W12),0) -> 0 | AM12: =AK12+AL12 -> 0 | AO12: 0 | AP12: 0 | AQ12: =AP12+X12 -> 0
B13: =VALUE("01/09/"&XLSperiodo) -> 46266 | C13: =IF(ISNUMBER(C12),C12+1,C12) -> 9 | D13: =SUMIF(VENTAS!BE:BE,MONTH(B13),VENTAS!CA:CA) -> 0 | E13: =SUMIF(VENTAS!BE:BE,MONTH(B13),VENTAS!BJ:BJ)+SUMIF(EXPORTACIONES!AL:AL,MONTH(B13),EXPORTACIONES!AF:AF) -> 0 | F13: =SUMIF(VENTAS!BE:BE,MONTH(B13),VENTAS!P:P)+SUMIF(VENTAS!BE:BE,MONTH(B13),VENTAS!S:S)+SUMIF(VENTAS!BE:BE,MONTH(B13),VENTAS!V:V) -> 0 | G13: =E13+F13 -> 0 | H13: =ROUND(SUMIF(VENTAS!BE:BE,MONTH(B13),VENTAS!BK:BK),2) -> 0 | I13: =ROUND(SUMIF(VENTAS!BE:BE,MONTH(B13),VENTAS!BL:BL),2) -> 0 | J13: =SUM(H13:I13) -> 0 | K13: =G13+J13 -> 0 | L13: =SUMIF(VENTAS!BE:BE,MONTH(B13),VENTAS!AR:AR) -> 0 | M13: =SUMIF(VENTAS!BE:BE,MONTH(B13),VENTAS!AS:AS) -> 0 | O13: =SUMIF(COMPRAS!DB:DB,MONTH(B13),COMPRAS!DH:DH) -> 0 | P13: =SUMIF(COMPRAS!DB:DB,MONTH(B13),COMPRAS!X:X)+SUMIF(COMPRAS!DB:DB,MONTH(B13),COMPRAS!AA:AA)+SUMIF(COMPRAS!DB:DB,MONTH(B13),COMPRAS!AD:AD) -> 0 | Q13: =O13+P13 -> 0 | R13: =ROUND(SUMIF(COMPRAS!DB:DB,MONTH(B13),COMPRAS!DI:DI),2) -> 0 | S13: =ROUND(SUMIF(COMPRAS!DB:DB,MONTH(B13),COMPRAS!DJ:DJ),2) -> 0 | T13: =ROUND(SUMIF(COMPRAS!DB:DB,MONTH(B13),COMPRAS!DK:DK),2) -> 0 | U13: =SUM(R13:T13) -> 0 | V13: =Q13+U13 -> 0 | W13: =ROUND(SUMIF(COMPRAS!DB:DB,MONTH(B13),COMPRAS!DL:DL),2) -> 0 | X13: =ROUND(SUMIF(COMPRAS!DB:DB,MONTH(B13),COMPRAS!DN:DN),2) -> 0 | Y13: =ROUND(SUMIF(COMPRAS!DB:DB,MONTH(B13),COMPRAS!DM:DM),2) -> 0 | AA13: =IF(C13<>C14,IF(SUMIF(C$5:C13,C13,I$5:I13)>0,ROUND(((SUMIF(C$5:C13,C13,G$5:G13)-SUMIF(C$5:C13,C13,D$5:D13))/SUMIF(C$5:C13,C13,G$5:G13)),4),1),0) -> 1 | AB13: =IF(C13<>C14,ROUND(SUMIF(C$5:C13,C13,T$5:T13)*AA13,2),0) -> 0 | AC13: =IF(C13<>C14,IF((SUMIF(C$5:C13,C13,I$5:I13)-SUMIF(C$5:C13,C13,AB$5:AB13))>0,(SUMIF(C$5:C13,C13,I$5:I13)-SUMIF(C$5:C13,C13,AB$5:AB13)),0),0) -> 0 | AD13: =IF(C13<>C14,IF((SUMIF(C$5:C13,C13,I$5:I13)-SUMIF(C$5:C13,C13,AB$5:AB13))>0,0,(SUMIF(C$5:C13,C13,I$5:I13)-SUMIF(C$5:C13,C13,AB$5:AB13))),0) -> 0 | AE13: =IF(C13<>C14,IF(AH12<0,AH12,0),0) -> -1714.99 | AF13: =IF(C13<>C14,IF(AI12<0,AI12,0),0) -> -89.29 | AG13: =-IF(C13<>C14,SUMIF(C$5:C13,C13,L$5:L13),0) -> 0 | AH13: =IF(C13<>C14,IF(SUM(AC13:AE13)<0,SUM(AC13:AE13),0),AH12) -> -1714.99 | AI13: =IF(C13<>C14,IF(SUM(AC13:AE13)>0,IF(SUM(AC13:AG13)>0,0,SUM(AC13:AG13)),SUM(AF13:AG13)),AI12) -> -89.29 | AK13: =IF(C13<>C14,IF(SUM(AC13:AG13)>0,SUM(AC13:AG13),0),0) -> 0 | AL13: =IF(C13<>C14,SUMIF(C$5:C13,C13,W$5:W13),0) -> 0 | AM13: =AK13+AL13 -> 0 | AO13: 0 | AP13: 0 | AQ13: =AP13+X13 -> 0
B14: =VALUE("01/10/"&XLSperiodo) -> 46296 | C14: =IF(ISNUMBER(C13),C13+1,C13) -> 10 | D14: =SUMIF(VENTAS!BE:BE,MONTH(B14),VENTAS!CA:CA) -> 0 | E14: =SUMIF(VENTAS!BE:BE,MONTH(B14),VENTAS!BJ:BJ)+SUMIF(EXPORTACIONES!AL:AL,MONTH(B14),EXPORTACIONES!AF:AF) -> 0 | F14: =SUMIF(VENTAS!BE:BE,MONTH(B14),VENTAS!P:P)+SUMIF(VENTAS!BE:BE,MONTH(B14),VENTAS!S:S)+SUMIF(VENTAS!BE:BE,MONTH(B14),VENTAS!V:V) -> 0 | G14: =E14+F14 -> 0 | H14: =ROUND(SUMIF(VENTAS!BE:BE,MONTH(B14),VENTAS!BK:BK),2) -> 0 | I14: =ROUND(SUMIF(VENTAS!BE:BE,MONTH(B14),VENTAS!BL:BL),2) -> 0 | J14: =SUM(H14:I14) -> 0 | K14: =G14+J14 -> 0 | L14: =SUMIF(VENTAS!BE:BE,MONTH(B14),VENTAS!AR:AR) -> 0 | M14: =SUMIF(VENTAS!BE:BE,MONTH(B14),VENTAS!AS:AS) -> 0 | O14: =SUMIF(COMPRAS!DB:DB,MONTH(B14),COMPRAS!DH:DH) -> 0 | P14: =SUMIF(COMPRAS!DB:DB,MONTH(B14),COMPRAS!X:X)+SUMIF(COMPRAS!DB:DB,MONTH(B14),COMPRAS!AA:AA)+SUMIF(COMPRAS!DB:DB,MONTH(B14),COMPRAS!AD:AD) -> 0 | Q14: =O14+P14 -> 0 | R14: =ROUND(SUMIF(COMPRAS!DB:DB,MONTH(B14),COMPRAS!DI:DI),2) -> 0 | S14: =ROUND(SUMIF(COMPRAS!DB:DB,MONTH(B14),COMPRAS!DJ:DJ),2) -> 0 | T14: =ROUND(SUMIF(COMPRAS!DB:DB,MONTH(B14),COMPRAS!DK:DK),2) -> 0 | U14: =SUM(R14:T14) -> 0 | V14: =Q14+U14 -> 0 | W14: =ROUND(SUMIF(COMPRAS!DB:DB,MONTH(B14),COMPRAS!DL:DL),2) -> 0 | X14: =ROUND(SUMIF(COMPRAS!DB:DB,MONTH(B14),COMPRAS!DN:DN),2) -> 0 | Y14: =ROUND(SUMIF(COMPRAS!DB:DB,MONTH(B14),COMPRAS!DM:DM),2) -> 0 | AA14: =IF(C14<>C15,IF(SUMIF(C$5:C14,C14,I$5:I14)>0,ROUND(((SUMIF(C$5:C14,C14,G$5:G14)-SUMIF(C$5:C14,C14,D$5:D14))/SUMIF(C$5:C14,C14,G$5:G14)),4),1),0) -> 1 | AB14: =IF(C14<>C15,ROUND(SUMIF(C$5:C14,C14,T$5:T14)*AA14,2),0) -> 0 | AC14: =IF(C14<>C15,IF((SUMIF(C$5:C14,C14,I$5:I14)-SUMIF(C$5:C14,C14,AB$5:AB14))>0,(SUMIF(C$5:C14,C14,I$5:I14)-SUMIF(C$5:C14,C14,AB$5:AB14)),0),0) -> 0 | AD14: =IF(C14<>C15,IF((SUMIF(C$5:C14,C14,I$5:I14)-SUMIF(C$5:C14,C14,AB$5:AB14))>0,0,(SUMIF(C$5:C14,C14,I$5:I14)-SUMIF(C$5:C14,C14,AB$5:AB14))),0) -> 0 | AE14: =IF(C14<>C15,IF(AH13<0,AH13,0),0) -> -1714.99 | AF14: =IF(C14<>C15,IF(AI13<0,AI13,0),0) -> -89.29 | AG14: =-IF(C14<>C15,SUMIF(C$5:C14,C14,L$5:L14),0) -> 0 | AH14: =IF(C14<>C15,IF(SUM(AC14:AE14)<0,SUM(AC14:AE14),0),AH13) -> -1714.99 | AI14: =IF(C14<>C15,IF(SUM(AC14:AE14)>0,IF(SUM(AC14:AG14)>0,0,SUM(AC14:AG14)),SUM(AF14:AG14)),AI13) -> -89.29 | AK14: =IF(C14<>C15,IF(SUM(AC14:AG14)>0,SUM(AC14:AG14),0),0) -> 0 | AL14: =IF(C14<>C15,SUMIF(C$5:C14,C14,W$5:W14),0) -> 0 | AM14: =AK14+AL14 -> 0 | AO14: 0 | AP14: 0 | AQ14: =AP14+X14 -> 0
B15: =VALUE("01/11/"&XLSperiodo) -> 46327 | C15: =IF(ISNUMBER(C14),C14+1,C14) -> 11 | D15: =SUMIF(VENTAS!BE:BE,MONTH(B15),VENTAS!CA:CA) -> 0 | E15: =SUMIF(VENTAS!BE:BE,MONTH(B15),VENTAS!BJ:BJ)+SUMIF(EXPORTACIONES!AL:AL,MONTH(B15),EXPORTACIONES!AF:AF) -> 0 | F15: =SUMIF(VENTAS!BE:BE,MONTH(B15),VENTAS!P:P)+SUMIF(VENTAS!BE:BE,MONTH(B15),VENTAS!S:S)+SUMIF(VENTAS!BE:BE,MONTH(B15),VENTAS!V:V) -> 0 | G15: =E15+F15 -> 0 | H15: =ROUND(SUMIF(VENTAS!BE:BE,MONTH(B15),VENTAS!BK:BK),2) -> 0 | I15: =ROUND(SUMIF(VENTAS!BE:BE,MONTH(B15),VENTAS!BL:BL),2) -> 0 | J15: =SUM(H15:I15) -> 0 | K15: =G15+J15 -> 0 | L15: =SUMIF(VENTAS!BE:BE,MONTH(B15),VENTAS!AR:AR) -> 0 | M15: =SUMIF(VENTAS!BE:BE,MONTH(B15),VENTAS!AS:AS) -> 0 | O15: =SUMIF(COMPRAS!DB:DB,MONTH(B15),COMPRAS!DH:DH) -> 0 | P15: =SUMIF(COMPRAS!DB:DB,MONTH(B15),COMPRAS!X:X)+SUMIF(COMPRAS!DB:DB,MONTH(B15),COMPRAS!AA:AA)+SUMIF(COMPRAS!DB:DB,MONTH(B15),COMPRAS!AD:AD) -> 0 | Q15: =O15+P15 -> 0 | R15: =ROUND(SUMIF(COMPRAS!DB:DB,MONTH(B15),COMPRAS!DI:DI),2) -> 0 | S15: =ROUND(SUMIF(COMPRAS!DB:DB,MONTH(B15),COMPRAS!DJ:DJ),2) -> 0 | T15: =ROUND(SUMIF(COMPRAS!DB:DB,MONTH(B15),COMPRAS!DK:DK),2) -> 0 | U15: =SUM(R15:T15) -> 0 | V15: =Q15+U15 -> 0 | W15: =ROUND(SUMIF(COMPRAS!DB:DB,MONTH(B15),COMPRAS!DL:DL),2) -> 0 | X15: =ROUND(SUMIF(COMPRAS!DB:DB,MONTH(B15),COMPRAS!DN:DN),2) -> 0 | Y15: =ROUND(SUMIF(COMPRAS!DB:DB,MONTH(B15),COMPRAS!DM:DM),2) -> 0 | AA15: =IF(C15<>C16,IF(SUMIF(C$5:C15,C15,I$5:I15)>0,ROUND(((SUMIF(C$5:C15,C15,G$5:G15)-SUMIF(C$5:C15,C15,D$5:D15))/SUMIF(C$5:C15,C15,G$5:G15)),4),1),0) -> 1 | AB15: =IF(C15<>C16,ROUND(SUMIF(C$5:C15,C15,T$5:T15)*AA15,2),0) -> 0 | AC15: =IF(C15<>C16,IF((SUMIF(C$5:C15,C15,I$5:I15)-SUMIF(C$5:C15,C15,AB$5:AB15))>0,(SUMIF(C$5:C15,C15,I$5:I15)-SUMIF(C$5:C15,C15,AB$5:AB15)),0),0) -> 0 | AD15: =IF(C15<>C16,IF((SUMIF(C$5:C15,C15,I$5:I15)-SUMIF(C$5:C15,C15,AB$5:AB15))>0,0,(SUMIF(C$5:C15,C15,I$5:I15)-SUMIF(C$5:C15,C15,AB$5:AB15))),0) -> 0 | AE15: =IF(C15<>C16,IF(AH14<0,AH14,0),0) -> -1714.99 | AF15: =IF(C15<>C16,IF(AI14<0,AI14,0),0) -> -89.29 | AG15: =-IF(C15<>C16,SUMIF(C$5:C15,C15,L$5:L15),0) -> 0 | AH15: =IF(C15<>C16,IF(SUM(AC15:AE15)<0,SUM(AC15:AE15),0),AH14) -> -1714.99 | AI15: =IF(C15<>C16,IF(SUM(AC15:AE15)>0,IF(SUM(AC15:AG15)>0,0,SUM(AC15:AG15)),SUM(AF15:AG15)),AI14) -> -89.29 | AK15: =IF(C15<>C16,IF(SUM(AC15:AG15)>0,SUM(AC15:AG15),0),0) -> 0 | AL15: =IF(C15<>C16,SUMIF(C$5:C15,C15,W$5:W15),0) -> 0 | AM15: =AK15+AL15 -> 0 | AO15: 0 | AP15: 0 | AQ15: =AP15+X15 -> 0
B16: =VALUE("01/12/"&XLSperiodo) -> 46357 | C16: =IF(ISNUMBER(C15),C15+1,C15) -> 12 | D16: =SUMIF(VENTAS!BE:BE,MONTH(B16),VENTAS!CA:CA) -> 0 | E16: =SUMIF(VENTAS!BE:BE,MONTH(B16),VENTAS!BJ:BJ)+SUMIF(EXPORTACIONES!AL:AL,MONTH(B16),EXPORTACIONES!AF:AF) -> 0 | F16: =SUMIF(VENTAS!BE:BE,MONTH(B16),VENTAS!P:P)+SUMIF(VENTAS!BE:BE,MONTH(B16),VENTAS!S:S)+SUMIF(VENTAS!BE:BE,MONTH(B16),VENTAS!V:V) -> 0 | G16: =E16+F16 -> 0 | H16: =ROUND(SUMIF(VENTAS!BE:BE,MONTH(B16),VENTAS!BK:BK),2) -> 0 | I16: =ROUND(SUMIF(VENTAS!BE:BE,MONTH(B16),VENTAS!BL:BL),2) -> 0 | J16: =SUM(H16:I16) -> 0 | K16: =G16+J16 -> 0 | L16: =SUMIF(VENTAS!BE:BE,MONTH(B16),VENTAS!AR:AR) -> 0 | M16: =SUMIF(VENTAS!BE:BE,MONTH(B16),VENTAS!AS:AS) -> 0 | O16: =SUMIF(COMPRAS!DB:DB,MONTH(B16),COMPRAS!DH:DH) -> 0 | P16: =SUMIF(COMPRAS!DB:DB,MONTH(B16),COMPRAS!X:X)+SUMIF(COMPRAS!DB:DB,MONTH(B16),COMPRAS!AA:AA)+SUMIF(COMPRAS!DB:DB,MONTH(B16),COMPRAS!AD:AD) -> 0 | Q16: =O16+P16 -> 0 | R16: =ROUND(SUMIF(COMPRAS!DB:DB,MONTH(B16),COMPRAS!DI:DI),2) -> 0 | S16: =ROUND(SUMIF(COMPRAS!DB:DB,MONTH(B16),COMPRAS!DJ:DJ),2) -> 0 | T16: =ROUND(SUMIF(COMPRAS!DB:DB,MONTH(B16),COMPRAS!DK:DK),2) -> 0 | U16: =SUM(R16:T16) -> 0 | V16: =Q16+U16 -> 0 | W16: =ROUND(SUMIF(COMPRAS!DB:DB,MONTH(B16),COMPRAS!DL:DL),2) -> 0 | X16: =ROUND(SUMIF(COMPRAS!DB:DB,MONTH(B16),COMPRAS!DN:DN),2) -> 0 | Y16: =ROUND(SUMIF(COMPRAS!DB:DB,MONTH(B16),COMPRAS!DM:DM),2) -> 0 | AA16: =IF(C16<>C17,IF(SUMIF(C$5:C16,C16,I$5:I16)>0,ROUND(((SUMIF(C$5:C16,C16,G$5:G16)-SUMIF(C$5:C16,C16,D$5:D16))/SUMIF(C$5:C16,C16,G$5:G16)),4),1),0) -> 1 | AB16: =ROUND(SUMIF(C$5:C16,C16,T$5:T16)*AA16,2) -> 0 | AC16: =IF(C16<>C17,IF((SUMIF(C$5:C16,C16,I$5:I16)-SUMIF(C$5:C16,C16,AB$5:AB16))>0,(SUMIF(C$5:C16,C16,I$5:I16)-SUMIF(C$5:C16,C16,AB$5:AB16)),0),0) -> 0 | AD16: =IF(C16<>C17,IF((SUMIF(C$5:C16,C16,I$5:I16)-SUMIF(C$5:C16,C16,AB$5:AB16))>0,0,(SUMIF(C$5:C16,C16,I$5:I16)-SUMIF(C$5:C16,C16,AB$5:AB16))),0) -> 0 | AE16: =IF(C16<>C17,IF(AH15<0,AH15,0),0) -> -1714.99 | AF16: =IF(C16<>C17,IF(AI15<0,AI15,0),0) -> -89.29 | AG16: =-IF(C16<>C17,SUMIF(C$5:C16,C16,L$5:L16),0) -> 0 | AH16: =IF(C16<>C17,IF(SUM(AC16:AE16)<0,SUM(AC16:AE16),0),AH15) -> -1714.99 | AI16: =IF(C16<>C17,IF(SUM(AC16:AE16)>0,IF(SUM(AC16:AG16)>0,0,SUM(AC16:AG16)),SUM(AF16:AG16)),AI15) -> -89.29 | AK16: =IF(C16<>C17,IF(SUM(AC16:AG16)>0,SUM(AC16:AG16),0),0) -> 0 | AL16: =IF(C16<>C17,SUMIF(C$5:C16,C16,W$5:W16),0) -> 0 | AM16: =AK16+AL16 -> 0 | AO16: 0 | AP16: 0 | AQ16: =AP16+X16 -> 0
E18: =SUM(E5:E17) -> 0 | F18: =SUM(F5:F17) -> 23234.98 | G18: =SUM(G5:G17) -> 23234.98 | H18: =SUM(H5:H17) -> 0 | I18: =SUM(I5:I17) -> 3485.73 | J18: =SUM(J5:J17) -> 3485.73 | K18: =SUM(K5:K17) -> 26720.71 | L18: =SUM(L5:L17) -> 89.29 | M18: =SUM(M5:M17) -> 25.5 | O18: =SUM(O5:O17) -> 76.76 | P18: =SUM(P5:P17) -> 36472.82 | Q18: =SUM(Q5:Q17) -> 36549.58 | R18: =SUM(R5:R17) -> 0 | S18: =SUM(S5:S17) -> 0 | T18: =SUM(T5:T17) -> 5200.72 | U18: =SUM(U5:U17) -> 5200.72 | V18: =SUM(V5:V17) -> 41750.3 | ... Y18: =SUM(Y5:Y17) -> 0 | AB18: =SUM(AB5:AB17) -> 5200.72 | AC18: =SUM(AC5:AC17) -> 0 | AD18: =SUM(AD5:AD17) -> -1714.99 | AE18: =SUM(AE5:AE17) -> -13719.92 | AF18: =SUM(AF5:AF17) -> -714.32 | AG18: =SUM(AG5:AG17) -> -89.29 | AH18: =SUM(AH5:AH17) -> -15434.91 | AI18: =SUM(AI5:AI17) -> -803.61 | AK18: =SUM(AK5:AK17) -> 0 | AL18: =SUM(AL5:AL17) -> 1031.35 | AM18: =SUM(AM5:AM17) -> 1031.35 | AO18: =SUM(AO5:AO17) -> 0 | AP18: =SUM(AP5:AP17) -> 0 | AQ18: =SUM(AQ5:AQ17) -> 353.92
B20: TIPO DE REGIMEN:
B21: RIMPE EMPRENDEDOR
A22: =+Parametros!C139 -> RIMPE | K22: 1er SEMESTRE (ENE-JUN) | L22: 2do SEMESTRE (JUL-DIC) | M22: TOTAL ANUAL
A23: SUBTOTAL INGRESOS | K23: =SUM(K24:K26) -> 0 | L23: =SUM(L24:L26) -> 0 | M23: =SUM(M24:M26) -> 0
B24: 18-Documentos autorizados utilizados en ventas excepto N/C N/D | K24: =SUMIFS(VENTAS!$M:$M,VENTAS!$AI:$AI,$A$22,VENTAS!$H:$H,$B24,VENTAS!$BE:$BE,"<7")+SUMIFS(VENTAS!$O:$O,VENTAS!$AI:$AI,$A$22,VENTAS!$H:$H,$B24,VENTAS!$BE:$BE,"<7")+SUMIFS(VENTAS!$P:$P,VENTAS!$AI:$AI,$A$22,VENTAS!$H:$H,$B24,VENTAS!$BE:$BE,"<7")+SUMIFS(VENTAS!$S:$S,VENTAS!$AI:$AI,$A$22,VENTAS!$H:$H,$B24,VENTAS!$BE:$BE,"<7")+SUMIFS(VENTAS!$V:$V,VENTAS!$AI:$AI,$A$22,VENTAS!$H:$H,$B24,VENTAS!$BE:$BE,"<7") -> 0 | L24: =SUMIFS(VENTAS!$M:$M,VENTAS!$AI:$AI,$A$22,VENTAS!$H:$H,$B24,VENTAS!$BE:$BE,">6")+SUMIFS(VENTAS!$O:$O,VENTAS!$AI:$AI,$A$22,VENTAS!$H:$H,$B24,VENTAS!$BE:$BE,">6")+SUMIFS(VENTAS!$P:$P,VENTAS!$AI:$AI,$A$22,VENTAS!$H:$H,$B24,VENTAS!$BE:$BE,">6")+SUMIFS(VENTAS!$S:$S,VENTAS!$AI:$AI,$A$22,VENTAS!$H:$H,$B24,VENTAS!$BE:$BE,">6")+SUMIFS(VENTAS!$V:$V,VENTAS!$AI:$AI,$A$22,VENTAS!$H:$H,$B24,VENTAS!$BE:$BE,">6") -> 0 | M24: =K24+L24 -> 0
B25: 370-Factura operadora transporte / socio | K25: =SUMIFS(VENTAS!$M:$M,VENTAS!$AI:$AI,$A$22,VENTAS!$H:$H,$B25,VENTAS!$BE:$BE,"<7")+SUMIFS(VENTAS!$O:$O,VENTAS!$AI:$AI,$A$22,VENTAS!$H:$H,$B25,VENTAS!$BE:$BE,"<7")+SUMIFS(VENTAS!$P:$P,VENTAS!$AI:$AI,$A$22,VENTAS!$H:$H,$B25,VENTAS!$BE:$BE,"<7")+SUMIFS(VENTAS!$S:$S,VENTAS!$AI:$AI,$A$22,VENTAS!$H:$H,$B25,VENTAS!$BE:$BE,"<7")+SUMIFS(VENTAS!$V:$V,VENTAS!$AI:$AI,$A$22,VENTAS!$H:$H,$B25,VENTAS!$BE:$BE,"<7") -> 0 | L25: =SUMIFS(VENTAS!$M:$M,VENTAS!$AI:$AI,$A$22,VENTAS!$H:$H,$B25,VENTAS!$BE:$BE,">6")+SUMIFS(VENTAS!$O:$O,VENTAS!$AI:$AI,$A$22,VENTAS!$H:$H,$B25,VENTAS!$BE:$BE,">6")+SUMIFS(VENTAS!$P:$P,VENTAS!$AI:$AI,$A$22,VENTAS!$H:$H,$B25,VENTAS!$BE:$BE,">6")+SUMIFS(VENTAS!$S:$S,VENTAS!$AI:$AI,$A$22,VENTAS!$H:$H,$B25,VENTAS!$BE:$BE,">6")+SUMIFS(VENTAS!$V:$V,VENTAS!$AI:$AI,$A$22,VENTAS!$H:$H,$B25,VENTAS!$BE:$BE,">6") -> 0 | M25: =K25+L25 -> 0
K26: =SUMIFS(VENTAS!$M:$M,VENTAS!$AI:$AI,$A$22,VENTAS!$H:$H,$B26,VENTAS!$BE:$BE,"<7")+SUMIFS(VENTAS!$O:$O,VENTAS!$AI:$AI,$A$22,VENTAS!$H:$H,$B26,VENTAS!$BE:$BE,"<7")+SUMIFS(VENTAS!$P:$P,VENTAS!$AI:$AI,$A$22,VENTAS!$H:$H,$B26,VENTAS!$BE:$BE,"<7")+SUMIFS(VENTAS!$S:$S,VENTAS!$AI:$AI,$A$22,VENTAS!$H:$H,$B26,VENTAS!$BE:$BE,"<7")+SUMIFS(VENTAS!$V:$V,VENTAS!$AI:$AI,$A$22,VENTAS!$H:$H,$B26,VENTAS!$BE:$BE,"<7") -> 0 | L26: =SUMIFS(VENTAS!$M:$M,VENTAS!$AI:$AI,$A$22,VENTAS!$H:$H,$B26,VENTAS!$BE:$BE,">6")+SUMIFS(VENTAS!$O:$O,VENTAS!$AI:$AI,$A$22,VENTAS!$H:$H,$B26,VENTAS!$BE:$BE,">6")+SUMIFS(VENTAS!$P:$P,VENTAS!$AI:$AI,$A$22,VENTAS!$H:$H,$B26,VENTAS!$BE:$BE,">6")+SUMIFS(VENTAS!$S:$S,VENTAS!$AI:$AI,$A$22,VENTAS!$H:$H,$B26,VENTAS!$BE:$BE,">6")+SUMIFS(VENTAS!$V:$V,VENTAS!$AI:$AI,$A$22,VENTAS!$H:$H,$B26,VENTAS!$BE:$BE,">6") -> 0 | M26: =K26+L26 -> 0
A27: (-)DEVOLUCIONES | K27: =SUM(K28:K30) -> 0 | L27: =SUM(L28:L30) -> 0 | M27: =SUM(M28:M30) -> 0
B28: 04-Nota de credito | K28: =SUMIFS(VENTAS!$M:$M,VENTAS!$AI:$AI,$A$22,VENTAS!$H:$H,$B28,VENTAS!$BE:$BE,"<7")+SUMIFS(VENTAS!$O:$O,VENTAS!$AI:$AI,$A$22,VENTAS!$H:$H,$B28,VENTAS!$BE:$BE,"<7")+SUMIFS(VENTAS!$P:$P,VENTAS!$AI:$AI,$A$22,VENTAS!$H:$H,$B28,VENTAS!$BE:$BE,"<7")+SUMIFS(VENTAS!$S:$S,VENTAS!$AI:$AI,$A$22,VENTAS!$H:$H,$B28,VENTAS!$BE:$BE,"<7")+SUMIFS(VENTAS!$V:$V,VENTAS!$AI:$AI,$A$22,VENTAS!$H:$H,$B28,VENTAS!$BE:$BE,"<7") -> 0 | L28: =SUMIFS(VENTAS!$M:$M,VENTAS!$AI:$AI,$A$22,VENTAS!$H:$H,$B28,VENTAS!$BE:$BE,">6")+SUMIFS(VENTAS!$O:$O,VENTAS!$AI:$AI,$A$22,VENTAS!$H:$H,$B28,VENTAS!$BE:$BE,">6")+SUMIFS(VENTAS!$P:$P,VENTAS!$AI:$AI,$A$22,VENTAS!$H:$H,$B28,VENTAS!$BE:$BE,">6")+SUMIFS(VENTAS!$S:$S,VENTAS!$AI:$AI,$A$22,VENTAS!$H:$H,$B28,VENTAS!$BE:$BE,">6")+SUMIFS(VENTAS!$V:$V,VENTAS!$AI:$AI,$A$22,VENTAS!$H:$H,$B28,VENTAS!$BE:$BE,">6") -> 0 | M28: =K28+L28 -> 0
B29: 372-Nota de crédito operadora transporte / socio | K29: =SUMIFS(VENTAS!$M:$M,VENTAS!$AI:$AI,$A$22,VENTAS!$H:$H,$B29,VENTAS!$BE:$BE,"<7")+SUMIFS(VENTAS!$O:$O,VENTAS!$AI:$AI,$A$22,VENTAS!$H:$H,$B29,VENTAS!$BE:$BE,"<7")+SUMIFS(VENTAS!$P:$P,VENTAS!$AI:$AI,$A$22,VENTAS!$H:$H,$B29,VENTAS!$BE:$BE,"<7")+SUMIFS(VENTAS!$S:$S,VENTAS!$AI:$AI,$A$22,VENTAS!$H:$H,$B29,VENTAS!$BE:$BE,"<7")+SUMIFS(VENTAS!$V:$V,VENTAS!$AI:$AI,$A$22,VENTAS!$H:$H,$B29,VENTAS!$BE:$BE,"<7") -> 0 | L29: =SUMIFS(VENTAS!$M:$M,VENTAS!$AI:$AI,$A$22,VENTAS!$H:$H,$B29,VENTAS!$BE:$BE,">6")+SUMIFS(VENTAS!$O:$O,VENTAS!$AI:$AI,$A$22,VENTAS!$H:$H,$B29,VENTAS!$BE:$BE,">6")+SUMIFS(VENTAS!$P:$P,VENTAS!$AI:$AI,$A$22,VENTAS!$H:$H,$B29,VENTAS!$BE:$BE,">6")+SUMIFS(VENTAS!$S:$S,VENTAS!$AI:$AI,$A$22,VENTAS!$H:$H,$B29,VENTAS!$BE:$BE,">6")+SUMIFS(VENTAS!$V:$V,VENTAS!$AI:$AI,$A$22,VENTAS!$H:$H,$B29,VENTAS!$BE:$BE,">6") -> 0 | M29: =K29+L29 -> 0
K30: =SUMIFS(VENTAS!$M:$M,VENTAS!$AI:$AI,$A$22,VENTAS!$H:$H,$B30,VENTAS!$BE:$BE,"<7")+SUMIFS(VENTAS!$O:$O,VENTAS!$AI:$AI,$A$22,VENTAS!$H:$H,$B30,VENTAS!$BE:$BE,"<7")+SUMIFS(VENTAS!$P:$P,VENTAS!$AI:$AI,$A$22,VENTAS!$H:$H,$B30,VENTAS!$BE:$BE,"<7")+SUMIFS(VENTAS!$S:$S,VENTAS!$AI:$AI,$A$22,VENTAS!$H:$H,$B30,VENTAS!$BE:$BE,"<7")+SUMIFS(VENTAS!$V:$V,VENTAS!$AI:$AI,$A$22,VENTAS!$H:$H,$B30,VENTAS!$BE:$BE,"<7") -> 0 | L30: =SUMIFS(VENTAS!$M:$M,VENTAS!$AI:$AI,$A$22,VENTAS!$H:$H,$B30,VENTAS!$BE:$BE,">6")+SUMIFS(VENTAS!$O:$O,VENTAS!$AI:$AI,$A$22,VENTAS!$H:$H,$B30,VENTAS!$BE:$BE,">6")+SUMIFS(VENTAS!$P:$P,VENTAS!$AI:$AI,$A$22,VENTAS!$H:$H,$B30,VENTAS!$BE:$BE,">6")+SUMIFS(VENTAS!$S:$S,VENTAS!$AI:$AI,$A$22,VENTAS!$H:$H,$B30,VENTAS!$BE:$BE,">6")+SUMIFS(VENTAS!$V:$V,VENTAS!$AI:$AI,$A$22,VENTAS!$H:$H,$B30,VENTAS!$BE:$BE,">6") -> 0 | M30: =K30+L30 -> 0
A31: BASE IMPONIBLE | K31: =K23+K27 -> 0 | L31: =L23+L27 -> 0 | M31: =K31+L31 -> 0
A32: IMPUESTO A LA RENTA SOBRE FRACCION BASICA | M32: =IF(B21="RIMPE EMPRENDEDOR",VLOOKUP(M31,tbl_Empre,3,1),IF(B21="RIMPE NEGOCIO POPULAR",VLOOKUP(M31,tbl_NegPop,3,1),0)) -> 0
A33: IMPUESTO A LA RENTA SOBRE FRACCION EXCEDENTE | M33: =IF(B21="RIMPE EMPRENDEDOR",(M31-VLOOKUP(M31,tbl_Empre,1,1))*VLOOKUP(M31,tbl_Empre,4,1),0) -> 0
A34: (-) RETENCIONES EN LA FUENTE x SEMESTRE | K34: =-SUMIFS(VENTAS!$AS:$AS,VENTAS!$AI:$AI,$A$22,VENTAS!$BE:$BE,"<7") -> 0 | L34: =-SUMIFS(VENTAS!$AS:$AS,VENTAS!$AI:$AI,$A$22,VENTAS!$BE:$BE,">6") -> 0 | M34: =SUM(K34:L34) -> 0
A35: IMPUESTO RENTA x PAGAR SEMESTRE | K35: =SUM(K32:K34) -> 0 | L35: =SUM(L32:L34) -> 0 | M35: =SUM(M32:M34) -> 0
A37: =Parametros!C140 -> MICROEMPRESA Y ACTIVIDADES INCLUYENTES | K37: 1er SEMESTRE (ENE-JUN) | L37: 2do SEMESTRE (JUL-DIC) | M37: TOTAL ANUAL
A38: SUBTOTAL INGRESOS | K38: =SUM(K39:K41) -> 0 | L38: =SUM(L39:L41) -> 0
B39: 18-Documentos autorizados utilizados en ventas excepto N/C N/D | K39: =SUMIFS(VENTAS!$M:$M,VENTAS!$AI:$AI,$A$22,VENTAS!$H:$H,$B39,VENTAS!$BE:$BE,"<7")+SUMIFS(VENTAS!$O:$O,VENTAS!$AI:$AI,$A$22,VENTAS!$H:$H,$B39,VENTAS!$BE:$BE,"<7")+SUMIFS(VENTAS!$P:$P,VENTAS!$AI:$AI,$A$22,VENTAS!$H:$H,$B39,VENTAS!$BE:$BE,"<7")+SUMIFS(VENTAS!$S:$S,VENTAS!$AI:$AI,$A$22,VENTAS!$H:$H,$B39,VENTAS!$BE:$BE,"<7")+SUMIFS(VENTAS!$V:$V,VENTAS!$AI:$AI,$A$22,VENTAS!$H:$H,$B39,VENTAS!$BE:$BE,"<7") -> 0 | L39: =SUMIFS(VENTAS!$M:$M,VENTAS!$AI:$AI,$A$22,VENTAS!$H:$H,$B39,VENTAS!$BE:$BE,">6")+SUMIFS(VENTAS!$O:$O,VENTAS!$AI:$AI,$A$22,VENTAS!$H:$H,$B39,VENTAS!$BE:$BE,">6")+SUMIFS(VENTAS!$P:$P,VENTAS!$AI:$AI,$A$22,VENTAS!$H:$H,$B39,VENTAS!$BE:$BE,">6")+SUMIFS(VENTAS!$S:$S,VENTAS!$AI:$AI,$A$22,VENTAS!$H:$H,$B39,VENTAS!$BE:$BE,">6")+SUMIFS(VENTAS!$V:$V,VENTAS!$AI:$AI,$A$22,VENTAS!$H:$H,$B39,VENTAS!$BE:$BE,">6") -> 0
B40: 370-Factura operadora transporte / socio | K40: =SUMIFS(VENTAS!$M:$M,VENTAS!$AI:$AI,$A$22,VENTAS!$H:$H,$B40,VENTAS!$BE:$BE,"<7")+SUMIFS(VENTAS!$O:$O,VENTAS!$AI:$AI,$A$22,VENTAS!$H:$H,$B40,VENTAS!$BE:$BE,"<7")+SUMIFS(VENTAS!$P:$P,VENTAS!$AI:$AI,$A$22,VENTAS!$H:$H,$B40,VENTAS!$BE:$BE,"<7")+SUMIFS(VENTAS!$S:$S,VENTAS!$AI:$AI,$A$22,VENTAS!$H:$H,$B40,VENTAS!$BE:$BE,"<7")+SUMIFS(VENTAS!$V:$V,VENTAS!$AI:$AI,$A$22,VENTAS!$H:$H,$B40,VENTAS!$BE:$BE,"<7") -> 0 | L40: =SUMIFS(VENTAS!$M:$M,VENTAS!$AI:$AI,$A$22,VENTAS!$H:$H,$B40,VENTAS!$BE:$BE,">6")+SUMIFS(VENTAS!$O:$O,VENTAS!$AI:$AI,$A$22,VENTAS!$H:$H,$B40,VENTAS!$BE:$BE,">6")+SUMIFS(VENTAS!$P:$P,VENTAS!$AI:$AI,$A$22,VENTAS!$H:$H,$B40,VENTAS!$BE:$BE,">6")+SUMIFS(VENTAS!$S:$S,VENTAS!$AI:$AI,$A$22,VENTAS!$H:$H,$B40,VENTAS!$BE:$BE,">6")+SUMIFS(VENTAS!$V:$V,VENTAS!$AI:$AI,$A$22,VENTAS!$H:$H,$B40,VENTAS!$BE:$BE,">6") -> 0
K41: =SUMIFS(VENTAS!$M:$M,VENTAS!$AI:$AI,$A$22,VENTAS!$H:$H,$B41,VENTAS!$BE:$BE,"<7")+SUMIFS(VENTAS!$O:$O,VENTAS!$AI:$AI,$A$22,VENTAS!$H:$H,$B41,VENTAS!$BE:$BE,"<7")+SUMIFS(VENTAS!$P:$P,VENTAS!$AI:$AI,$A$22,VENTAS!$H:$H,$B41,VENTAS!$BE:$BE,"<7")+SUMIFS(VENTAS!$S:$S,VENTAS!$AI:$AI,$A$22,VENTAS!$H:$H,$B41,VENTAS!$BE:$BE,"<7")+SUMIFS(VENTAS!$V:$V,VENTAS!$AI:$AI,$A$22,VENTAS!$H:$H,$B41,VENTAS!$BE:$BE,"<7") -> 0 | L41: =SUMIFS(VENTAS!$M:$M,VENTAS!$AI:$AI,$A$22,VENTAS!$H:$H,$B41,VENTAS!$BE:$BE,">6")+SUMIFS(VENTAS!$O:$O,VENTAS!$AI:$AI,$A$22,VENTAS!$H:$H,$B41,VENTAS!$BE:$BE,">6")+SUMIFS(VENTAS!$P:$P,VENTAS!$AI:$AI,$A$22,VENTAS!$H:$H,$B41,VENTAS!$BE:$BE,">6")+SUMIFS(VENTAS!$S:$S,VENTAS!$AI:$AI,$A$22,VENTAS!$H:$H,$B41,VENTAS!$BE:$BE,">6")+SUMIFS(VENTAS!$V:$V,VENTAS!$AI:$AI,$A$22,VENTAS!$H:$H,$B41,VENTAS!$BE:$BE,">6") -> 0
A42: (-)DEVOLUCIONES | K42: =SUM(K43:K45) -> 0 | L42: =SUM(L43:L45) -> 0
B43: 04-Nota de credito | K43: =SUMIFS(VENTAS!$M:$M,VENTAS!$AI:$AI,$A$22,VENTAS!$H:$H,$B43,VENTAS!$BE:$BE,"<7")+SUMIFS(VENTAS!$O:$O,VENTAS!$AI:$AI,$A$22,VENTAS!$H:$H,$B43,VENTAS!$BE:$BE,"<7")+SUMIFS(VENTAS!$P:$P,VENTAS!$AI:$AI,$A$22,VENTAS!$H:$H,$B43,VENTAS!$BE:$BE,"<7")+SUMIFS(VENTAS!$S:$S,VENTAS!$AI:$AI,$A$22,VENTAS!$H:$H,$B43,VENTAS!$BE:$BE,"<7")+SUMIFS(VENTAS!$V:$V,VENTAS!$AI:$AI,$A$22,VENTAS!$H:$H,$B43,VENTAS!$BE:$BE,"<7") -> 0 | L43: =SUMIFS(VENTAS!$M:$M,VENTAS!$AI:$AI,$A$22,VENTAS!$H:$H,$B43,VENTAS!$BE:$BE,">6")+SUMIFS(VENTAS!$O:$O,VENTAS!$AI:$AI,$A$22,VENTAS!$H:$H,$B43,VENTAS!$BE:$BE,">6")+SUMIFS(VENTAS!$P:$P,VENTAS!$AI:$AI,$A$22,VENTAS!$H:$H,$B43,VENTAS!$BE:$BE,">6")+SUMIFS(VENTAS!$S:$S,VENTAS!$AI:$AI,$A$22,VENTAS!$H:$H,$B43,VENTAS!$BE:$BE,">6")+SUMIFS(VENTAS!$V:$V,VENTAS!$AI:$AI,$A$22,VENTAS!$H:$H,$B43,VENTAS!$BE:$BE,">6") -> 0
B44: 372-Nota de crédito operadora transporte / socio | K44: =SUMIFS(VENTAS!$M:$M,VENTAS!$AI:$AI,$A$22,VENTAS!$H:$H,$B44,VENTAS!$BE:$BE,"<7")+SUMIFS(VENTAS!$O:$O,VENTAS!$AI:$AI,$A$22,VENTAS!$H:$H,$B44,VENTAS!$BE:$BE,"<7")+SUMIFS(VENTAS!$P:$P,VENTAS!$AI:$AI,$A$22,VENTAS!$H:$H,$B44,VENTAS!$BE:$BE,"<7")+SUMIFS(VENTAS!$S:$S,VENTAS!$AI:$AI,$A$22,VENTAS!$H:$H,$B44,VENTAS!$BE:$BE,"<7")+SUMIFS(VENTAS!$V:$V,VENTAS!$AI:$AI,$A$22,VENTAS!$H:$H,$B44,VENTAS!$BE:$BE,"<7") -> 0 | L44: =SUMIFS(VENTAS!$M:$M,VENTAS!$AI:$AI,$A$22,VENTAS!$H:$H,$B44,VENTAS!$BE:$BE,">6")+SUMIFS(VENTAS!$O:$O,VENTAS!$AI:$AI,$A$22,VENTAS!$H:$H,$B44,VENTAS!$BE:$BE,">6")+SUMIFS(VENTAS!$P:$P,VENTAS!$AI:$AI,$A$22,VENTAS!$H:$H,$B44,VENTAS!$BE:$BE,">6")+SUMIFS(VENTAS!$S:$S,VENTAS!$AI:$AI,$A$22,VENTAS!$H:$H,$B44,VENTAS!$BE:$BE,">6")+SUMIFS(VENTAS!$V:$V,VENTAS!$AI:$AI,$A$22,VENTAS!$H:$H,$B44,VENTAS!$BE:$BE,">6") -> 0
K45: =SUMIFS(VENTAS!$M:$M,VENTAS!$AI:$AI,$A$22,VENTAS!$H:$H,$B45,VENTAS!$BE:$BE,"<7")+SUMIFS(VENTAS!$O:$O,VENTAS!$AI:$AI,$A$22,VENTAS!$H:$H,$B45,VENTAS!$BE:$BE,"<7")+SUMIFS(VENTAS!$P:$P,VENTAS!$AI:$AI,$A$22,VENTAS!$H:$H,$B45,VENTAS!$BE:$BE,"<7")+SUMIFS(VENTAS!$S:$S,VENTAS!$AI:$AI,$A$22,VENTAS!$H:$H,$B45,VENTAS!$BE:$BE,"<7")+SUMIFS(VENTAS!$V:$V,VENTAS!$AI:$AI,$A$22,VENTAS!$H:$H,$B45,VENTAS!$BE:$BE,"<7") -> 0 | L45: =SUMIFS(VENTAS!$M:$M,VENTAS!$AI:$AI,$A$22,VENTAS!$H:$H,$B45,VENTAS!$BE:$BE,">6")+SUMIFS(VENTAS!$O:$O,VENTAS!$AI:$AI,$A$22,VENTAS!$H:$H,$B45,VENTAS!$BE:$BE,">6")+SUMIFS(VENTAS!$P:$P,VENTAS!$AI:$AI,$A$22,VENTAS!$H:$H,$B45,VENTAS!$BE:$BE,">6")+SUMIFS(VENTAS!$S:$S,VENTAS!$AI:$AI,$A$22,VENTAS!$H:$H,$B45,VENTAS!$BE:$BE,">6")+SUMIFS(VENTAS!$V:$V,VENTAS!$AI:$AI,$A$22,VENTAS!$H:$H,$B45,VENTAS!$BE:$BE,">6") -> 0
A46: BASE IMPONIBLE | K46: =K38+K42 -> 0 | L46: =L38+L42 -> 0 | M46: =SUM(K46:L46) -> 0
A47: IMPUESTO A LA RENTA x SEMESTRE | J47: 0.02 | K47: =K46*J47 -> 0 | L47: =L46*J47 -> 0 | M47: =SUM(K47:L47) -> 0
A48: (-) RETENCIONES EN LA FUENTE x SEMESTRE | K48: =-SUMIFS(VENTAS!$AS:$AS,VENTAS!$AI:$AI,$A$37,VENTAS!$BE:$BE,"<7") -> 0 | L48: =-SUMIFS(VENTAS!$AS:$AS,VENTAS!$AI:$AI,$A$37,VENTAS!$BE:$BE,">6") -> 0 | M48: =SUM(K48:L48) -> 0
A49: IMPUESTO RENTA x PAGAR SEMESTRE | K49: =SUM(K47:K48) -> 0 | L49: =SUM(L47:L48) -> 0 | M49: =SUM(M47:M48) -> 0
K52: INGRESOS | L52: EGRESOS | M52: RET. FTE. | U52: RESUMEN DE GASTOS PERSONALES
A53: =A22 -> RIMPE | K53: =M31 -> 0 | L53: =SUMIF(COMPRAS!AR:AR,A53,COMPRAS!U:U)+SUMIF(COMPRAS!AR:AR,A53,COMPRAS!W:W)+SUMIF(COMPRAS!AR:AR,A53,COMPRAS!X:X)+SUMIF(COMPRAS!AR:AR,A53,COMPRAS!AA:AA)+SUMIF(COMPRAS!AR:AR,A53,COMPRAS!AD:AD) -> 0 | M53: =ABS(M34) -> 0 | U53: TIPO GASTO | V53: F-Fisico | W53: E-Electronico | X53: Subtotal
A54: =A37 -> MICROEMPRESA Y ACTIVIDADES INCLUYENTES | K54: =M46 -> 0 | L54: =SUMIF(COMPRAS!AR:AR,A54,COMPRAS!U:U)+SUMIF(COMPRAS!AR:AR,A54,COMPRAS!W:W)+SUMIF(COMPRAS!AR:AR,A54,COMPRAS!X:X)+SUMIF(COMPRAS!AR:AR,A54,COMPRAS!AA:AA)+SUMIF(COMPRAS!AR:AR,A54,COMPRAS!AD:AD) -> 0 | M54: =ABS(M48) -> 0 | U54: 1-VIVIENDA | V54: =SUMIF(GASTOSP!D:D,V$53,GASTOSP!O:O) -> 0 | W54: =SUMIF(GASTOSP!D:D,W$53,GASTOSP!O:O) -> 0 | X54: =SUM(V54:W54) -> 0
A55: ACTIVIDADES EMPRESARIALES Y EXCLUYENTES | K55: =G18-K54 -> 23234.98 | L55: =Q18+R18-L54 -> 36549.58 | M55: =M18-M53-M54 -> 25.5 | U55: 2-VESTIMENTA | V55: =SUMIF(GASTOSP!D:D,V$53,GASTOSP!P:P) -> 0 | W55: =SUMIF(GASTOSP!D:D,W$53,GASTOSP!P:P) -> 0 | X55: =SUM(V55:W55) -> 0
A56: DIVIDENDOS | K56: 0 | L56: 0 | M56: 0 | U56: 3-SALUD | V56: =SUMIF(GASTOSP!D:D,V$53,GASTOSP!Q:Q) -> 0 | W56: =SUMIF(GASTOSP!D:D,W$53,GASTOSP!Q:Q) -> 0 | X56: =SUM(V56:W56) -> 0
A57: RENDIMIENTOS FINANCIEROS | K57: 0 | L57: 0 | M57: 0 | U57: 4-EDUCACION | V57: =SUMIF(GASTOSP!D:D,V$53,GASTOSP!R:R) -> 0 | W57: =SUMIF(GASTOSP!D:D,W$53,GASTOSP!R:R) -> 0 | X57: =SUM(V57:W57) -> 0
A58: RELACION DE DEPENDENCIA | K58: 0 | L58: 0 | M58: 0 | U58: 5-ALIMENTACION | V58: =SUMIF(GASTOSP!D:D,V$53,GASTOSP!S:S) -> 0 | W58: =SUMIF(GASTOSP!D:D,W$53,GASTOSP!S:S) -> 0 | X58: =SUM(V58:W58) -> 0
A59: OTROS | K59: 0 | U59: 6-TURISMO | V59: =SUMIF(GASTOSP!D:D,V$53,GASTOSP!T:T) -> 0 | W59: =SUMIF(GASTOSP!D:D,W$53,GASTOSP!T:T) -> 0 | X59: =SUM(V59:W59) -> 0
I60: TOTAL DE INGRESOS GRAVABLES | K60: =SUM(K55:K59) -> 23234.98 | L60: =SUM(L55:L59) -> 36549.58 | M60: =SUM(M55:M59) -> 25.5 | U60: TOTALES | V60: =GASTOSP!O5 -> 0 | W60: =SUM(W54:W59) -> 0 | X60: =SUM(X54:X59) -> 0
K61: =K60-L60 -> -13314.6
A62: INGRESOS EXENTOS
A63: RENDIMIENTOS FINANCIEROS | K63: 0
A64: RELACION DE DEPENDENCIA | K64: =SUM(J65:J69) -> 0
B65: DECIMO TERCER SUELDO | J65: 0
B66: DECIMO CUARTO SUELDO | J66: 0
B67: FONDO DE RESERVA | J67: 0
B68: BONIFICACIONES | J68: 0
B69: OTROS REL.DEP | J69: 0
A70: OTROS INGRESOS EXENTOS | K70: =SUM(J71:J73) -> 0
B71: PENSIONES JUBILARES | J71: 0
B72: OTROS_EXE1 | J72: 0
B73: OTROS_EXE2
J74: TOTAL DE INGRESOS EXENTOS | K74: =SUM(K63:K73) -> 0 | L74: =SUM(L63:L73) -> 0

Sheet 103
D1: FORMULARIO 103 | I1: DECLARACIÓN DE RETENCIONES EN LA FUENTE DEL IMPUESTO A LA RENTA | AD1: No.
D2: RESOLUCIÓN Nº XXX
A4: 100 IDENTIFICACIÓN DE LA DECLARACIÓN | K4: IMPORTANTE: SÍRVASE LEER INSTRUCCIONES AL REVERSO
C5: =IF(C6,C7,0) -> 0 | D5: =IF(D6,D7,0) -> 0 | E5: =IF(E6,E7,0) -> 0 | F5: =IF(F6,F7,0) -> 4 | G5: =IF(G6,G7,0) -> 0 | H5: =IF(H6,H7,0) -> 0 | I5: =IF(I6,I7,0) -> 0 | J5: =IF(J6,J7,0) -> 0 | ... N5: =IF(N6,N7,0) -> 0 | Q5: SELECCIONE PERIODO | U5: 4 | W5: <<-- Seleccione el periodo a declarar
C6: =IF($U$5=LIQ_IMPUESTOS!$C5,TRUE,FALSE) -> FALSE | D6: =IF($U$5=LIQ_IMPUESTOS!$C6,TRUE,FALSE) -> FALSE | E6: =IF($U$5=LIQ_IMPUESTOS!$C7,TRUE,FALSE) -> FALSE | F6: =IF($U$5=LIQ_IMPUESTOS!$C8,TRUE,FALSE) -> TRUE | G6: =IF($U$5=LIQ_IMPUESTOS!$C9,TRUE,FALSE) -> FALSE | H6: =IF($U$5=LIQ_IMPUESTOS!$C10,TRUE,FALSE) -> FALSE | I6: =IF($U$5=LIQ_IMPUESTOS!$C11,TRUE,FALSE) -> FALSE | J6: =IF($U$5=LIQ_IMPUESTOS!$C12,TRUE,FALSE) -> FALSE | K6: =IF($U$5=LIQ_IMPUESTOS!$C13,TRUE,FALSE) -> FALSE | L6: =IF($U$5=LIQ_IMPUESTOS!$C14,TRUE,FALSE) -> FALSE | M6: =IF($U$5=LIQ_IMPUESTOS!$C15,TRUE,FALSE) -> FALSE | N6: =IF($U$5=LIQ_IMPUESTOS!$C16,TRUE,FALSE) -> FALSE
A7: 101 | B7: MES | C7: 1 | D7: 2 | E7: 3 | F7: 4 | G7: 5 | H7: 6 | I7: 7 | J7: 8 | K7: 9 | L7: 10 | M7: 11 | N7: 12 | Q7: 102 | R7: AÑO | S7: =MID(XLSperiodo,1,1) -> 2 | T7: =MID(XLSperiodo,2,1) -> 0 | U7: =MID(XLSperiodo,3,1) -> 2 | V7: =MID(XLSperiodo,4,1) -> 6 | Y7: 104 | Z7: Nº. DE FORMULARIO QUE SUSTITUYE
A10: 200 IDENTIFICACIÓN DEL SUJETO PASIVO (AGENTE DE RETENCIÓN)
A11: 201 | B11: RUC | O11: 202 | P11: RAZÓN SOCIAL O APELLIDOS Y NOMBRES COMPLETOS
B12: =Parametros!D4 -> 0917809451001 | P12: =Parametros!D5 -> GARCIA RODRIGUEZ CHARLES MILTON
A14: DETALLE DE PAGOS Y RETENCIÓN POR IMPUESTO A LA RENTA
A15: POR PAGOS EFECTUADOS A RESIDENTES Y ESTABLECIMIENTOS PERMANENTES
V16: BASE IMPONIBLE | AC16: VALOR RETENIDO
A17: DERIVADAS DEL TRABAJO Y SERVICIOS PRESTADOS
A18: EN RELACIÓN DE DEPENDENCIA QUE SUPERA O NO LA BASE GRAVADA | V18: 302 | W18: + | X18: =+SUMIFS(COMPRAS!BG:BG,COMPRAS!BF:BF,V18,COMPRAS!DD:DD,"SI")+SUMIFS(COMPRAS!BP:BP,COMPRAS!BO:BO,V18,COMPRAS!DD:DD,"SI")+SUMIFS(COMPRAS!BY:BY,COMPRAS!BX:BX,V18,COMPRAS!DD:DD,"SI") -> 0 | AC18: 352 | AD18: + | AE18: =SUMIFS(COMPRAS!BI:BI,COMPRAS!BF:BF,V18,COMPRAS!DD:DD,"SI")+SUMIFS(COMPRAS!BR:BR,COMPRAS!BO:BO,V18,COMPRAS!DD:DD,"SI")+SUMIFS(COMPRAS!CA:CA,COMPRAS!BX:BX,V18,COMPRAS!DD:DD,"SI") -> 0
A19: SERVICIOS | D19: HONORARIOS PROFESIONALES Y DIETAS | V19: 303 | W19: + | X19: =SUM(X20:AA20) -> 0 | AC19: 353 | AD19: + | AE19: =SUM(AE20:AH20) -> 0
U20: Honorarios profesionales y dietas | V20: 303 | X20: =+SUMIFS(COMPRAS!BG:BG,COMPRAS!BF:BF,V20,COMPRAS!DD:DD,"SI")+SUMIFS(COMPRAS!BP:BP,COMPRAS!BO:BO,V20,COMPRAS!DD:DD,"SI")+SUMIFS(COMPRAS!BY:BY,COMPRAS!BX:BX,V20,COMPRAS!DD:DD,"SI") -> 0 | AE20: =SUMIFS(COMPRAS!BI:BI,COMPRAS!BF:BF,V20,COMPRAS!DD:DD,"SI")+SUMIFS(COMPRAS!BR:BR,COMPRAS!BO:BO,V20,COMPRAS!DD:DD,"SI")+SUMIFS(COMPRAS!CA:CA,COMPRAS!BX:BX,V20,COMPRAS!DD:DD,"SI") -> 0
D21: SERVICIOS PROFESIONALES PRESTADOS POR SOCIEDADES RESIDENTES | V21: 3030 | W21: + | X21: =SUM(X22:AA22) -> 0 | AC21: 3530 | AD21: + | AE21: =SUM(AE22:AH22) -> 0
U22: Servicios profesionales prestados por sociedades residentes | V22: 303A | X22: =+SUMIFS(COMPRAS!BG:BG,COMPRAS!BF:BF,V22,COMPRAS!DD:DD,"SI")+SUMIFS(COMPRAS!BP:BP,COMPRAS!BO:BO,V22,COMPRAS!DD:DD,"SI")+SUMIFS(COMPRAS!BY:BY,COMPRAS!BX:BX,V22,COMPRAS!DD:DD,"SI") -> 0 | AE22: =SUMIFS(COMPRAS!BI:BI,COMPRAS!BF:BF,V22,COMPRAS!DD:DD,"SI")+SUMIFS(COMPRAS!BR:BR,COMPRAS!BO:BO,V22,COMPRAS!DD:DD,"SI")+SUMIFS(COMPRAS!CA:CA,COMPRAS!BX:BX,V22,COMPRAS!DD:DD,"SI") -> 0
D23: PREDOMINA EL INTELECTO | V23: 304 | W23: + | X23: =SUM(X24:AA29) -> 0 | AC23: 354 | AD23: + | AE23: =SUM(AE24:AH29) -> 0
U24: Servicios predomina el intelecto no relacionados con el título profesional | V24: 304 | X24: =+SUMIFS(COMPRAS!BG:BG,COMPRAS!BF:BF,V24,COMPRAS!DD:DD,"SI")+SUMIFS(COMPRAS!BP:BP,COMPRAS!BO:BO,V24,COMPRAS!DD:DD,"SI")+SUMIFS(COMPRAS!BY:BY,COMPRAS!BX:BX,V24,COMPRAS!DD:DD,"SI") -> 0 | AE24: =SUMIFS(COMPRAS!BI:BI,COMPRAS!BF:BF,V24,COMPRAS!DD:DD,"SI")+SUMIFS(COMPRAS!BR:BR,COMPRAS!BO:BO,V24,COMPRAS!DD:DD,"SI")+SUMIFS(COMPRAS!CA:CA,COMPRAS!BX:BX,V24,COMPRAS!DD:DD,"SI") -> 0
U25: Comisiones y demás pagos por servicios predomina intelecto no relacionados con el título profesional | V25: 304A | X25: =+SUMIFS(COMPRAS!BG:BG,COMPRAS!BF:BF,V25,COMPRAS!DD:DD,"SI")+SUMIFS(COMPRAS!BP:BP,COMPRAS!BO:BO,V25,COMPRAS!DD:DD,"SI")+SUMIFS(COMPRAS!BY:BY,COMPRAS!BX:BX,V25,COMPRAS!DD:DD,"SI") -> 0 | AE25: =SUMIFS(COMPRAS!BI:BI,COMPRAS!BF:BF,V25,COMPRAS!DD:DD,"SI")+SUMIFS(COMPRAS!BR:BR,COMPRAS!BO:BO,V25,COMPRAS!DD:DD,"SI")+SUMIFS(COMPRAS!CA:CA,COMPRAS!BX:BX,V25,COMPRAS!DD:DD,"SI") -> 0
U26: Pagos a notarios y registradores de la propiedad y mercantil por sus actividades ejercidas como tales | V26: 304B | X26: =+SUMIFS(COMPRAS!BG:BG,COMPRAS!BF:BF,V26,COMPRAS!DD:DD,"SI")+SUMIFS(COMPRAS!BP:BP,COMPRAS!BO:BO,V26,COMPRAS!DD:DD,"SI")+SUMIFS(COMPRAS!BY:BY,COMPRAS!BX:BX,V26,COMPRAS!DD:DD,"SI") -> 0 | AE26: =SUMIFS(COMPRAS!BI:BI,COMPRAS!BF:BF,V26,COMPRAS!DD:DD,"SI")+SUMIFS(COMPRAS!BR:BR,COMPRAS!BO:BO,V26,COMPRAS!DD:DD,"SI")+SUMIFS(COMPRAS!CA:CA,COMPRAS!BX:BX,V26,COMPRAS!DD:DD,"SI") -> 0
U27: Pagos a deportistas, entrenadores, árbitros, miembros del cuerpo técnico por sus actividades ejercidas como tales | V27: 304C | X27: =+SUMIFS(COMPRAS!BG:BG,COMPRAS!BF:BF,V27,COMPRAS!DD:DD,"SI")+SUMIFS(COMPRAS!BP:BP,COMPRAS!BO:BO,V27,COMPRAS!DD:DD,"SI")+SUMIFS(COMPRAS!BY:BY,COMPRAS!BX:BX,V27,COMPRAS!DD:DD,"SI") -> 0 | AE27: =SUMIFS(COMPRAS!BI:BI,COMPRAS!BF:BF,V27,COMPRAS!DD:DD,"SI")+SUMIFS(COMPRAS!BR:BR,COMPRAS!BO:BO,V27,COMPRAS!DD:DD,"SI")+SUMIFS(COMPRAS!CA:CA,COMPRAS!BX:BX,V27,COMPRAS!DD:DD,"SI") -> 0
U28: Pagos a artistas por sus actividades ejercidas como tales | V28: 304D | X28: =+SUMIFS(COMPRAS!BG:BG,COMPRAS!BF:BF,V28,COMPRAS!DD:DD,"SI")+SUMIFS(COMPRAS!BP:BP,COMPRAS!BO:BO,V28,COMPRAS!DD:DD,"SI")+SUMIFS(COMPRAS!BY:BY,COMPRAS!BX:BX,V28,COMPRAS!DD:DD,"SI") -> 0 | AE28: =SUMIFS(COMPRAS!BI:BI,COMPRAS!BF:BF,V28,COMPRAS!DD:DD,"SI")+SUMIFS(COMPRAS!BR:BR,COMPRAS!BO:BO,V28,COMPRAS!DD:DD,"SI")+SUMIFS(COMPRAS!CA:CA,COMPRAS!BX:BX,V28,COMPRAS!DD:DD,"SI") -> 0
U29: Honorarios y demás pagos por servicios de docencia | V29: 304E | X29: =+SUMIFS(COMPRAS!BG:BG,COMPRAS!BF:BF,V29,COMPRAS!DD:DD,"SI")+SUMIFS(COMPRAS!BP:BP,COMPRAS!BO:BO,V29,COMPRAS!DD:DD,"SI")+SUMIFS(COMPRAS!BY:BY,COMPRAS!BX:BX,V29,COMPRAS!DD:DD,"SI") -> 0 | AE29: =SUMIFS(COMPRAS!BI:BI,COMPRAS!BF:BF,V29,COMPRAS!DD:DD,"SI")+SUMIFS(COMPRAS!BR:BR,COMPRAS!BO:BO,V29,COMPRAS!DD:DD,"SI")+SUMIFS(COMPRAS!CA:CA,COMPRAS!BX:BX,V29,COMPRAS!DD:DD,"SI") -> 0
D30: PREDOMINA MANO DE OBRA | V30: 307 | W30: + | X30: =+SUMIFS(COMPRAS!BG:BG,COMPRAS!BF:BF,V30,COMPRAS!DD:DD,"SI")+SUMIFS(COMPRAS!BP:BP,COMPRAS!BO:BO,V30,COMPRAS!DD:DD,"SI")+SUMIFS(COMPRAS!BY:BY,COMPRAS!BX:BX,V30,COMPRAS!DD:DD,"SI") -> 0 | AC30: 357 | AD30: + | AE30: =SUMIFS(COMPRAS!BI:BI,COMPRAS!BF:BF,V30,COMPRAS!DD:DD,"SI")+SUMIFS(COMPRAS!BR:BR,COMPRAS!BO:BO,V30,COMPRAS!DD:DD,"SI")+SUMIFS(COMPRAS!CA:CA,COMPRAS!BX:BX,V30,COMPRAS!DD:DD,"SI") -> 0
D31: UTILIZACION O APROVECHAMIENTO DE LA IMAGEN O RENOMBRE | V31: 308 | W31: + | X31: =+SUMIFS(COMPRAS!BG:BG,COMPRAS!BF:BF,V31,COMPRAS!DD:DD,"SI")+SUMIFS(COMPRAS!BP:BP,COMPRAS!BO:BO,V31,COMPRAS!DD:DD,"SI")+SUMIFS(COMPRAS!BY:BY,COMPRAS!BX:BX,V31,COMPRAS!DD:DD,"SI") -> 0 | AC31: 358 | AD31: + | AE31: =SUMIFS(COMPRAS!BI:BI,COMPRAS!BF:BF,V31,COMPRAS!DD:DD,"SI")+SUMIFS(COMPRAS!BR:BR,COMPRAS!BO:BO,V31,COMPRAS!DD:DD,"SI")+SUMIFS(COMPRAS!CA:CA,COMPRAS!BX:BX,V31,COMPRAS!DD:DD,"SI") -> 0
D32: PUBLICIDAD Y COMUNICACIÓN | V32: 309 | W32: + | X32: =+SUMIFS(COMPRAS!BG:BG,COMPRAS!BF:BF,V32,COMPRAS!DD:DD,"SI")+SUMIFS(COMPRAS!BP:BP,COMPRAS!BO:BO,V32,COMPRAS!DD:DD,"SI")+SUMIFS(COMPRAS!BY:BY,COMPRAS!BX:BX,V32,COMPRAS!DD:DD,"SI") -> 795 | AC32: 359 | AD32: + | AE32: =SUMIFS(COMPRAS!BI:BI,COMPRAS!BF:BF,V32,COMPRAS!DD:DD,"SI")+SUMIFS(COMPRAS!BR:BR,COMPRAS!BO:BO,V32,COMPRAS!DD:DD,"SI")+SUMIFS(COMPRAS!CA:CA,COMPRAS!BX:BX,V32,COMPRAS!DD:DD,"SI") -> 23.85
D33: TRANSPORTE PRIVADO DE PASAJEROS O SERVICIO PÚBLICO O PRIVADO DE CARGA | V33: 310 | W33: + | X33: =+SUMIFS(COMPRAS!BG:BG,COMPRAS!BF:BF,V33,COMPRAS!DD:DD,"SI")+SUMIFS(COMPRAS!BP:BP,COMPRAS!BO:BO,V33,COMPRAS!DD:DD,"SI")+SUMIFS(COMPRAS!BY:BY,COMPRAS!BX:BX,V33,COMPRAS!DD:DD,"SI") -> 0 | AC33: 360 | AD33: + | AE33: =SUMIFS(COMPRAS!BI:BI,COMPRAS!BF:BF,V33,COMPRAS!DD:DD,"SI")+SUMIFS(COMPRAS!BR:BR,COMPRAS!BO:BO,V33,COMPRAS!DD:DD,"SI")+SUMIFS(COMPRAS!CA:CA,COMPRAS!BX:BX,V33,COMPRAS!DD:DD,"SI") -> 0
A34: A TRAVES DE LIQUIDACIONES DE COMPRA (NIVEL CULTURAL O RUSTICIDAD) | V34: 311 | W34: + | X34: =+SUMIFS(COMPRAS!BG:BG,COMPRAS!BF:BF,V34,COMPRAS!DD:DD,"SI")+SUMIFS(COMPRAS!BP:BP,COMPRAS!BO:BO,V34,COMPRAS!DD:DD,"SI")+SUMIFS(COMPRAS!BY:BY,COMPRAS!BX:BX,V34,COMPRAS!DD:DD,"SI") -> 0 | AC34: 361 | AD34: + | AE34: =SUMIFS(COMPRAS!BI:BI,COMPRAS!BF:BF,V34,COMPRAS!DD:DD,"SI")+SUMIFS(COMPRAS!BR:BR,COMPRAS!BO:BO,V34,COMPRAS!DD:DD,"SI")+SUMIFS(COMPRAS!CA:CA,COMPRAS!BX:BX,V34,COMPRAS!DD:DD,"SI") -> 0
A35: POR BIENES Y SERVICIOS
A36: TRANSFERENCIA DE BIENES MUEBLES DE NATURALEZA CORPORAL | V36: 312 | W36: + | X36: =SUM(X37:AA37) -> 16503.36 | AC36: 362 | AD36: + | AE36: =SUM(AE37:AH37) -> 330.07
U37: Transferencia de bienes muebles de naturaleza corporal | V37: 312 | X37: =+SUMIFS(COMPRAS!BG:BG,COMPRAS!BF:BF,V37,COMPRAS!DD:DD,"SI")+SUMIFS(COMPRAS!BP:BP,COMPRAS!BO:BO,V37,COMPRAS!DD:DD,"SI")+SUMIFS(COMPRAS!BY:BY,COMPRAS!BX:BX,V37,COMPRAS!DD:DD,"SI") -> 16503.36 | AE37: =SUMIFS(COMPRAS!BI:BI,COMPRAS!BF:BF,V37,COMPRAS!DD:DD,"SI")+SUMIFS(COMPRAS!BR:BR,COMPRAS!BO:BO,V37,COMPRAS!DD:DD,"SI")+SUMIFS(COMPRAS!CA:CA,COMPRAS!BX:BX,V37,COMPRAS!DD:DD,"SI") -> 330.07
A38: SEGUROS Y REASEGUROS (PRIMAS Y CESIONES) | V38: 322 | W38: + | X38: =+SUMIFS(COMPRAS!BG:BG,COMPRAS!BF:BF,V38,COMPRAS!DD:DD,"SI")+SUMIFS(COMPRAS!BP:BP,COMPRAS!BO:BO,V38,COMPRAS!DD:DD,"SI")+SUMIFS(COMPRAS!BY:BY,COMPRAS!BX:BX,V38,COMPRAS!DD:DD,"SI") -> 0 | AC38: 372 | AD38: + | AE38: =SUMIFS(COMPRAS!BI:BI,COMPRAS!BF:BF,V38,COMPRAS!DD:DD,"SI")+SUMIFS(COMPRAS!BR:BR,COMPRAS!BO:BO,V38,COMPRAS!DD:DD,"SI")+SUMIFS(COMPRAS!CA:CA,COMPRAS!BX:BX,V38,COMPRAS!DD:DD,"SI") -> 0
A39: COMPRAS AL PRODUCTOR: de bienes de origen agrícola, avícola, pecuario, apícola, cunícola, bioacuático, forestal y carnes en estado natural y los descritos en el art.27.1 de LRTI. | V39: 3120 | W39: + | X39: =SUM(X40:AA40) -> 0 | AC39: 3620 | AD39: + | AE39: =SUM(AE40:AH40) -> 0
U40: COMPRAS AL PRODUCTOR: de bienes de origen bioacuático, forestal y los descritos el art.27.1 de LRTI | V40: 312A | X40: =+SUMIFS(COMPRAS!BG:BG,COMPRAS!BF:BF,V40,COMPRAS!DD:DD,"SI")+SUMIFS(COMPRAS!BP:BP,COMPRAS!BO:BO,V40,COMPRAS!DD:DD,"SI")+SUMIFS(COMPRAS!BY:BY,COMPRAS!BX:BX,V40,COMPRAS!DD:DD,"SI") -> 0 | AE40: =SUMIFS(COMPRAS!BI:BI,COMPRAS!BF:BF,V40,COMPRAS!DD:DD,"SI")+SUMIFS(COMPRAS!BR:BR,COMPRAS!BO:BO,V40,COMPRAS!DD:DD,"SI")+SUMIFS(COMPRAS!CA:CA,COMPRAS!BX:BX,V40,COMPRAS!DD:DD,"SI") -> 0
A41: COMPRAS AL COMERCIALIZADOR: de bienes de origen agrícola, avícola, pecuario, apícola, cunícola, bioacuático, forestal y carnes en estado natural y los descritos en el art.27.1 de LRTI. | V41: 3121 | W41: + | X41: =SUM(X42:AA42) -> 0 | AC41: 3621 | AD41: + | AE41: =SUM(AE42:AH42) -> 0
U42: COMPRAS AL COMERCIALIZADOR: de bienes de origen bioacuático, forestal y los descritos el art.27.1 de LRTI | V42: 312C | X42: =+SUMIFS(COMPRAS!BG:BG,COMPRAS!BF:BF,V42,COMPRAS!DD:DD,"SI")+SUMIFS(COMPRAS!BP:BP,COMPRAS!BO:BO,V42,COMPRAS!DD:DD,"SI")+SUMIFS(COMPRAS!BY:BY,COMPRAS!BX:BX,V42,COMPRAS!DD:DD,"SI") -> 0 | AE42: =SUMIFS(COMPRAS!BI:BI,COMPRAS!BF:BF,V42,COMPRAS!DD:DD,"SI")+SUMIFS(COMPRAS!BR:BR,COMPRAS!BO:BO,V42,COMPRAS!DD:DD,"SI")+SUMIFS(COMPRAS!CA:CA,COMPRAS!BX:BX,V42,COMPRAS!DD:DD,"SI") -> 0
A43: ACTIVIDADES DE CONSTRUCCIÓN DE OBRA MATERIAL INMUEBLE, URBANIZACIÓN, LOTIZACIÓN O ACTIVIDADES SIMILARES | V43: 3430 | W43: + | X43: =SUM(X44:AA44) -> 0 | AC43: 3450 | AD43: + | AE43: =SUM(AE44:AH44) -> 0
U44: Por actividades de construcción de obra material inmueble, urbanización, lotización o actividades similares | V44: 343B | X44: =+SUMIFS(COMPRAS!BG:BG,COMPRAS!BF:BF,V44,COMPRAS!DD:DD,"SI")+SUMIFS(COMPRAS!BP:BP,COMPRAS!BO:BO,V44,COMPRAS!DD:DD,"SI")+SUMIFS(COMPRAS!BY:BY,COMPRAS!BX:BX,V44,COMPRAS!DD:DD,"SI") -> 0 | AE44: =SUMIFS(COMPRAS!BI:BI,COMPRAS!BF:BF,V44,COMPRAS!DD:DD,"SI")+SUMIFS(COMPRAS!BR:BR,COMPRAS!BO:BO,V44,COMPRAS!DD:DD,"SI")+SUMIFS(COMPRAS!CA:CA,COMPRAS!BX:BX,V44,COMPRAS!DD:DD,"SI") -> 0
A45: PAGOS APLICABLES EL 1% (Energía Eléctrica y régimen RIMPE - Emprendedores, para este caso aplica con cualquier forma de pago inclusive los pagos que deban realizar las tarjetas de crédito/débito) | V45: 343 | W45: + | X45: =SUM(X46:AA48) -> 0 | AC45: 393 | AD45: + | AE45: =SUM(AE46:AH48) -> 0
U46: Otras retenciones aplicables el 1% | V46: 343 | X46: =+SUMIFS(COMPRAS!BG:BG,COMPRAS!BF:BF,V46,COMPRAS!DD:DD,"SI")+SUMIFS(COMPRAS!BP:BP,COMPRAS!BO:BO,V46,COMPRAS!DD:DD,"SI")+SUMIFS(COMPRAS!BY:BY,COMPRAS!BX:BX,V46,COMPRAS!DD:DD,"SI") -> 0 | AE46: =SUMIFS(COMPRAS!BI:BI,COMPRAS!BF:BF,V46,COMPRAS!DD:DD,"SI")+SUMIFS(COMPRAS!BR:BR,COMPRAS!BO:BO,V46,COMPRAS!DD:DD,"SI")+SUMIFS(COMPRAS!CA:CA,COMPRAS!BX:BX,V46,COMPRAS!DD:DD,"SI") -> 0
U47: Por energía eléctrica 1% | V47: 343A | X47: =+SUMIFS(COMPRAS!BG:BG,COMPRAS!BF:BF,V47,COMPRAS!BH:BH,"=0.01",COMPRAS!DD:DD,"SI")+SUMIFS(COMPRAS!BP:BP,COMPRAS!BO:BO,V47,COMPRAS!BQ:BQ,"=0.01",COMPRAS!DD:DD,"SI")+SUMIFS(COMPRAS!BY:BY,COMPRAS!BX:BX,V47,COMPRAS!BZ:BZ,"=0.01",COMPRAS!DD:DD,"SI") -> 0 | AE47: =SUMIFS(COMPRAS!BI:BI,COMPRAS!BF:BF,V47,COMPRAS!BH:BH,"=0.01",COMPRAS!DD:DD,"SI")+SUMIFS(COMPRAS!BR:BR,COMPRAS!BO:BO,V47,COMPRAS!BQ:BQ,"=0.01",COMPRAS!DD:DD,"SI")+SUMIFS(COMPRAS!CA:CA,COMPRAS!BX:BX,V47,COMPRAS!BZ:BZ,"=0.01",COMPRAS!DD:DD,"SI") -> 0
U48: Impuesto Redimible a las botellas plásticas - IRBP | V48: 343C | X48: =+SUMIFS(COMPRAS!BG:BG,COMPRAS!BF:BF,V48,COMPRAS!DD:DD,"SI")+SUMIFS(COMPRAS!BP:BP,COMPRAS!BO:BO,V48,COMPRAS!DD:DD,"SI")+SUMIFS(COMPRAS!BY:BY,COMPRAS!BX:BX,V48,COMPRAS!DD:DD,"SI") -> 0 | AE48: =SUMIFS(COMPRAS!BI:BI,COMPRAS!BF:BF,V48,COMPRAS!DD:DD,"SI")+SUMIFS(COMPRAS!BR:BR,COMPRAS!BO:BO,V48,COMPRAS!DD:DD,"SI")+SUMIFS(COMPRAS!CA:CA,COMPRAS!BX:BX,V48,COMPRAS!DD:DD,"SI") -> 0
A49: PAGOS APLICABLES EL 2% (Energía Eléctrica incluye Pago local tarjeta de crédito /débito reportada por la Emisora de tarjeta de crédito / entidades del sistema financiero; adquisición de sustancias minerales dentro del territorio nacional; Recepción de botellas plásticas no retornables de PET) | V49: 344 | W49: + | X49: =SUM(X50:AA53) -> 0 | AC49: 394 | AD49: + | AE49: =SUM(AE50:AH53) -> 0
U50: Otras retenciones aplicables el 2% | V50: 344 | X50: =+SUMIFS(COMPRAS!BG:BG,COMPRAS!BF:BF,V50,COMPRAS!DD:DD,"SI")+SUMIFS(COMPRAS!BP:BP,COMPRAS!BO:BO,V50,COMPRAS!DD:DD,"SI")+SUMIFS(COMPRAS!BY:BY,COMPRAS!BX:BX,V50,COMPRAS!DD:DD,"SI") -> 0 | AE50: =SUMIFS(COMPRAS!BI:BI,COMPRAS!BF:BF,V50,COMPRAS!DD:DD,"SI")+SUMIFS(COMPRAS!BR:BR,COMPRAS!BO:BO,V50,COMPRAS!DD:DD,"SI")+SUMIFS(COMPRAS!CA:CA,COMPRAS!BX:BX,V50,COMPRAS!DD:DD,"SI") -> 0
U51: Por energía eléctrica 2% | V51: 343A | X51: =+SUMIFS(COMPRAS!BG:BG,COMPRAS!BF:BF,V51,COMPRAS!BH:BH,"=0.02",COMPRAS!DD:DD,"SI")+SUMIFS(COMPRAS!BP:BP,COMPRAS!BO:BO,V51,COMPRAS!BQ:BQ,"=0.02",COMPRAS!DD:DD,"SI")+SUMIFS(COMPRAS!BY:BY,COMPRAS!BX:BX,V51,COMPRAS!BZ:BZ,"=0.02",COMPRAS!DD:DD,"SI") -> 0 | AE51: =SUMIFS(COMPRAS!BI:BI,COMPRAS!BF:BF,V51,COMPRAS!BH:BH,"=0.02",COMPRAS!DD:DD,"SI")+SUMIFS(COMPRAS!BR:BR,COMPRAS!BO:BO,V51,COMPRAS!BQ:BQ,"=0.02",COMPRAS!DD:DD,"SI")+SUMIFS(COMPRAS!CA:CA,COMPRAS!BX:BX,V51,COMPRAS!BZ:BZ,"=0.02",COMPRAS!DD:DD,"SI") -> 0
U52: Pago local tarjeta de crédito reportada por la Emisora de tarjeta de crédito, solo recap | V52: 344A | X52: =+SUMIFS(COMPRAS!BG:BG,COMPRAS!BF:BF,V52,COMPRAS!DD:DD,"SI")+SUMIFS(COMPRAS!BP:BP,COMPRAS!BO:BO,V52,COMPRAS!DD:DD,"SI")+SUMIFS(COMPRAS!BY:BY,COMPRAS!BX:BX,V52,COMPRAS!DD:DD,"SI") -> 0 | AE52: =SUMIFS(COMPRAS!BI:BI,COMPRAS!BF:BF,V52,COMPRAS!DD:DD,"SI")+SUMIFS(COMPRAS!BR:BR,COMPRAS!BO:BO,V52,COMPRAS!DD:DD,"SI")+SUMIFS(COMPRAS!CA:CA,COMPRAS!BX:BX,V52,COMPRAS!DD:DD,"SI") -> 0
U53: Adquisición de sustancias minerales dentro del territorio nacional | V53: 344B | X53: =+SUMIFS(COMPRAS!BG:BG,COMPRAS!BF:BF,V53,COMPRAS!DD:DD,"SI")+SUMIFS(COMPRAS!BP:BP,COMPRAS!BO:BO,V53,COMPRAS!DD:DD,"SI")+SUMIFS(COMPRAS!BY:BY,COMPRAS!BX:BX,V53,COMPRAS!DD:DD,"SI") -> 0 | AE53: =SUMIFS(COMPRAS!BI:BI,COMPRAS!BF:BF,V53,COMPRAS!DD:DD,"SI")+SUMIFS(COMPRAS!BR:BR,COMPRAS!BO:BO,V53,COMPRAS!DD:DD,"SI")+SUMIFS(COMPRAS!CA:CA,COMPRAS!BX:BX,V53,COMPRAS!DD:DD,"SI") -> 0
A54: PAGOS DE BIENES Y SERVICIOS NO SUJETOS A RETENCIÓN O CON 0% (DISTINTOS DE RENDIMIENTOS FINANCIEROS) | V54: 332 | W54: + | X54: =SUM(X55:AA63) -> 19251.22
U55: Otras compras de bienes y servicios no sujetas a retención | V55: 332 | X55: =+SUMIFS(COMPRAS!BG:BG,COMPRAS!BF:BF,V55,COMPRAS!DD:DD,"SI")+SUMIFS(COMPRAS!BP:BP,COMPRAS!BO:BO,V55,COMPRAS!DD:DD,"SI")+SUMIFS(COMPRAS!BY:BY,COMPRAS!BX:BX,V55,COMPRAS!DD:DD,"SI") -> 19251.22
U56: Compra de bienes inmuebles | V56: 332B | X56: =+SUMIFS(COMPRAS!BG:BG,COMPRAS!BF:BF,V56,COMPRAS!DD:DD,"SI")+SUMIFS(COMPRAS!BP:BP,COMPRAS!BO:BO,V56,COMPRAS!DD:DD,"SI")+SUMIFS(COMPRAS!BY:BY,COMPRAS!BX:BX,V56,COMPRAS!DD:DD,"SI") -> 0
U57: Transporte público de pasajeros | V57: 332C | X57: =+SUMIFS(COMPRAS!BG:BG,COMPRAS!BF:BF,V57,COMPRAS!DD:DD,"SI")+SUMIFS(COMPRAS!BP:BP,COMPRAS!BO:BO,V57,COMPRAS!DD:DD,"SI")+SUMIFS(COMPRAS!BY:BY,COMPRAS!BX:BX,V57,COMPRAS!DD:DD,"SI") -> 0
U58: Pagos en el país por transporte de pasajeros o transporte internacional de carga, a compañías nacionales o extranjeras de aviación o marítimas | V58: 332D | X58: =+SUMIFS(COMPRAS!BG:BG,COMPRAS!BF:BF,V58,COMPRAS!DD:DD,"SI")+SUMIFS(COMPRAS!BP:BP,COMPRAS!BO:BO,V58,COMPRAS!DD:DD,"SI")+SUMIFS(COMPRAS!BY:BY,COMPRAS!BX:BX,V58,COMPRAS!DD:DD,"SI") -> 0
U59: Valores entregados por las cooperativas de transporte a sus socios | V59: 332E | X59: =+SUMIFS(COMPRAS!BG:BG,COMPRAS!BF:BF,V59,COMPRAS!DD:DD,"SI")+SUMIFS(COMPRAS!BP:BP,COMPRAS!BO:BO,V59,COMPRAS!DD:DD,"SI")+SUMIFS(COMPRAS!BY:BY,COMPRAS!BX:BX,V59,COMPRAS!DD:DD,"SI") -> 0
U60: Compraventa de divisas distintas al dólar de los Estados Unidos de América | V60: 332F | X60: =+SUMIFS(COMPRAS!BG:BG,COMPRAS!BF:BF,V60,COMPRAS!DD:DD,"SI")+SUMIFS(COMPRAS!BP:BP,COMPRAS!BO:BO,V60,COMPRAS!DD:DD,"SI")+SUMIFS(COMPRAS!BY:BY,COMPRAS!BX:BX,V60,COMPRAS!DD:DD,"SI") -> 0
U61: Pagos con tarjeta de crédito | V61: 332G | X61: =+SUMIFS(COMPRAS!BG:BG,COMPRAS!BF:BF,V61,COMPRAS!DD:DD,"SI")+SUMIFS(COMPRAS!BP:BP,COMPRAS!BO:BO,V61,COMPRAS!DD:DD,"SI")+SUMIFS(COMPRAS!BY:BY,COMPRAS!BX:BX,V61,COMPRAS!DD:DD,"SI") -> 0
U62: Pago al exterior tarjeta de crédito reportada por la Emisora de tarjeta de crédito, solo recap | V62: 332H | X62: =+SUMIFS(COMPRAS!BG:BG,COMPRAS!BF:BF,V62,COMPRAS!DD:DD,"SI")+SUMIFS(COMPRAS!BP:BP,COMPRAS!BO:BO,V62,COMPRAS!DD:DD,"SI")+SUMIFS(COMPRAS!BY:BY,COMPRAS!BX:BX,V62,COMPRAS!DD:DD,"SI") -> 0
U63: Pago a través de convenio de debito (Clientes IFI`s) | V63: 332I | X63: =+SUMIFS(COMPRAS!BG:BG,COMPRAS!BF:BF,V63,COMPRAS!DD:DD,"SI")+SUMIFS(COMPRAS!BP:BP,COMPRAS!BO:BO,V63,COMPRAS!DD:DD,"SI")+SUMIFS(COMPRAS!BY:BY,COMPRAS!BX:BX,V63,COMPRAS!DD:DD,"SI") -> 0
A64: POR REGALIAS, COMISIONES, ARRENDAMIENTOS Y OTROS
A65: POR REGALIAS, DERECHOS DE AUTOR, MARCAS, PATENTES Y SIMILARES | V65: 314 | W65: + | X65: =SUM(X66:AA69) -> 0 | AC65: 364 | AD65: + | AE65: =SUM(AE66:AH69) -> 0
U66: Regalías por concepto de franquicias de acuerdo a Ley de Propiedad Intelectual - pago a personas naturales | V66: 314A | X66: =+SUMIFS(COMPRAS!BG:BG,COMPRAS!BF:BF,V66,COMPRAS!DD:DD,"SI")+SUMIFS(COMPRAS!BP:BP,COMPRAS!BO:BO,V66,COMPRAS!DD:DD,"SI")+SUMIFS(COMPRAS!BY:BY,COMPRAS!BX:BX,V66,COMPRAS!DD:DD,"SI") -> 0 | AE66: =SUMIFS(COMPRAS!BI:BI,COMPRAS!BF:BF,V66,COMPRAS!DD:DD,"SI")+SUMIFS(COMPRAS!BR:BR,COMPRAS!BO:BO,V66,COMPRAS!DD:DD,"SI")+SUMIFS(COMPRAS!CA:CA,COMPRAS!BX:BX,V66,COMPRAS!DD:DD,"SI") -> 0
U67: Cánones, derechos de autor, marcas, patentes y similares de acuerdo a Ley de Propiedad Intelectual – pago a personas naturales | V67: 314B | X67: =+SUMIFS(COMPRAS!BG:BG,COMPRAS!BF:BF,V67,COMPRAS!DD:DD,"SI")+SUMIFS(COMPRAS!BP:BP,COMPRAS!BO:BO,V67,COMPRAS!DD:DD,"SI")+SUMIFS(COMPRAS!BY:BY,COMPRAS!BX:BX,V67,COMPRAS!DD:DD,"SI") -> 0 | AE67: =SUMIFS(COMPRAS!BI:BI,COMPRAS!BF:BF,V67,COMPRAS!DD:DD,"SI")+SUMIFS(COMPRAS!BR:BR,COMPRAS!BO:BO,V67,COMPRAS!DD:DD,"SI")+SUMIFS(COMPRAS!CA:CA,COMPRAS!BX:BX,V67,COMPRAS!DD:DD,"SI") -> 0
U68: Regalías por concepto de franquicias de acuerdo a Ley de Propiedad Intelectual - pago a sociedades | V68: 314C | X68: =+SUMIFS(COMPRAS!BG:BG,COMPRAS!BF:BF,V68,COMPRAS!DD:DD,"SI")+SUMIFS(COMPRAS!BP:BP,COMPRAS!BO:BO,V68,COMPRAS!DD:DD,"SI")+SUMIFS(COMPRAS!BY:BY,COMPRAS!BX:BX,V68,COMPRAS!DD:DD,"SI") -> 0 | AE68: =SUMIFS(COMPRAS!BI:BI,COMPRAS!BF:BF,V68,COMPRAS!DD:DD,"SI")+SUMIFS(COMPRAS!BR:BR,COMPRAS!BO:BO,V68,COMPRAS!DD:DD,"SI")+SUMIFS(COMPRAS!CA:CA,COMPRAS!BX:BX,V68,COMPRAS!DD:DD,"SI") -> 0
U69: Cánones, derechos de autor, marcas, patentes y similares de acuerdo a Ley de Propiedad Intelectual – pago a sociedades | V69: 314D | X69: =+SUMIFS(COMPRAS!BG:BG,COMPRAS!BF:BF,V69,COMPRAS!DD:DD,"SI")+SUMIFS(COMPRAS!BP:BP,COMPRAS!BO:BO,V69,COMPRAS!DD:DD,"SI")+SUMIFS(COMPRAS!BY:BY,COMPRAS!BX:BX,V69,COMPRAS!DD:DD,"SI") -> 0 | AE69: =SUMIFS(COMPRAS!BI:BI,COMPRAS!BF:BF,V69,COMPRAS!DD:DD,"SI")+SUMIFS(COMPRAS!BR:BR,COMPRAS!BO:BO,V69,COMPRAS!DD:DD,"SI")+SUMIFS(COMPRAS!CA:CA,COMPRAS!BX:BX,V69,COMPRAS!DD:DD,"SI") -> 0
A70: COMISIONES A SOCIEDADES, NACIONALES O EXTRANJERAS RESIDENTES Y ESTABLECIMIENTOS PERMANENTES DOMICILIADOS EN EL PAÍS | V70: 3140 | W70: + | X70: =SUM(X71:AA71) -> 0 | AC70: 3640 | AD70: + | AE70: =SUM(AE71:AH71) -> 0
U71: Comisiones pagadas a sociedades, nacionales o extranjeras residentes en el Ecuador y establecimientos permanentes domiciliados en el país | V71: 3482 | X71: =+SUMIFS(COMPRAS!BG:BG,COMPRAS!BF:BF,V71,COMPRAS!DD:DD,"SI")+SUMIFS(COMPRAS!BP:BP,COMPRAS!BO:BO,V71,COMPRAS!DD:DD,"SI")+SUMIFS(COMPRAS!BY:BY,COMPRAS!BX:BX,V71,COMPRAS!DD:DD,"SI") -> 0 | AE71: =SUMIFS(COMPRAS!BI:BI,COMPRAS!BF:BF,V71,COMPRAS!DD:DD,"SI")+SUMIFS(COMPRAS!BR:BR,COMPRAS!BO:BO,V71,COMPRAS!DD:DD,"SI")+SUMIFS(COMPRAS!CA:CA,COMPRAS!BX:BX,V71,COMPRAS!DD:DD,"SI") -> 0
A72: ARRENDAMIENTO | D72: MERCANTIL | V72: 319 | W72: + | X72: =+SUMIFS(COMPRAS!BG:BG,COMPRAS!BF:BF,V72,COMPRAS!DD:DD,"SI")+SUMIFS(COMPRAS!BP:BP,COMPRAS!BO:BO,V72,COMPRAS!DD:DD,"SI")+SUMIFS(COMPRAS!BY:BY,COMPRAS!BX:BX,V72,COMPRAS!DD:DD,"SI") -> 0 | AC72: 369 | AD72: + | AE72: =SUMIFS(COMPRAS!BI:BI,COMPRAS!BF:BF,V72,COMPRAS!DD:DD,"SI")+SUMIFS(COMPRAS!BR:BR,COMPRAS!BO:BO,V72,COMPRAS!DD:DD,"SI")+SUMIFS(COMPRAS!CA:CA,COMPRAS!BX:BX,V72,COMPRAS!DD:DD,"SI") -> 0
D73: BIENES INMUEBLES | V73: 320 | W73: + | X73: =+SUMIFS(COMPRAS!BG:BG,COMPRAS!BF:BF,V73,COMPRAS!DD:DD,"SI")+SUMIFS(COMPRAS!BP:BP,COMPRAS!BO:BO,V73,COMPRAS!DD:DD,"SI")+SUMIFS(COMPRAS!BY:BY,COMPRAS!BX:BX,V73,COMPRAS!DD:DD,"SI") -> 0 | AC73: 370 | AD73: + | AE73: =SUMIFS(COMPRAS!BI:BI,COMPRAS!BF:BF,V73,COMPRAS!DD:DD,"SI")+SUMIFS(COMPRAS!BR:BR,COMPRAS!BO:BO,V73,COMPRAS!DD:DD,"SI")+SUMIFS(COMPRAS!CA:CA,COMPRAS!BX:BX,V73,COMPRAS!DD:DD,"SI") -> 0
A74: RELACIONADAS CON EL CAPITAL ( RENDIMIENTOS, GANANCIAS, DIVIDENDOS Y OTROS)
A75: RENDIMIENTOS FINANCIEROS | V75: 323 | W75: + | X75: =SUM(X76:AA87) -> 0 | AC75: 373 | AD75: + | AE75: =SUM(AE76:AH87) -> 0
U76: Por rendimientos financieros pagados a naturales y sociedades (No a IFIs) | V76: 323 | X76: =+SUMIFS(COMPRAS!BG:BG,COMPRAS!BF:BF,V76,COMPRAS!DD:DD,"SI")+SUMIFS(COMPRAS!BP:BP,COMPRAS!BO:BO,V76,COMPRAS!DD:DD,"SI")+SUMIFS(COMPRAS!BY:BY,COMPRAS!BX:BX,V76,COMPRAS!DD:DD,"SI") -> 0 | AE76: =SUMIFS(COMPRAS!BI:BI,COMPRAS!BF:BF,V76,COMPRAS!DD:DD,"SI")+SUMIFS(COMPRAS!BR:BR,COMPRAS!BO:BO,V76,COMPRAS!DD:DD,"SI")+SUMIFS(COMPRAS!CA:CA,COMPRAS!BX:BX,V76,COMPRAS!DD:DD,"SI") -> 0
U77: Por RF: depósitos Cta. Corriente | V77: 323A | X77: =+SUMIFS(COMPRAS!BG:BG,COMPRAS!BF:BF,V77,COMPRAS!DD:DD,"SI")+SUMIFS(COMPRAS!BP:BP,COMPRAS!BO:BO,V77,COMPRAS!DD:DD,"SI")+SUMIFS(COMPRAS!BY:BY,COMPRAS!BX:BX,V77,COMPRAS!DD:DD,"SI") -> 0 | AE77: =SUMIFS(COMPRAS!BI:BI,COMPRAS!BF:BF,V77,COMPRAS!DD:DD,"SI")+SUMIFS(COMPRAS!BR:BR,COMPRAS!BO:BO,V77,COMPRAS!DD:DD,"SI")+SUMIFS(COMPRAS!CA:CA,COMPRAS!BX:BX,V77,COMPRAS!DD:DD,"SI") -> 0
U78: Por RF: depósitos Cta. Ahorros Sociedades | V78: 323B1 | X78: =+SUMIFS(COMPRAS!BG:BG,COMPRAS!BF:BF,V78,COMPRAS!DD:DD,"SI")+SUMIFS(COMPRAS!BP:BP,COMPRAS!BO:BO,V78,COMPRAS!DD:DD,"SI")+SUMIFS(COMPRAS!BY:BY,COMPRAS!BX:BX,V78,COMPRAS!DD:DD,"SI") -> 0 | AE78: =SUMIFS(COMPRAS!BI:BI,COMPRAS!BF:BF,V78,COMPRAS!DD:DD,"SI")+SUMIFS(COMPRAS!BR:BR,COMPRAS!BO:BO,V78,COMPRAS!DD:DD,"SI")+SUMIFS(COMPRAS!CA:CA,COMPRAS!BX:BX,V78,COMPRAS!DD:DD,"SI") -> 0
U79: Por RF: depósito a plazo fijo gravados | V79: 323E | X79: =+SUMIFS(COMPRAS!BG:BG,COMPRAS!BF:BF,V79,COMPRAS!DD:DD,"SI")+SUMIFS(COMPRAS!BP:BP,COMPRAS!BO:BO,V79,COMPRAS!DD:DD,"SI")+SUMIFS(COMPRAS!BY:BY,COMPRAS!BX:BX,V79,COMPRAS!DD:DD,"SI") -> 0 | AE79: =SUMIFS(COMPRAS!BI:BI,COMPRAS!BF:BF,V79,COMPRAS!DD:DD,"SI")+SUMIFS(COMPRAS!BR:BR,COMPRAS!BO:BO,V79,COMPRAS!DD:DD,"SI")+SUMIFS(COMPRAS!CA:CA,COMPRAS!BX:BX,V79,COMPRAS!DD:DD,"SI") -> 0
U80: Por rendimientos financieros: operaciones de reporto - repos | V80: 323F | X80: =+SUMIFS(COMPRAS!BG:BG,COMPRAS!BF:BF,V80,COMPRAS!DD:DD,"SI")+SUMIFS(COMPRAS!BP:BP,COMPRAS!BO:BO,V80,COMPRAS!DD:DD,"SI")+SUMIFS(COMPRAS!BY:BY,COMPRAS!BX:BX,V80,COMPRAS!DD:DD,"SI") -> 0 | AE80: =SUMIFS(COMPRAS!BI:BI,COMPRAS!BF:BF,V80,COMPRAS!DD:DD,"SI")+SUMIFS(COMPRAS!BR:BR,COMPRAS!BO:BO,V80,COMPRAS!DD:DD,"SI")+SUMIFS(COMPRAS!CA:CA,COMPRAS!BX:BX,V80,COMPRAS!DD:DD,"SI") -> 0
U81: Por RF: inversiones (captaciones) rendimientos distintos de aquellos pagados a IFIs | V81: 323G | X81: =+SUMIFS(COMPRAS!BG:BG,COMPRAS!BF:BF,V81,COMPRAS!DD:DD,"SI")+SUMIFS(COMPRAS!BP:BP,COMPRAS!BO:BO,V81,COMPRAS!DD:DD,"SI")+SUMIFS(COMPRAS!BY:BY,COMPRAS!BX:BX,V81,COMPRAS!DD:DD,"SI") -> 0 | AE81: =SUMIFS(COMPRAS!BI:BI,COMPRAS!BF:BF,V81,COMPRAS!DD:DD,"SI")+SUMIFS(COMPRAS!BR:BR,COMPRAS!BO:BO,V81,COMPRAS!DD:DD,"SI")+SUMIFS(COMPRAS!CA:CA,COMPRAS!BX:BX,V81,COMPRAS!DD:DD,"SI") -> 0
U82: Por RF: obligaciones | V82: 323H | X82: =+SUMIFS(COMPRAS!BG:BG,COMPRAS!BF:BF,V82,COMPRAS!DD:DD,"SI")+SUMIFS(COMPRAS!BP:BP,COMPRAS!BO:BO,V82,COMPRAS!DD:DD,"SI")+SUMIFS(COMPRAS!BY:BY,COMPRAS!BX:BX,V82,COMPRAS!DD:DD,"SI") -> 0 | AE82: =SUMIFS(COMPRAS!BI:BI,COMPRAS!BF:BF,V82,COMPRAS!DD:DD,"SI")+SUMIFS(COMPRAS!BR:BR,COMPRAS!BO:BO,V82,COMPRAS!DD:DD,"SI")+SUMIFS(COMPRAS!CA:CA,COMPRAS!BX:BX,V82,COMPRAS!DD:DD,"SI") -> 0
U83: Por RF: bonos convertible en acciones | V83: 323I | X83: =+SUMIFS(COMPRAS!BG:BG,COMPRAS!BF:BF,V83,COMPRAS!DD:DD,"SI")+SUMIFS(COMPRAS!BP:BP,COMPRAS!BO:BO,V83,COMPRAS!DD:DD,"SI")+SUMIFS(COMPRAS!BY:BY,COMPRAS!BX:BX,V83,COMPRAS!DD:DD,"SI") -> 0 | AE83: =SUMIFS(COMPRAS!BI:BI,COMPRAS!BF:BF,V83,COMPRAS!DD:DD,"SI")+SUMIFS(COMPRAS!BR:BR,COMPRAS!BO:BO,V83,COMPRAS!DD:DD,"SI")+SUMIFS(COMPRAS!CA:CA,COMPRAS!BX:BX,V83,COMPRAS!DD:DD,"SI") -> 0
U84: Por RF: Inversiones en títulos valores en renta fija gravados | V84: 323M | X84: =+SUMIFS(COMPRAS!BG:BG,COMPRAS!BF:BF,V84,COMPRAS!DD:DD,"SI")+SUMIFS(COMPRAS!BP:BP,COMPRAS!BO:BO,V84,COMPRAS!DD:DD,"SI")+SUMIFS(COMPRAS!BY:BY,COMPRAS!BX:BX,V84,COMPRAS!DD:DD,"SI") -> 0 | AE84: =SUMIFS(COMPRAS!BI:BI,COMPRAS!BF:BF,V84,COMPRAS!DD:DD,"SI")+SUMIFS(COMPRAS!BR:BR,COMPRAS!BO:BO,V84,COMPRAS!DD:DD,"SI")+SUMIFS(COMPRAS!CA:CA,COMPRAS!BX:BX,V84,COMPRAS!DD:DD,"SI") -> 0
U85: Por RF: Intereses pagados por entidades del sector público a favor de sujetos pasivos | V85: 323P | X85: =+SUMIFS(COMPRAS!BG:BG,COMPRAS!BF:BF,V85,COMPRAS!DD:DD,"SI")+SUMIFS(COMPRAS!BP:BP,COMPRAS!BO:BO,V85,COMPRAS!DD:DD,"SI")+SUMIFS(COMPRAS!BY:BY,COMPRAS!BX:BX,V85,COMPRAS!DD:DD,"SI") -> 0 | AE85: =SUMIFS(COMPRAS!BI:BI,COMPRAS!BF:BF,V85,COMPRAS!DD:DD,"SI")+SUMIFS(COMPRAS!BR:BR,COMPRAS!BO:BO,V85,COMPRAS!DD:DD,"SI")+SUMIFS(COMPRAS!CA:CA,COMPRAS!BX:BX,V85,COMPRAS!DD:DD,"SI") -> 0
U86: Por RF: Otros intereses y rendimientos financieros gravados | V86: 323Q | X86: =+SUMIFS(COMPRAS!BG:BG,COMPRAS!BF:BF,V86,COMPRAS!DD:DD,"SI")+SUMIFS(COMPRAS!BP:BP,COMPRAS!BO:BO,V86,COMPRAS!DD:DD,"SI")+SUMIFS(COMPRAS!BY:BY,COMPRAS!BX:BX,V86,COMPRAS!DD:DD,"SI") -> 0 | AE86: =SUMIFS(COMPRAS!BI:BI,COMPRAS!BF:BF,V86,COMPRAS!DD:DD,"SI")+SUMIFS(COMPRAS!BR:BR,COMPRAS!BO:BO,V86,COMPRAS!DD:DD,"SI")+SUMIFS(COMPRAS!CA:CA,COMPRAS!BX:BX,V86,COMPRAS!DD:DD,"SI") -> 0
U87: Pagos y créditos en cuenta efectuados por el BCE y los depósitos centralizados de valores, en calidad de intermediarios, a instituciones del sistema financiero por cuenta de otras personas naturales y sociedades | V87: 323S | X87: =+SUMIFS(COMPRAS!BG:BG,COMPRAS!BF:BF,V87,COMPRAS!DD:DD,"SI")+SUMIFS(COMPRAS!BP:BP,COMPRAS!BO:BO,V87,COMPRAS!DD:DD,"SI")+SUMIFS(COMPRAS!BY:BY,COMPRAS!BX:BX,V87,COMPRAS!DD:DD,"SI") -> 0 | AE87: =SUMIFS(COMPRAS!BI:BI,COMPRAS!BF:BF,V87,COMPRAS!DD:DD,"SI")+SUMIFS(COMPRAS!BR:BR,COMPRAS!BO:BO,V87,COMPRAS!DD:DD,"SI")+SUMIFS(COMPRAS!CA:CA,COMPRAS!BX:BX,V87,COMPRAS!DD:DD,"SI") -> 0
A88: RENDIMIENTOS FINANCIEROS ENTRE INSTITUCIONES DEL SISTEMA FINANCIERO Y ENTIDADES ECONOMIA POPULAR Y SOLIDARIA | V88: 324 | W88: + | X88: =SUM(X89:AA91) -> 0 | AC88: 374 | AD88: + | AE88: =SUM(AE89:AH91) -> 0
U89: Por RF: Intereses en operaciones de crédito entre instituciones del sistema financiero y entidades economía popular y solidaria. | V89: 324A | X89: =+SUMIFS(COMPRAS!BG:BG,COMPRAS!BF:BF,V89,COMPRAS!DD:DD,"SI")+SUMIFS(COMPRAS!BP:BP,COMPRAS!BO:BO,V89,COMPRAS!DD:DD,"SI")+SUMIFS(COMPRAS!BY:BY,COMPRAS!BX:BX,V89,COMPRAS!DD:DD,"SI") -> 0 | AE89: =SUMIFS(COMPRAS!BI:BI,COMPRAS!BF:BF,V89,COMPRAS!DD:DD,"SI")+SUMIFS(COMPRAS!BR:BR,COMPRAS!BO:BO,V89,COMPRAS!DD:DD,"SI")+SUMIFS(COMPRAS!CA:CA,COMPRAS!BX:BX,V89,COMPRAS!DD:DD,"SI") -> 0
U90: Por RF: Por inversiones entre instituciones del sistema financiero y entidades economía popular y solidaria. | V90: 324B | X90: =+SUMIFS(COMPRAS!BG:BG,COMPRAS!BF:BF,V90,COMPRAS!DD:DD,"SI")+SUMIFS(COMPRAS!BP:BP,COMPRAS!BO:BO,V90,COMPRAS!DD:DD,"SI")+SUMIFS(COMPRAS!BY:BY,COMPRAS!BX:BX,V90,COMPRAS!DD:DD,"SI") -> 0 | AE90: =SUMIFS(COMPRAS!BI:BI,COMPRAS!BF:BF,V90,COMPRAS!DD:DD,"SI")+SUMIFS(COMPRAS!BR:BR,COMPRAS!BO:BO,V90,COMPRAS!DD:DD,"SI")+SUMIFS(COMPRAS!CA:CA,COMPRAS!BX:BX,V90,COMPRAS!DD:DD,"SI") -> 0
U91: Pagos y créditos en cuenta efectuados por el BCE y los depósitos centralizados de valores, en calidad de intermediarios, a instituciones del sistema financiero por cuenta de otras instituciones del sistema financiero | V91: 324C | X91: =+SUMIFS(COMPRAS!BG:BG,COMPRAS!BF:BF,V91,COMPRAS!DD:DD,"SI")+SUMIFS(COMPRAS!BP:BP,COMPRAS!BO:BO,V91,COMPRAS!DD:DD,"SI")+SUMIFS(COMPRAS!BY:BY,COMPRAS!BX:BX,V91,COMPRAS!DD:DD,"SI") -> 0 | AE91: =SUMIFS(COMPRAS!BI:BI,COMPRAS!BF:BF,V91,COMPRAS!DD:DD,"SI")+SUMIFS(COMPRAS!BR:BR,COMPRAS!BO:BO,V91,COMPRAS!DD:DD,"SI")+SUMIFS(COMPRAS!CA:CA,COMPRAS!BX:BX,V91,COMPRAS!DD:DD,"SI") -> 0
A92: OTROS RENDIMIENTOS FINANCIEROS 0% | V92: 3230 | W92: + | X92: =SUM(X93:AA98) -> 0
U93: Por RF: depósito a plazo fijo exentos | V93: 323E2 | X93: =+SUMIFS(COMPRAS!BG:BG,COMPRAS!BF:BF,V93,COMPRAS!DD:DD,"SI")+SUMIFS(COMPRAS!BP:BP,COMPRAS!BO:BO,V93,COMPRAS!DD:DD,"SI")+SUMIFS(COMPRAS!BY:BY,COMPRAS!BX:BX,V93,COMPRAS!DD:DD,"SI") -> 0
U94: Por RF: Inversiones en títulos valores en renta fija exentos | V94: 323N | X94: =+SUMIFS(COMPRAS!BG:BG,COMPRAS!BF:BF,V94,COMPRAS!DD:DD,"SI")+SUMIFS(COMPRAS!BP:BP,COMPRAS!BO:BO,V94,COMPRAS!DD:DD,"SI")+SUMIFS(COMPRAS!BY:BY,COMPRAS!BX:BX,V94,COMPRAS!DD:DD,"SI") -> 0
U95: Por RF: Intereses pagados a bancos y otras entidades sometidas al control de la Superintendencia de Bancos y de la Economía Popular y Solidaria | V95: 323O | X95: =+SUMIFS(COMPRAS!BG:BG,COMPRAS!BF:BF,V95,COMPRAS!DD:DD,"SI")+SUMIFS(COMPRAS!BP:BP,COMPRAS!BO:BO,V95,COMPRAS!DD:DD,"SI")+SUMIFS(COMPRAS!BY:BY,COMPRAS!BX:BX,V95,COMPRAS!DD:DD,"SI") -> 0
U96: Por RF: Otros intereses y rendimientos financieros exentos | V96: 323R | X96: =+SUMIFS(COMPRAS!BG:BG,COMPRAS!BF:BF,V96,COMPRAS!DD:DD,"SI")+SUMIFS(COMPRAS!BP:BP,COMPRAS!BO:BO,V96,COMPRAS!DD:DD,"SI")+SUMIFS(COMPRAS!BY:BY,COMPRAS!BX:BX,V96,COMPRAS!DD:DD,"SI") -> 0
U97: Rendimientos financieros originados en la deuda pública ecuatoriana | V97: 323T | X97: =+SUMIFS(COMPRAS!BG:BG,COMPRAS!BF:BF,V97,COMPRAS!DD:DD,"SI")+SUMIFS(COMPRAS!BP:BP,COMPRAS!BO:BO,V97,COMPRAS!DD:DD,"SI")+SUMIFS(COMPRAS!BY:BY,COMPRAS!BX:BX,V97,COMPRAS!DD:DD,"SI") -> 0
U98: Rendimientos financieros originados en títulos valores de obligaciones de 360 días o más para el financiamiento de proyectos públicos en asociación público-privada | V98: 323U | X98: =+SUMIFS(COMPRAS!BG:BG,COMPRAS!BF:BF,V98,COMPRAS!DD:DD,"SI")+SUMIFS(COMPRAS!BP:BP,COMPRAS!BO:BO,V98,COMPRAS!DD:DD,"SI")+SUMIFS(COMPRAS!BY:BY,COMPRAS!BX:BX,V98,COMPRAS!DD:DD,"SI") -> 0
A99: DIVIDENDOS | D99: ANTICIPO DIVIDENDOS | V99: 325 | W99: + | X99: =SUM(X100:AA101) -> 0 | AC99: 375 | AD99: + | AE99: =SUM(AE100:AH101) -> 0
U100: Anticipo dividendos | V100: 325 | X100: =+SUMIFS(COMPRAS!BG:BG,COMPRAS!BF:BF,V100,COMPRAS!DD:DD,"SI")+SUMIFS(COMPRAS!BP:BP,COMPRAS!BO:BO,V100,COMPRAS!DD:DD,"SI")+SUMIFS(COMPRAS!BY:BY,COMPRAS!BX:BX,V100,COMPRAS!DD:DD,"SI") -> 0 | AE100: =SUMIFS(COMPRAS!BI:BI,COMPRAS!BF:BF,V100,COMPRAS!DD:DD,"SI")+SUMIFS(COMPRAS!BR:BR,COMPRAS!BO:BO,V100,COMPRAS!DD:DD,"SI")+SUMIFS(COMPRAS!CA:CA,COMPRAS!BX:BX,V100,COMPRAS!DD:DD,"SI") -> 0
U101: Dividendos anticipados préstamos accionistas, beneficiarios o partìcipes | V101: 325A | X101: =+SUMIFS(COMPRAS!BG:BG,COMPRAS!BF:BF,V101,COMPRAS!DD:DD,"SI")+SUMIFS(COMPRAS!BP:BP,COMPRAS!BO:BO,V101,COMPRAS!DD:DD,"SI")+SUMIFS(COMPRAS!BY:BY,COMPRAS!BX:BX,V101,COMPRAS!DD:DD,"SI") -> 0 | AE101: =SUMIFS(COMPRAS!BI:BI,COMPRAS!BF:BF,V101,COMPRAS!DD:DD,"SI")+SUMIFS(COMPRAS!BR:BR,COMPRAS!BO:BO,V101,COMPRAS!DD:DD,"SI")+SUMIFS(COMPRAS!CA:CA,COMPRAS!BX:BX,V101,COMPRAS!DD:DD,"SI") -> 0
D102: DIVIDENDOS EXENTOS (POR NO SUPERAR LA FRANJA EXENTA O BENEFICIO DE OTRAS LEYES) | V102: 3250 | W102: + | X102: =+SUMIFS(COMPRAS!BG:BG,COMPRAS!BF:BF,V102,COMPRAS!DD:DD,"SI")+SUMIFS(COMPRAS!BP:BP,COMPRAS!BO:BO,V102,COMPRAS!DD:DD,"SI")+SUMIFS(COMPRAS!BY:BY,COMPRAS!BX:BX,V102,COMPRAS!DD:DD,"SI") -> 0
D103: DIVIDENDOS DISTRIBUIDOS QUE CORRESPONDAN AL IMPUESTO A LA RENTA ÚNICO ESTABLECIDO EN EL ART. 27 DE LA LRTI | V103: 326 | W103: + | X103: =+SUMIFS(COMPRAS!BG:BG,COMPRAS!BF:BF,V103,COMPRAS!DD:DD,"SI")+SUMIFS(COMPRAS!BP:BP,COMPRAS!BO:BO,V103,COMPRAS!DD:DD,"SI")+SUMIFS(COMPRAS!BY:BY,COMPRAS!BX:BX,V103,COMPRAS!DD:DD,"SI") -> 0 | AC103: 376 | AD103: + | AE103: =SUMIFS(COMPRAS!BI:BI,COMPRAS!BF:BF,V103,COMPRAS!DD:DD,"SI")+SUMIFS(COMPRAS!BR:BR,COMPRAS!BO:BO,V103,COMPRAS!DD:DD,"SI")+SUMIFS(COMPRAS!CA:CA,COMPRAS!BX:BX,V103,COMPRAS!DD:DD,"SI") -> 0
D104: DIVIDENDOS DISTRIBUIDOS A PERSONAS NATURALES RESIDENTES | V104: 327 | W104: + | X104: =+SUMIFS(COMPRAS!BG:BG,COMPRAS!BF:BF,V104,COMPRAS!DD:DD,"SI")+SUMIFS(COMPRAS!BP:BP,COMPRAS!BO:BO,V104,COMPRAS!DD:DD,"SI")+SUMIFS(COMPRAS!BY:BY,COMPRAS!BX:BX,V104,COMPRAS!DD:DD,"SI") -> 0 | AC104: 377 | AD104: + | AE104: =SUMIFS(COMPRAS!BI:BI,COMPRAS!BF:BF,V104,COMPRAS!DD:DD,"SI")+SUMIFS(COMPRAS!BR:BR,COMPRAS!BO:BO,V104,COMPRAS!DD:DD,"SI")+SUMIFS(COMPRAS!CA:CA,COMPRAS!BX:BX,V104,COMPRAS!DD:DD,"SI") -> 0
...

Sheet 104
D1: FORMULARIO 104 | I1: DECLARACIÓN DEL IMPUESTO AL VALOR AGREGADO | AF1: No.
D2: RESOLUCIÓN Nº XXX
A3: 100 IDENTIFICACIÓN DE LA DECLARACIÓN
C4: =IF(C5,C6,0) -> 0 | D4: =IF(D5,D6,0) -> 0 | E4: =IF(E5,E6,0) -> 0 | F4: =IF(F5,F6,0) -> 4 | G4: =IF(G5,G6,0) -> 0 | H4: =IF(H5,H6,0) -> 0 | I4: =IF(I5,I6,0) -> 0 | J4: =IF(J5,J6,0) -> 0 | ... N4: =IF(N5,N6,0) -> 0 | P4: SELECCIONE PERIODO | T4: 4 | V4: <<-- Seleccione el periodo a declarar
C5: =IF($T$4=LIQ_IMPUESTOS!$C5,TRUE,FALSE) -> FALSE | D5: =IF($T$4=LIQ_IMPUESTOS!$C6,TRUE,FALSE) -> FALSE | E5: =IF($T$4=LIQ_IMPUESTOS!$C7,TRUE,FALSE) -> FALSE | F5: =IF($T$4=LIQ_IMPUESTOS!$C8,TRUE,FALSE) -> TRUE | G5: =IF($T$4=LIQ_IMPUESTOS!$C9,TRUE,FALSE) -> FALSE | H5: =IF($T$4=LIQ_IMPUESTOS!$C10,TRUE,FALSE) -> FALSE | I5: =IF($T$4=LIQ_IMPUESTOS!$C11,TRUE,FALSE) -> FALSE | J5: =IF($T$4=LIQ_IMPUESTOS!$C12,TRUE,FALSE) -> FALSE | K5: =IF($T$4=LIQ_IMPUESTOS!$C13,TRUE,FALSE) -> FALSE | L5: =IF($T$4=LIQ_IMPUESTOS!$C14,TRUE,FALSE) -> FALSE | M5: =IF($T$4=LIQ_IMPUESTOS!$C15,TRUE,FALSE) -> FALSE | N5: =IF($T$4=LIQ_IMPUESTOS!$C16,TRUE,FALSE) -> FALSE
A6: 101 | B6: MES | C6: 1 | D6: 2 | E6: 3 | F6: 4 | G6: 5 | H6: 6 | I6: 7 | J6: 8 | K6: 9 | L6: 10 | M6: 11 | N6: 12 | P6: 102 | Q6: AÑO | R6: =MID(XLSperiodo,1,1) -> 2 | S6: =MID(XLSperiodo,2,1) -> 0 | T6: =MID(XLSperiodo,3,1) -> 2 | U6: =MID(XLSperiodo,4,1) -> 6 | W6: 104 | X6: Nº. DE FORMULARIO QUE SUSTITUYE | AG6: 203 | AH6: Nº. DECRETO TURISMO
A8: 200 IDENTIFICACIÓN DEL SUJETO PASIVO
A9: 201 | B9: RUC | O9: 202 | P9: RAZÓN SOCIAL O APELLIDOS Y NOMBRES COMPLETOS
B10: =Parametros!D4 -> 0917809451001 | P10: =+Parametros!D5 -> GARCIA RODRIGUEZ CHARLES MILTON
A12: RESUMEN DE VENTAS Y OTRAS OPERACIONES DEL PERÍODO QUE DECLARA | P12: VALOR BRUTO | W12: VALOR NETO (VALOR BRUTO - N/C) | AE12: IMPUESTO GENERADO
A13: Ventas locales (excluye activos fijos) gravadas tarifa diferente de cero | P13: 401 | Q13: + | R13: =SUMIFS(VENTAS!BG:BG,VENTAS!AJ:AJ,W13,VENTAS!BF:BF,"SI")+SUMIFS(VENTAS!BH:BH,VENTAS!AL:AL,W13,VENTAS!BF:BF,"SI")+SUMIFS(VENTAS!BI:BI,VENTAS!AN:AN,W13,VENTAS!BF:BF,"SI") -> 23234.98 | W13: 411 | X13: + | Y13: =SUMIFS(VENTAS!AK:AK,VENTAS!AJ:AJ,W13,VENTAS!BF:BF,"SI")+SUMIFS(VENTAS!AM:AM,VENTAS!AL:AL,W13,VENTAS!BF:BF,"SI")+SUMIFS(VENTAS!AO:AO,VENTAS!AN:AN,W13,VENTAS!BF:BF,"SI") -> 23234.98 | Z13: =IF(Y13<0,0,Y13) -> 23234.98 | AE13: 421 | AF13: + | AG13: =IF(Z13>0,SUMIFS(VENTAS!R:R,VENTAS!AJ:AJ,W13,VENTAS!BF:BF,"SI")+SUMIFS(VENTAS!R:R,VENTAS!AL:AL,W13,VENTAS!BF:BF,"SI")+SUMIFS(VENTAS!R:R,VENTAS!AN:AN,W13,VENTAS!BF:BF,"SI"),0) -> 3485.73
A14: Ventas de activos fijos gravadas tarifa diferente de cero | P14: 402 | Q14: + | R14: =SUMIFS(VENTAS!BG:BG,VENTAS!AJ:AJ,W14,VENTAS!BF:BF,"SI")+SUMIFS(VENTAS!BH:BH,VENTAS!AL:AL,W14,VENTAS!BF:BF,"SI")+SUMIFS(VENTAS!BI:BI,VENTAS!AN:AN,W14,VENTAS!BF:BF,"SI") -> 0 | W14: 412 | X14: + | Y14: =SUMIFS(VENTAS!AK:AK,VENTAS!AJ:AJ,W14,VENTAS!BF:BF,"SI")+SUMIFS(VENTAS!AM:AM,VENTAS!AL:AL,W14,VENTAS!BF:BF,"SI")+SUMIFS(VENTAS!AO:AO,VENTAS!AN:AN,W14,VENTAS!BF:BF,"SI") -> 0 | Z14: =IF(Y14<0,0,Y14) -> 0 | AE14: 422 | AF14: + | AG14: =IF(Z14>0,SUMIFS(VENTAS!R:R,VENTAS!AJ:AJ,W14,VENTAS!BF:BF,"SI")+SUMIFS(VENTAS!R:R,VENTAS!AL:AL,W14,VENTAS!BF:BF,"SI")+SUMIFS(VENTAS!R:R,VENTAS!AN:AN,W14,VENTAS!BF:BF,"SI"),0) -> 0
A15: Ventas locales (excluye activos fijos) gravadas tarifa diferente de cero (TARIFA VARIABLE) | P15: 410 | Q15: + | R15: =SUMIFS(VENTAS!BG:BG,VENTAS!AJ:AJ,W15,VENTAS!BF:BF,"SI")+SUMIFS(VENTAS!BH:BH,VENTAS!AL:AL,W15,VENTAS!BF:BF,"SI")+SUMIFS(VENTAS!BI:BI,VENTAS!AN:AN,W15,VENTAS!BF:BF,"SI") -> 0 | W15: 420 | X15: + | Y15: =SUMIFS(VENTAS!AK:AK,VENTAS!AJ:AJ,W15,VENTAS!BF:BF,"SI")+SUMIFS(VENTAS!AM:AM,VENTAS!AL:AL,W15,VENTAS!BF:BF,"SI")+SUMIFS(VENTAS!AO:AO,VENTAS!AN:AN,W15,VENTAS!BF:BF,"SI") -> 0 | Z15: =IF(Y15<0,0,Y15) -> 0 | AE15: 430 | AF15: + | AG15: =IF(Z15>0,SUMIFS(VENTAS!X:X,VENTAS!AJ:AJ,W15,VENTAS!BF:BF,"SI")+SUMIFS(VENTAS!X:X,VENTAS!AL:AL,W15,VENTAS!BF:BF,"SI")+SUMIFS(VENTAS!X:X,VENTAS!AN:AN,W15,VENTAS!BF:BF,"SI"),0) -> 0
A16: Ventas locales (excluye activos fijos) gravadas tarifa 5% | P16: 425 | Q16: + | R16: =SUMIFS(VENTAS!BG:BG,VENTAS!AJ:AJ,W16,VENTAS!BF:BF,"SI")+SUMIFS(VENTAS!BH:BH,VENTAS!AL:AL,W16,VENTAS!BF:BF,"SI")+SUMIFS(VENTAS!BI:BI,VENTAS!AN:AN,W16,VENTAS!BF:BF,"SI") -> 0 | W16: 435 | X16: + | Y16: =SUMIFS(VENTAS!AK:AK,VENTAS!AJ:AJ,W16,VENTAS!BF:BF,"SI")+SUMIFS(VENTAS!AM:AM,VENTAS!AL:AL,W16,VENTAS!BF:BF,"SI")+SUMIFS(VENTAS!AO:AO,VENTAS!AN:AN,W16,VENTAS!BF:BF,"SI") -> 0 | Z16: =IF(Y16<0,0,Y16) -> 0 | AE16: 445 | AF16: + | AG16: =IF(Z16>0,SUMIFS(VENTAS!U:U,VENTAS!AJ:AJ,W16,VENTAS!BF:BF,"SI")+SUMIFS(VENTAS!U:U,VENTAS!AL:AL,W16,VENTAS!BF:BF,"SI")+SUMIFS(VENTAS!U:U,VENTAS!AN:AN,W16,VENTAS!BF:BF,"SI"),0) -> 0
A17: IVA generado en la diferencia entre ventas y notas de crédito con distinta tarifa (ajuste a pagar) | AE17: 423 | AF17: + | AG17: 0
A18: IVA generado en la diferencia entre ventas y notas de crédito con distinta tarifa (ajuste a favor) | AE18: 424 | AF18: + | AG18: 0
A19: Ventas locales (excluye activos fijos) gravadas tarifa 0% que no dan derecho a crédito tributario | P19: 403 | Q19: + | R19: =SUMIFS(VENTAS!BG:BG,VENTAS!AJ:AJ,W19,VENTAS!BF:BF,"SI")+SUMIFS(VENTAS!BH:BH,VENTAS!AL:AL,W19,VENTAS!BF:BF,"SI")+SUMIFS(VENTAS!BI:BI,VENTAS!AN:AN,W19,VENTAS!BF:BF,"SI") -> 0 | W19: 413 | X19: + | Y19: =SUMIFS(VENTAS!AK:AK,VENTAS!AJ:AJ,W19,VENTAS!BF:BF,"SI")+SUMIFS(VENTAS!AM:AM,VENTAS!AL:AL,W19,VENTAS!BF:BF,"SI")+SUMIFS(VENTAS!AO:AO,VENTAS!AN:AN,W19,VENTAS!BF:BF,"SI") -> 0 | Z19: =IF(Y19<0,0,Y19) -> 0
A20: Ventas de activos fijos gravadas tarifa 0% que no dan derecho a crédito tributario | P20: 404 | Q20: + | R20: =SUMIFS(VENTAS!BG:BG,VENTAS!AJ:AJ,W20,VENTAS!BF:BF,"SI")+SUMIFS(VENTAS!BH:BH,VENTAS!AL:AL,W20,VENTAS!BF:BF,"SI")+SUMIFS(VENTAS!BI:BI,VENTAS!AN:AN,W20,VENTAS!BF:BF,"SI") -> 0 | W20: 414 | X20: + | Y20: =SUMIFS(VENTAS!AK:AK,VENTAS!AJ:AJ,W20,VENTAS!BF:BF,"SI")+SUMIFS(VENTAS!AM:AM,VENTAS!AL:AL,W20,VENTAS!BF:BF,"SI")+SUMIFS(VENTAS!AO:AO,VENTAS!AN:AN,W20,VENTAS!BF:BF,"SI") -> 0 | Z20: =IF(Y20<0,0,Y20) -> 0
A21: Ventas locales (excluye activos fijos) gravadas tarifa 0% que dan derecho a crédito tributario | P21: 405 | Q21: + | R21: =SUMIFS(VENTAS!BG:BG,VENTAS!AJ:AJ,W21,VENTAS!BF:BF,"SI")+SUMIFS(VENTAS!BH:BH,VENTAS!AL:AL,W21,VENTAS!BF:BF,"SI")+SUMIFS(VENTAS!BI:BI,VENTAS!AN:AN,W21,VENTAS!BF:BF,"SI") -> 0 | W21: 415 | X21: + | Y21: =SUMIFS(VENTAS!AK:AK,VENTAS!AJ:AJ,W21,VENTAS!BF:BF,"SI")+SUMIFS(VENTAS!AM:AM,VENTAS!AL:AL,W21,VENTAS!BF:BF,"SI")+SUMIFS(VENTAS!AO:AO,VENTAS!AN:AN,W21,VENTAS!BF:BF,"SI") -> 0 | Z21: =IF(Y21<0,0,Y21) -> 0
A22: Ventas de activos fijos gravadas tarifa 0% que dan derecho a crédito tributario | P22: 406 | Q22: + | R22: =SUMIFS(VENTAS!BG:BG,VENTAS!AJ:AJ,W22,VENTAS!BF:BF,"SI")+SUMIFS(VENTAS!BH:BH,VENTAS!AL:AL,W22,VENTAS!BF:BF,"SI")+SUMIFS(VENTAS!BI:BI,VENTAS!AN:AN,W22,VENTAS!BF:BF,"SI") -> 0 | W22: 416 | X22: + | Y22: =SUMIFS(VENTAS!AK:AK,VENTAS!AJ:AJ,W22,VENTAS!BF:BF,"SI")+SUMIFS(VENTAS!AM:AM,VENTAS!AL:AL,W22,VENTAS!BF:BF,"SI")+SUMIFS(VENTAS!AO:AO,VENTAS!AN:AN,W22,VENTAS!BF:BF,"SI") -> 0 | Z22: =IF(Y22<0,0,Y22) -> 0
A23: Exportaciones de bienes | P23: 407 | Q23: + | R23: =SUMIFS(VENTAS!BG:BG,VENTAS!AJ:AJ,W23,VENTAS!BF:BF,"SI")+SUMIFS(VENTAS!BH:BH,VENTAS!AL:AL,W23,VENTAS!BF:BF,"SI")+SUMIFS(VENTAS!BI:BI,VENTAS!AN:AN,W23,VENTAS!BF:BF,"SI")+SUMIFS(EXPORTACIONES!AN:AN,EXPORTACIONES!AG:AG,W23,EXPORTACIONES!AM:AM,"SI")+SUMIFS(EXPORTACIONES!AO:AO,EXPORTACIONES!AI:AI,W23,EXPORTACIONES!AM:AM,"SI") -> 0 | W23: 417 | X23: + | Y23: =SUMIFS(VENTAS!AK:AK,VENTAS!AJ:AJ,W23,VENTAS!BF:BF,"SI")+SUMIFS(VENTAS!AM:AM,VENTAS!AL:AL,W23,VENTAS!BF:BF,"SI")+SUMIFS(VENTAS!AO:AO,VENTAS!AN:AN,W23,VENTAS!BF:BF,"SI")+SUMIFS(EXPORTACIONES!AH:AH,EXPORTACIONES!AG:AG,W23,EXPORTACIONES!AM:AM,"SI")+SUMIFS(EXPORTACIONES!AJ:AJ,EXPORTACIONES!AI:AI,W23,EXPORTACIONES!AM:AM,"SI") -> 0 | Z23: =IF(Y23<0,0,Y23) -> 0
A24: Exportaciones de servicios y/o derechos | P24: 408 | Q24: + | R24: =SUMIFS(VENTAS!BG:BG,VENTAS!AJ:AJ,W24,VENTAS!BF:BF,"SI")+SUMIFS(VENTAS!BH:BH,VENTAS!AL:AL,W24,VENTAS!BF:BF,"SI")+SUMIFS(VENTAS!BI:BI,VENTAS!AN:AN,W24,VENTAS!BF:BF,"SI")+SUMIFS(EXPORTACIONES!AN:AN,EXPORTACIONES!AG:AG,W24,EXPORTACIONES!AM:AM,"SI")+SUMIFS(EXPORTACIONES!AO:AO,EXPORTACIONES!AI:AI,W24,EXPORTACIONES!AM:AM,"SI") -> 0 | W24: 418 | X24: + | Y24: =SUMIFS(VENTAS!AK:AK,VENTAS!AJ:AJ,W24,VENTAS!BF:BF,"SI")+SUMIFS(VENTAS!AM:AM,VENTAS!AL:AL,W24,VENTAS!BF:BF,"SI")+SUMIFS(VENTAS!AO:AO,VENTAS!AN:AN,W24,VENTAS!BF:BF,"SI")+SUMIFS(EXPORTACIONES!AH:AH,EXPORTACIONES!AG:AG,W24,EXPORTACIONES!AM:AM,"SI")+SUMIFS(EXPORTACIONES!AJ:AJ,EXPORTACIONES!AI:AI,W24,EXPORTACIONES!AM:AM,"SI") -> 0 | Z24: =IF(Y24<0,0,Y24) -> 0
A25: TOTAL VENTAS Y OTRAS OPERACIONES | P25: 409 | Q25: = | R25: =SUM(R13:V24) -> 23234.98 | W25: 419 | X25: = | Y25: =+Z25+X26+X27+X28+X29 -> 23234.98 | Z25: =SUM(Z13:AD24) -> 23234.98 | AE25: 429 | AF25: = | AG25: =IF((SUM(AG13:AK17)-AG18)>0,(SUM(AG13:AK17)-AG18),0) -> 3485.73
A26: Transferencias no objeto o exentas de IVA | P26: 431 | Q26: + | R26: =SUMIFS(VENTAS!BG:BG,VENTAS!AJ:AJ,W26,VENTAS!BF:BF,"SI")+SUMIFS(VENTAS!BH:BH,VENTAS!AL:AL,W26,VENTAS!BF:BF,"SI")+SUMIFS(VENTAS!BI:BI,VENTAS!AN:AN,W26,VENTAS!BF:BF,"SI") -> 0 | W26: 441 | X26: =SUMIFS(VENTAS!AK:AK,VENTAS!AJ:AJ,W26,VENTAS!BF:BF,"SI")+SUMIFS(VENTAS!AM:AM,VENTAS!AL:AL,W26,VENTAS!BF:BF,"SI")+SUMIFS(VENTAS!AO:AO,VENTAS!AN:AN,W26,VENTAS!BF:BF,"SI") -> 0
A27: Notas de crédito tarifa 0% por compensar próximo mes | W27: 442 | X27: =IF(Y19<0,ABS(Y19),0)+IF(Y20<0,ABS(Y20),0)+IF(Y21<0,ABS(Y21),0)+IF(Y22<0,ABS(Y22),0)+IF(Y23<0,ABS(Y23),0)+IF(Y24<0,ABS(Y24),0) -> 0
A28: Notas de crédito tarifa diferente de cero por compensar próximo mes | W28: 443 | X28: =IF(Y13<0,ABS(Y13),0)+IF(Y14<0,ABS(Y14),0)+IF(Y15<0,ABS(Y15),0) -> 0 | AE28: 453 | AF28: =IF(X28>0,ABS(AF29-SUMIF(VENTAS!BF:BF,"SI",VENTAS!R:R)+SUMIF(VENTAS!BF:BF,"SI",VENTAS!U:U)+SUMIF(VENTAS!BF:BF,"SI",VENTAS!X:X)),0) -> 0
A29: Ingresos por reembolso como intermediario / valores facturados por operadoras de transporte / ingresos obtenidos por parte de las sociedades de gestión colectiva como intermediarios (informativo) | P29: 434 | Q29: + | R29: =SUMIFS(VENTAS!BG:BG,VENTAS!AJ:AJ,W29,VENTAS!BF:BF,"SI")+SUMIFS(VENTAS!BH:BH,VENTAS!AL:AL,W29,VENTAS!BF:BF,"SI")+SUMIFS(VENTAS!BI:BI,VENTAS!AN:AN,W29,VENTAS!BF:BF,"SI") -> 0 | W29: 444 | X29: =SUMIFS(VENTAS!AK:AK,VENTAS!AJ:AJ,W29,VENTAS!BF:BF,"SI")+SUMIFS(VENTAS!AM:AM,VENTAS!AL:AL,W29,VENTAS!BF:BF,"SI")+SUMIFS(VENTAS!AO:AO,VENTAS!AN:AN,W29,VENTAS!BF:BF,"SI") -> 0 | AE29: 454 | AF29: =SUMIFS(VENTAS!R:R,VENTAS!AJ:AJ,W29,VENTAS!BF:BF,"SI")+SUMIFS(VENTAS!R:R,VENTAS!AL:AL,W29,VENTAS!BF:BF,"SI")+SUMIFS(VENTAS!R:R,VENTAS!AN:AN,W29,VENTAS!BF:BF,"SI")+SUMIFS(VENTAS!U:U,VENTAS!AJ:AJ,W29,VENTAS!BF:BF,"SI")+SUMIFS(VENTAS!U:U,VENTAS!AL:AL,W29,VENTAS!BF:BF,"SI")+SUMIFS(VENTAS!U:U,VENTAS!AN:AN,W29,VENTAS!BF:BF,"SI")+SUMIFS(VENTAS!X:X,VENTAS!AJ:AJ,W29,VENTAS!BF:BF,"SI")+SUMIFS(VENTAS!X:X,VENTAS!AL:AL,W29,VENTAS!BF:BF,"SI")+SUMIFS(VENTAS!X:X,VENTAS!AN:AN,W29,VENTAS!BF:BF,"SI") -> 0
A31: LIQUIDACIÓN DEL 12 EN EL MES
A33: TOTAL TRANSFERENCIAS GRAVADAS TARIFA DIFERENTE DE CERO A CONTADO ESTE MES | F33: TOTAL TRANSFERENCIAS GRAVADAS TARIFA DIFERENTE DE CERO A CRÉDITO ESTE MES | K33: TOTAL IMPUESTO GENERADO Trasládese campo 429 | P33: IMPUESTO A LIQUIDAR DEL MES ANTERIOR (Trasládese el campo 485 de la declaración del período anterior) | V33: IMPUESTO A LIQUIDAR EN ESTE MES (Mínimo campo 480 x tarifa IVA diferente de cero) | AB33: IMPUESTO A LIQUIDAR EN EL PRÓXIMO MES (482 - 484) | AG33: TOTAL IMPUESTO A LIQUIDAR EN ESTE MES SUMAR 483 + 484
A34: 480 | B34: =+(Z13+Z14)-G34 -> 23234.98 | F34: 481 | G34: 0 | K34: 482 | L34: =+AG25 -> 3485.73 | P34: 483 | Q34: 0 | V34: 484 | W34: =ROUND(B34*15%,2) -> 3485.25 | AB34: 485 | AC34: =+L34-W34 -> 0.48 | AG34: 499 | AH34: =+Q34+W34 -> 3485.25
A36: TOTAL COMPROBANTES DE VENTA EMITIDOS | K36: 111 | L36: =COUNTIFS(VENTAS!BF:BF,"SI",VENTAS!H:H,"18-Documentos autorizados utilizados en ventas excepto N/C N/D") -> 480 | P36: TOTAL COMPROBANTES DE VENTAS ANULADOS | AB36: 113 | AC36: =IF(COUNTIFS(ANULADOS!I:I,"SI",ANULADOS!A:A,"01-Factura")>0,COUNTIFS(ANULADOS!I:I,"SI",ANULADOS!A:A,"01-Factura"),COUNTIFS(VENTAS!BF:BF,"SI",VENTAS!H:H,"00-Comprobante de ventas anulado")) -> 0
A38: RESUMEN DE ADQUISICIONES Y PAGOS DEL PERÍODO QUE DECLARA | P38: VALOR BRUTO | W38: VALOR NETO (VALOR BRUTO - N/C) | AE38: IMPUESTO GENERADO
A39: Adquisiciones y pagos (excluye activos fijos) gravados tarifa diferente de cero (con derecho a crédito tributario) | P39: 500 | Q39: + | R39: =SUMIFS(COMPRAS!DE:DE,COMPRAS!AS:AS,W39,COMPRAS!DC:DC,"SI")+SUMIFS(COMPRAS!DF:DF,COMPRAS!AU:AU,W39,COMPRAS!DC:DC,"SI")+SUMIFS(COMPRAS!DG:DG,COMPRAS!AW:AW,W39,COMPRAS!DC:DC,"SI") -> 35909.6 | W39: 510 | X39: + | Y39: =SUMIFS(COMPRAS!AT:AT,COMPRAS!AS:AS,W39,COMPRAS!DC:DC,"SI")+SUMIFS(COMPRAS!AV:AV,COMPRAS!AU:AU,W39,COMPRAS!DC:DC,"SI")+SUMIFS(COMPRAS!AX:AX,COMPRAS!AW:AW,W39,COMPRAS!DC:DC,"SI") -> 33770.64 | Z39: =IF(Y39<0,0,Y39) -> 33770.64 | AE39: 520 | AF39: + | AG39: =IF(Z39>0,SUMIFS(COMPRAS!Z:Z,COMPRAS!AS:AS,W39,COMPRAS!DC:DC,"SI")+SUMIFS(COMPRAS!Z:Z,COMPRAS!AU:AU,W39,COMPRAS!DC:DC,"SI")+SUMIFS(COMPRAS!Z:Z,COMPRAS!AW:AW,W39,COMPRAS!DC:DC,"SI"),0) -> 5065.61
A40: Adquisiciones locales de activos fijos gravados tarifa diferente de cero (con derecho a crédito tributario) | P40: 501 | Q40: + | R40: =SUMIFS(COMPRAS!DE:DE,COMPRAS!AS:AS,W40,COMPRAS!DC:DC,"SI")+SUMIFS(COMPRAS!DF:DF,COMPRAS!AU:AU,W40,COMPRAS!DC:DC,"SI")+SUMIFS(COMPRAS!DG:DG,COMPRAS!AW:AW,W40,COMPRAS!DC:DC,"SI") -> 0 | W40: 511 | X40: + | Y40: =SUMIFS(COMPRAS!AT:AT,COMPRAS!AS:AS,W40,COMPRAS!DC:DC,"SI")+SUMIFS(COMPRAS!AV:AV,COMPRAS!AU:AU,W40,COMPRAS!DC:DC,"SI")+SUMIFS(COMPRAS!AX:AX,COMPRAS!AW:AW,W40,COMPRAS!DC:DC,"SI") -> 0 | Z40: =IF(Y40<0,0,Y40) -> 0 | AE40: 521 | AF40: + | AG40: =IF(Z40>0,SUMIFS(COMPRAS!Z:Z,COMPRAS!AS:AS,W40,COMPRAS!DC:DC,"SI")+SUMIFS(COMPRAS!Z:Z,COMPRAS!AU:AU,W40,COMPRAS!DC:DC,"SI")+SUMIFS(COMPRAS!Z:Z,COMPRAS!AW:AW,W40,COMPRAS!DC:DC,"SI"),0) -> 0
A41: Adquisiciones y pagos (excluye activos fijos) gravados tarifa diferente de cero (con derecho a créd.trib.tarifa variable) | P41: 530 | Q41: + | R41: =SUMIFS(COMPRAS!DE:DE,COMPRAS!AS:AS,W41,COMPRAS!DC:DC,"SI")+SUMIFS(COMPRAS!DF:DF,COMPRAS!AU:AU,W41,COMPRAS!DC:DC,"SI")+SUMIFS(COMPRAS!DG:DG,COMPRAS!AW:AW,W41,COMPRAS!DC:DC,"SI") -> 0 | W41: 533 | X41: + | Y41: =SUMIFS(COMPRAS!AT:AT,COMPRAS!AS:AS,W41,COMPRAS!DC:DC,"SI")+SUMIFS(COMPRAS!AV:AV,COMPRAS!AU:AU,W41,COMPRAS!DC:DC,"SI")+SUMIFS(COMPRAS!AX:AX,COMPRAS!AW:AW,W41,COMPRAS!DC:DC,"SI") -> 0 | Z41: =IF(Y41<0,0,Y41) -> 0 | AE41: 534 | AF41: + | AG41: =IF(Z41>0,SUMIFS(COMPRAS!AF:AF,COMPRAS!AS:AS,W41,COMPRAS!DC:DC,"SI")+SUMIFS(COMPRAS!AF:AF,COMPRAS!AU:AU,W41,COMPRAS!DC:DC,"SI")+SUMIFS(COMPRAS!AF:AF,COMPRAS!AW:AW,W41,COMPRAS!DC:DC,"SI"),0) -> 0
A42: Adquisiciones y pagos (excluye activos fijos) gravados tarifa 5% (con derecho a crédito tributario) | P42: 540 | Q42: + | R42: =SUMIFS(COMPRAS!DE:DE,COMPRAS!AS:AS,W42,COMPRAS!DC:DC,"SI")+SUMIFS(COMPRAS!DF:DF,COMPRAS!AU:AU,W42,COMPRAS!DC:DC,"SI")+SUMIFS(COMPRAS!DG:DG,COMPRAS!AW:AW,W42,COMPRAS!DC:DC,"SI") -> 0 | W42: 550 | X42: + | Y42: =SUMIFS(COMPRAS!AT:AT,COMPRAS!AS:AS,W42,COMPRAS!DC:DC,"SI")+SUMIFS(COMPRAS!AV:AV,COMPRAS!AU:AU,W42,COMPRAS!DC:DC,"SI")+SUMIFS(COMPRAS!AX:AX,COMPRAS!AW:AW,W42,COMPRAS!DC:DC,"SI") -> 0 | Z42: =IF(Y42<0,0,Y42) -> 0 | AE42: 560 | AF42: + | AG42: =IF(Z42>0,SUMIFS(COMPRAS!AC:AC,COMPRAS!AS:AS,W42,COMPRAS!DC:DC,"SI")+SUMIFS(COMPRAS!AC:AC,COMPRAS!AU:AU,W42,COMPRAS!DC:DC,"SI")+SUMIFS(COMPRAS!AC:AC,COMPRAS!AW:AW,W42,COMPRAS!DC:DC,"SI"),0) -> 0
A43: Otras adquisiciones y pagos gravados tarifa diferente de cero (sin derecho a crédito tributario) | P43: 502 | Q43: + | R43: =SUMIFS(COMPRAS!DE:DE,COMPRAS!AS:AS,W43,COMPRAS!DC:DC,"SI")+SUMIFS(COMPRAS!DF:DF,COMPRAS!AU:AU,W43,COMPRAS!DC:DC,"SI")+SUMIFS(COMPRAS!DG:DG,COMPRAS!AW:AW,W43,COMPRAS!DC:DC,"SI") -> 0 | W43: 512 | X43: + | Y43: =SUMIFS(COMPRAS!AT:AT,COMPRAS!AS:AS,W43,COMPRAS!DC:DC,"SI")+SUMIFS(COMPRAS!AV:AV,COMPRAS!AU:AU,W43,COMPRAS!DC:DC,"SI")+SUMIFS(COMPRAS!AX:AX,COMPRAS!AW:AW,W43,COMPRAS!DC:DC,"SI") -> 0 | Z43: =IF(Y43<0,0,Y43) -> 0 | AE43: 522 | AF43: + | AG43: =IF(Z43>0,SUMIFS(COMPRAS!DJ:DJ,COMPRAS!AS:AS,W43,COMPRAS!DC:DC,"SI")+SUMIFS(COMPRAS!DJ:DJ,COMPRAS!AU:AU,W43,COMPRAS!DC:DC,"SI")+SUMIFS(COMPRAS!DJ:DJ,COMPRAS!AW:AW,W43,COMPRAS!DC:DC,"SI"),0) -> 0
A44: Importaciones de servicios y/o derechos gravados tarifa diferente de cero | P44: 503 | Q44: + | R44: =SUMIFS(COMPRAS!DE:DE,COMPRAS!AS:AS,W44,COMPRAS!DC:DC,"SI")+SUMIFS(COMPRAS!DF:DF,COMPRAS!AU:AU,W44,COMPRAS!DC:DC,"SI")+SUMIFS(COMPRAS!DG:DG,COMPRAS!AW:AW,W44,COMPRAS!DC:DC,"SI") -> 0 | W44: 513 | X44: + | Y44: =SUMIFS(COMPRAS!AT:AT,COMPRAS!AS:AS,W44,COMPRAS!DC:DC,"SI")+SUMIFS(COMPRAS!AV:AV,COMPRAS!AU:AU,W44,COMPRAS!DC:DC,"SI")+SUMIFS(COMPRAS!AX:AX,COMPRAS!AW:AW,W44,COMPRAS!DC:DC,"SI") -> 0 | Z44: =IF(Y44<0,0,Y44) -> 0 | AE44: 523 | AF44: + | AG44: =IF(Z44>0,SUMIFS(COMPRAS!Z:Z,COMPRAS!AS:AS,W44,COMPRAS!DC:DC,"SI")+SUMIFS(COMPRAS!Z:Z,COMPRAS!AU:AU,W44,COMPRAS!DC:DC,"SI")+SUMIFS(COMPRAS!Z:Z,COMPRAS!AW:AW,W44,COMPRAS!DC:DC,"SI"),0) -> 0
A45: Importaciones de bienes (excluye activos fijos) gravados tarifa diferente de cero | P45: 504 | Q45: + | R45: =SUMIFS(COMPRAS!DE:DE,COMPRAS!AS:AS,W45,COMPRAS!DC:DC,"SI")+SUMIFS(COMPRAS!DF:DF,COMPRAS!AU:AU,W45,COMPRAS!DC:DC,"SI")+SUMIFS(COMPRAS!DG:DG,COMPRAS!AW:AW,W45,COMPRAS!DC:DC,"SI") -> 0 | W45: 514 | X45: + | Y45: =SUMIFS(COMPRAS!AT:AT,COMPRAS!AS:AS,W45,COMPRAS!DC:DC,"SI")+SUMIFS(COMPRAS!AV:AV,COMPRAS!AU:AU,W45,COMPRAS!DC:DC,"SI")+SUMIFS(COMPRAS!AX:AX,COMPRAS!AW:AW,W45,COMPRAS!DC:DC,"SI") -> 0 | Z45: =IF(Y45<0,0,Y45) -> 0 | AE45: 524 | AF45: + | AG45: =IF(Z45>0,SUMIFS(COMPRAS!Z:Z,COMPRAS!AS:AS,W45,COMPRAS!DC:DC,"SI")+SUMIFS(COMPRAS!Z:Z,COMPRAS!AU:AU,W45,COMPRAS!DC:DC,"SI")+SUMIFS(COMPRAS!Z:Z,COMPRAS!AW:AW,W45,COMPRAS!DC:DC,"SI"),0) -> 0
A46: Importaciones de activos fijos gravados tarifa diferente de cero | P46: 505 | Q46: + | R46: =SUMIFS(COMPRAS!DE:DE,COMPRAS!AS:AS,W46,COMPRAS!DC:DC,"SI")+SUMIFS(COMPRAS!DF:DF,COMPRAS!AU:AU,W46,COMPRAS!DC:DC,"SI")+SUMIFS(COMPRAS!DG:DG,COMPRAS!AW:AW,W46,COMPRAS!DC:DC,"SI") -> 0 | W46: 515 | X46: + | Y46: =SUMIFS(COMPRAS!AT:AT,COMPRAS!AS:AS,W46,COMPRAS!DC:DC,"SI")+SUMIFS(COMPRAS!AV:AV,COMPRAS!AU:AU,W46,COMPRAS!DC:DC,"SI")+SUMIFS(COMPRAS!AX:AX,COMPRAS!AW:AW,W46,COMPRAS!DC:DC,"SI") -> 0 | Z46: =IF(Y46<0,0,Y46) -> 0 | AE46: 525 | AF46: + | AG46: =IF(Z46>0,SUMIFS(COMPRAS!Z:Z,COMPRAS!AS:AS,W46,COMPRAS!DC:DC,"SI")+SUMIFS(COMPRAS!Z:Z,COMPRAS!AU:AU,W46,COMPRAS!DC:DC,"SI")+SUMIFS(COMPRAS!Z:Z,COMPRAS!AW:AW,W46,COMPRAS!DC:DC,"SI"),0) -> 0
A47: IVA generado en la diferencia entre adquisiciones y notas de crédito con distinta tarifa (ajuste en positivo al crédito tributario) | AE47: 526 | AF47: + | AG47: 0
A48: IVA generado en la diferencia entre adquisiciones y notas de crédito con distinta tarifa (ajuste en negativo al crédito tributario) | AE48: 527 | AF48: + | AG48: 0
A49: Importaciones de bienes (incluye activos fijos) gravados tarifa 0% | P49: 506 | Q49: + | R49: =SUMIFS(COMPRAS!DE:DE,COMPRAS!AS:AS,W49,COMPRAS!DC:DC,"SI")+SUMIFS(COMPRAS!DF:DF,COMPRAS!AU:AU,W49,COMPRAS!DC:DC,"SI")+SUMIFS(COMPRAS!DG:DG,COMPRAS!AW:AW,W49,COMPRAS!DC:DC,"SI") -> 0 | W49: 516 | X49: + | Y49: =SUMIFS(COMPRAS!AT:AT,COMPRAS!AS:AS,W49,COMPRAS!DC:DC,"SI")+SUMIFS(COMPRAS!AV:AV,COMPRAS!AU:AU,W49,COMPRAS!DC:DC,"SI")+SUMIFS(COMPRAS!AX:AX,COMPRAS!AW:AW,W49,COMPRAS!DC:DC,"SI") -> 0 | Z49: =IF(Y49<0,0,Y49) -> 0
A50: Adquisiciones y pagos (incluye activos fijos) gravados tarifa 0% | P50: 507 | Q50: + | R50: =SUMIFS(COMPRAS!DE:DE,COMPRAS!AS:AS,W50,COMPRAS!DC:DC,"SI")+SUMIFS(COMPRAS!DF:DF,COMPRAS!AU:AU,W50,COMPRAS!DC:DC,"SI")+SUMIFS(COMPRAS!DG:DG,COMPRAS!AW:AW,W50,COMPRAS!DC:DC,"SI") -> 0 | W50: 517 | X50: + | Y50: =SUMIFS(COMPRAS!AT:AT,COMPRAS!AS:AS,W50,COMPRAS!DC:DC,"SI")+SUMIFS(COMPRAS!AV:AV,COMPRAS!AU:AU,W50,COMPRAS!DC:DC,"SI")+SUMIFS(COMPRAS!AX:AX,COMPRAS!AW:AW,W50,COMPRAS!DC:DC,"SI") -> 0 | Z50: =IF(Y50<0,0,Y50) -> 0
A51: Adquisiciones realizadas a contribuyentes RISE (hasta diciembre 2021), NEGOCIOS POPULARES (desde enero 2022) | P51: 508 | Q51: + | R51: =SUMIFS(COMPRAS!DE:DE,COMPRAS!AS:AS,W51,COMPRAS!DC:DC,"SI")+SUMIFS(COMPRAS!DF:DF,COMPRAS!AU:AU,W51,COMPRAS!DC:DC,"SI")+SUMIFS(COMPRAS!DG:DG,COMPRAS!AW:AW,W51,COMPRAS!DC:DC,"SI") -> 0 | W51: 518 | X51: + | Y51: =SUMIFS(COMPRAS!AT:AT,COMPRAS!AS:AS,W51,COMPRAS!DC:DC,"SI")+SUMIFS(COMPRAS!AV:AV,COMPRAS!AU:AU,W51,COMPRAS!DC:DC,"SI")+SUMIFS(COMPRAS!AX:AX,COMPRAS!AW:AW,W51,COMPRAS!DC:DC,"SI") -> 0 | Z51: =IF(Y51<0,0,Y51) -> 0
A52: TOTAL ADQUISICIONES Y PAGOS | P52: 509 | Q52: = | R52: =SUM(R39:V51) -> 35909.6 | W52: 519 | X52: = | Y52: =+Z52+X53+X55+X56+X57 -> 33770.64 | Z52: =SUM(Z39:AD51) -> 33770.64 | AE52: 529 | AF52: = | AG52: =IF((SUM(AG39:AK47)-AG48)>0,(SUM(AG39:AK47)-AG48),0) -> 5065.61
A53: Adquisiciones no objeto de IVA | P53: 531 | Q53: + | R53: =SUMIFS(COMPRAS!DE:DE,COMPRAS!AS:AS,W53,COMPRAS!DC:DC,"SI")+SUMIFS(COMPRAS!DF:DF,COMPRAS!AU:AU,W53,COMPRAS!DC:DC,"SI")+SUMIFS(COMPRAS!DG:DG,COMPRAS!AW:AW,W53,COMPRAS!DC:DC,"SI") -> 0 | W53: 541 | X53: =SUMIFS(COMPRAS!AT:AT,COMPRAS!AS:AS,W53,COMPRAS!DC:DC,"SI")+SUMIFS(COMPRAS!AV:AV,COMPRAS!AU:AU,W53,COMPRAS!DC:DC,"SI")+SUMIFS(COMPRAS!AX:AX,COMPRAS!AW:AW,W53,COMPRAS!DC:DC,"SI") -> 0
A54: Adquisiciones exentas del pago de IVA | P54: 532 | Q54: + | R54: =SUMIFS(COMPRAS!DE:DE,COMPRAS!AS:AS,W54,COMPRAS!DC:DC,"SI")+SUMIFS(COMPRAS!DF:DF,COMPRAS!AU:AU,W54,COMPRAS!DC:DC,"SI")+SUMIFS(COMPRAS!DG:DG,COMPRAS!AW:AW,W54,COMPRAS!DC:DC,"SI") -> 0 | W54: 542 | X54: =SUMIFS(COMPRAS!AT:AT,COMPRAS!AS:AS,W54,COMPRAS!DC:DC,"SI")+SUMIFS(COMPRAS!AV:AV,COMPRAS!AU:AU,W54,COMPRAS!DC:DC,"SI")+SUMIFS(COMPRAS!AX:AX,COMPRAS!AW:AW,W54,COMPRAS!DC:DC,"SI") -> 0
A55: Notas de crédito tarifa 0% por compensar próximo mes | W55: 543 | X55: =IF(Y49<0,ABS(Y49),0)+IF(Y50<0,ABS(Y50),0) -> 0
A56: Notas de crédito tarifa diferente de cero por compensar próximo mes | W56: 544 | X56: =IF(Y39<0,ABS(Y39),0)+IF(Y40<0,ABS(Y40),0)+IF(Y41<0,ABS(Y41),0)+IF(Y42<0,ABS(Y42),0)+IF(Y43<0,ABS(Y43),0)+IF(Y44<0,ABS(Y44),0)+IF(Y45<0,ABS(Y45),0)+IF(Y46<0,ABS(Y46),0) -> 0 | AE56: 554 | AF56: =IF(X56>0,ABS(AF57-SUMIF(COMPRAS!DC:DC,"SI",COMPRAS!Z:Z)+SUMIF(COMPRAS!DC:DC,"SI",COMPRAS!AC:AC)+SUMIF(COMPRAS!DC:DC,"SI",COMPRAS!AF:AF)),0) -> 0
A57: Pagos netos por reembolso como intermediario / valores facturados por socios a operadoras de transporte / pagos realizados por parte de las sociedades de gestión colectiva como intermediarios (informativo) | P57: 535 | Q57: + | R57: =SUMIFS(COMPRAS!DE:DE,COMPRAS!AS:AS,W57,COMPRAS!DC:DC,"SI")+SUMIFS(COMPRAS!DF:DF,COMPRAS!AU:AU,W57,COMPRAS!DC:DC,"SI")+SUMIFS(COMPRAS!DG:DG,COMPRAS!AW:AW,W57,COMPRAS!DC:DC,"SI") -> 0 | W57: 545 | X57: =SUMIFS(COMPRAS!AT:AT,COMPRAS!AS:AS,W57,COMPRAS!DC:DC,"SI")+SUMIFS(COMPRAS!AV:AV,COMPRAS!AU:AU,W57,COMPRAS!DC:DC,"SI")+SUMIFS(COMPRAS!AX:AX,COMPRAS!AW:AW,W57,COMPRAS!DC:DC,"SI") -> 0 | AE57: 555 | AF57: =SUMIFS(COMPRAS!Z:Z,COMPRAS!DC:DC,"SI",COMPRAS!AS:AS,W57)+SUMIFS(COMPRAS!Z:Z,COMPRAS!DC:DC,"SI",COMPRAS!AU:AU,W57)+SUMIFS(COMPRAS!Z:Z,COMPRAS!DC:DC,"SI",COMPRAS!AW:AW,W57)+SUMIFS(COMPRAS!AC:AC,COMPRAS!DC:DC,"SI",COMPRAS!AS:AS,W57)+SUMIFS(COMPRAS!AC:AC,COMPRAS!DC:DC,"SI",COMPRAS!AU:AU,W57)+SUMIFS(COMPRAS!AC:AC,COMPRAS!DC:DC,"SI",COMPRAS!AW:AW,W57)+SUMIFS(COMPRAS!AF:AF,COMPRAS!DC:DC,"SI",COMPRAS!AS:AS,W57)+SUMIFS(COMPRAS!AF:AF,COMPRAS!DC:DC,"SI",COMPRAS!AU:AU,W57)+SUMIFS(COMPRAS!AF:AF,COMPRAS!DC:DC,"SI",COMPRAS!AW:AW,W57) -> 0
A59: FACTOR DE PROPORCIONALIDAD PARA CRÉDITO TRIBUTARIO | AD59: (411+412+420+435+415+416+417+418) / 419 | AE59: 563 | AF59: =ROUND((IF(AND(Z25>0,(Z19+Z20)>0),(Z13+Z14+Z15+Z16+Z21+Z22+Z23+Z24)/Z25,IF(Z25>0,1,0))),4) -> 1
A60: CRÉDITO TRIBUTARIO APLICABLE EN ESTE PERÍODO (De acuerdo al Factor de Proporcionalidad o a su Contabilidad) | AD60: (520+521+534+560+523+524+525+526-527) x 563 | AE60: 564 | AF60: = | AG60: =+ROUND(((AG39+AG40+AG41+AG42+AG44+AG45+AG46+AG47-AG48)*AF59),2) -> 5065.61
A61: Valor de IVA no considerado como crédito tributario por factor de proporcionalidad | AE61: 565 | AF61: = | AG61: =+ROUND(((AG39+AG40+AG41+AG42+AG44+AG45+AG46+AG47-AG48)-AG60),2) -> 0
A63: TOTAL COMPROBANTES DE VENTA RECIBIDOS POR ADQUISICIONES Y PAGOS (excepto notas de venta) | K63: 115 | L63: =COUNTIFS(COMPRAS!DC:DC,"SI")-COUNTIFS(COMPRAS!DC:DC,"SI",COMPRAS!G:G,"04-Nota de credito")-AC63-AC64 -> 56 | P63: TOTAL NOTAS DE VENTA RECIBIDAS | AB63: 117 | AC63: =COUNTIFS(COMPRAS!DC:DC,"SI",COMPRAS!G:G,"02-Nota o boleta de venta") -> 0
A64: TOTAL LIQUIDACIONES DE COMPRA EMITIDAS (por pago tarifa 0% de IVA o por reembolsos en relacion de dependencia) | AB64: 119 | AC64: =COUNTIFS(COMPRAS!DC:DC,"SI",COMPRAS!G:G,"03-Liquidación de compra de Bienes o Prestación de servicios") -> 0
A66: RESUMEN IMPOSITIVO AGENTE DE PERCEPCIÓN DEL IMPUESTO AL VALOR AGREGADO
A67: Impuesto causado | AD67: (si la diferencia de los campos 499-564 es mayor que cero) | AE67: 601 | AF67: = | AG67: =IF((AH34-AG60)>0,(AH34-AG60),0) -> 0
A68: Crédito tributario aplicable en este período | AD68: (si la diferencia de los campos 499-564 es menor que cero) | AE68: 602 | AF68: = | AG68: =IF((AH34-AG60)<0,ABS(AH34-AG60),0) -> 1580.36
A69: (-) Compensación de IVA por ventas efectuadas con medio electrónico y/o IVA devuelto o descontado por transacciones realizadas con personas adultas mayores o personas con discapacidad | AE69: 603 | AF69: (-) | AG69: 0
A70: (-) Compensación de IVA por ventas efectuadas en zonas afectadas - Ley de solidaridad, restitución de crédito tributario en resoluciones administrativas o sentencias judiciales de última instancia | AE70: 604 | AF70: (-) | AG70: 0
A71: (-) SALDO CRÉDITO TRIBUTARIO DEL MES ANTERIOR | D71: Por adquisiciones e importaciones | AD71: (trasládese el campo 615 de la declaración del período anterior) | AE71: 605 | AF71: (-) | AG71: =ABS(SUMIF(LIQ_IMPUESTOS!C$5:C$16,T4,LIQ_IMPUESTOS!AE$5:AE$16)) -> 0
D72: Por retenciones en la fuente de IVA que le han sido efectuadas | AD72: (trasládese el campo 617 de la declaración del período anterior) | AE72: 606 | AF72: (-) | AG72: =ABS(SUMIF(LIQ_IMPUESTOS!C$5:C$16,T4,LIQ_IMPUESTOS!AF$5:AF$16)) -> 0
D73: Por compensación de IVA por ventas efectuadas con medio electrónico | AD73: (trasládese el campo 618 de la declaración del período anterior) | AE73: 607 | AF73: (-) | AG73: 0
D74: Por compensación de IVA por ventas efectuadas en zonas afectadas - Ley de solidaridad, restitución de crédito tributario en resoluciones administrativas o sentencias judiciales de última instancia | AD74: (trasládese el campo 619 de la declaración del período anterior) | AE74: 608 | AF74: (-) | AG74: 0
A75: (-) Retenciones en la fuente de IVA que le han sido efectuadas en este período | AE75: 609 | AF75: (-) | AG75: =IF(N5,ABS(LIQ_IMPUESTOS!AG16),0)+IF(M5,ABS(LIQ_IMPUESTOS!AG15),0)+IF(L5,ABS(LIQ_IMPUESTOS!AG14),0)+IF(K5,ABS(LIQ_IMPUESTOS!AG13),0)+IF(J5,ABS(LIQ_IMPUESTOS!AG12),0)+IF(I5,ABS(LIQ_IMPUESTOS!AG11),0)+IF(H5,ABS(LIQ_IMPUESTOS!AG10),0)+IF(G5,ABS(LIQ_IMPUESTOS!AG9),0)+IF(F5,ABS(LIQ_IMPUESTOS!AG8),0)+IF(E5,ABS(LIQ_IMPUESTOS!AG7),0)+IF(D5,ABS(LIQ_IMPUESTOS!AG6),0)+IF(C5,ABS(LIQ_IMPUESTOS!AG5),0) -> 89.29
A76: (-) IVA devuelto o descontado por transacciones realizadas con personas adultas mayores o personas con discapacidad | AE76: 622 | AF76: (-) | AG76: 0
A77: (+) Ajuste por IVA devuelto o descontado por adquisiciones efectuadas con medio electrónico | AE77: 610 | AF77: (+) | AG77: 0
A78: (+) Ajuste por IVA devuelto o descontado en adquisiciones efectuadas en zonas afectadas - Ley de solidaridad | AE78: 611 | AF78: (+) | AG78: =IF(AND(SUMIF(COMPRAS!DC:DC,"SI",COMPRAS!DO:DO)>0,SUM(R13:R14)>0),SUMIF(COMPRAS!DC:DC,"SI",COMPRAS!DO:DO),0) -> 0
A79: (+) Ajuste por IVA devuelto e IVA rechazado (por concepto de devoluciones de IVA), ajuste de IVA por procesos de control y otros (adquisiciones en importaciones), imputables al crédito tributario | AE79: 612 | AF79: + | AG79: 0
A80: (+) Ajuste por IVA devuelto e IVA rechazado, ajuste de IVA por procesos de control y otros (por concepto retenciones en la fuente de IVA), imputables al crédito tributario | AE80: 613 | AF80: + | AG80: 0
A81: (+) Ajuste por IVA devuelto por otras instituciones del sector público imputable al crédito tributario en el mes | AE81: 614 | AF81: + | AG81: 0
A82: SALDO CRÉDITO TRIBUTARIO PARA EL PRÓXIMO MES | D82: Por adquisiciones e importaciones | AE82: 615 | AF82: = | AG82: =IF((AG67-AG68-AG69-AG70-AG71-AG72-AG73-AG74-AG75+AG77+AG78+AG79+AG80+AG81)<0,ABS((AG67-AG68-AG69-AG70-AG71-AG72-AG73-AG74-AG75+AG77+AG78+AG79+AG80+AG81))-AG83-AG84-AG85,0) -> 1580.36
D83: Por retenciones en la fuente de IVA que le han sido efectuadas | AE83: 617 | AF83: = | AG83: =IF((AG67-AG68-AG69-AG70-AG71-AG72-AG73-AG74-AG75+AG77+AG78+AG79+AG80+AG81)<0,IF((AG67-AG68-AG69-AG70-AG71-AG74+AG77+AG78+AG79+AG80+AG81)<0,(AG72+AG75),IF((AG72+AG75-(AG67-AG68-AG69-AG70-AG71-AG73-AG74+AG77+AG78+AG79+AG80+AG81))<0,0,(AG72+AG75-(AG67-AG68-AG69-AG70-AG71-AG73-AG74+AG77+AG78+AG79+AG80+AG81)))),0) -> 89.29
D84: Por compensación de IVA por ventas efectuadas con medio electrónico | AE84: 618 | AF84: = | AG84: 0
D85: Por compensación de IVA por ventas efectuadas en zonas afectadas - Ley de solidaridad, restitución de crédito tributario en resoluciones administrativas o sentencias judiciales de última instancia | AE85: 619 | AF85: = | AG85: =IF((AG67-AG68-AG69-AG70-AG71-AG72-AG73-AG74-AG75+AG77+AG78+AG79+AG80+AG81)<0,IF((AG70+AG74-AG78)>0,IF((AG67-AG68-AG69)-(AG70+AG74-AG78)>0,0,(AG70+AG74-AG78)-(AG67-AG69)),0),0) -> 0
A86: Ajuste del crédito tributario de Impuesto al Valor Agregado pagado en adquisiciones locales e importaciones de bienes y servicios superior a cinco (5) años | AE86: 625 | AF86: = | AG86: 0
A87: SUBTOTAL A PAGAR | AD87: Si (601-602-603-604-605-606-607-608-623-609-622+610+611+612+613+614) > 0 | AE87: 620 | AF87: = | AG87: =IF((AG67-AG68-AG69-AG70-AG71-AG72-AG73-AG74-AG75+AG77+AG78+AG79+AG80+AG81)>0,(AG67-AG68-AG69-AG70-AG71-AG72-AG73-AG74-AG75+AG77+AG78+AG79+AG80+AG81),0) -> 0
A88: IVA PRESUNTIVO DE SALAS DE JUEGO (BINGO MECÁNICOS) Y OTROS JUEGOS DE AZAR (Aplica para Ejercicios Anteriores al 2013), RETENCIÓN DE IVA EN VENTAS DIFERENTES PORCENTAJES (aplica para Ejercicios posteriores al 2021) | AE88: 621 | AF88: + | AG88: 0
A89: TOTAL IMPUESTO A PAGAR POR PERCEPCIÓN Y RETENCIONES EFECTUADAS EN VENTAS (varios porcentajes) | AD89: (620 + 621) | AE89: 699 | AF89: = | AG89: =+AG87+AG88 -> 0
A91: AGENTE DE RETENCIÓN DEL IMPUESTO AL VALOR AGREGADO | W91: VALOR | AE91: ISD PAGADO
A92: Importaciones de materias primas, insumos y bienes de capital que sean incorporadas en procesos productivos de bienes que se exporten | W92: 700 | X92: = | Z92: 0 | AE92: 701 | AF92: = | AG92: 0
AE93: PORCENTAJE
A94: Importaciones de materias primas, insumos y bienes de capital que sean incorporadas en procesos productivos de bienes que se exporten | AE94: 702 | AF94: = | AG94: 0
A96: AGENTE DE RETENCIÓN DEL IMPUESTO AL VALOR AGREGADO
A97: Retención del 10% | AE97: 721 | AF97: + | AG97: =SUMIF(COMPRAS!DC:DC,"SI",COMPRAS!CC:CC) -> 0
A98: Retención del 20% | AE98: 723 | AF98: + | AG98: =SUMIF(COMPRAS!DC:DC,"SI",COMPRAS!CD:CD) -> 0
A99: Retención del 30% | AE99: 725 | AF99: + | AG99: =SUMIF(COMPRAS!DC:DC,"SI",COMPRAS!CE:CE) -> 182.47
A100: Retención del 50% | AE100: 727 | AF100: + | AG100: =SUMIF(COMPRAS!DC:DC,"SI",COMPRAS!CF:CF) -> 0
A101: Retención del 70% | AE101: 729 | AF101: + | AG101: =SUMIF(COMPRAS!DC:DC,"SI",COMPRAS!CG:CG) -> 848.88
A102: Retención del 100% | AE102: 731 | AF102: + | AG102: =SUMIF(COMPRAS!DC:DC,"SI",COMPRAS!CH:CH)+SUMIF(COMPRAS!DC:DC,"SI",COMPRAS!CI:CI) -> 0
A103: TOTAL IMPUESTO RETENIDO | AD103: (721+723+725+727+729+731) | AE103: 799 | AF103: = | AG103: =SUM(AG97:AK102) -> 1031.35
A105: Devolución provisional de IVA mediante compensación con retenciones efectuadas | AE105: 800 | AF105: (-) | AG105: 0
A106: Retenciones efectuadas y no pagadas sector público, universidades y escuelas politécnicas | AE106: 802 | AF106: (-) | AG106: =SUMIF(COMPRAS!DC:DC,"SI",COMPRAS!CI:CI) -> 0
A107: TOTAL IMPUESTO A PAGAR POR RETENCIÓN | AD107: (799-800-802) | AE107: 801 | AF107: = | AG107: =AG103-AG105-AG106 -> 1031.35
A109: TOTAL CONSOLIDADO DE IMPUESTO AL VALOR AGREGADO | AD109: (699+801) | AE109: 859 | AF109: = | AG109: =+AG89+AG107 -> 1031.35
A111: PAGO PREVIO (Informativo) | AE111: 890 | AF111: = | AG111: =+I113+V113+AH113 -> 0
A112: DETALLE DE IMPUTACIÓN AL PAGO (Para declaraciones sustitut12s)
A113: INTERES | G113: 897 | H113: USD | I113: 0 | M113: IMPUESTO | T113: 898 | U113: USD | V113: 0 | AA113: MULTA | AF113: 899 | AG113: USD | AH113: 0
A115: Pago directo en cuenta única del tesoro nacional (uso exclusivo para instituciones y empresas del sector público autorizadas) | AE115: 880 | AF115: = | AG115: 0
...

Sheet COMPRAS
A1: =Parametros!D4&" - "&Parametros!D5 -> 0917809451001 - GARCIA RODRIGUEZ CHARLES MILTON
A2: DETALLE DE COMPRAS
B4: ="# Registros COMPRAS : " & COUNTIF(M:M,">0") -> # Registros COMPRAS : 58 | C4: -------------------- (Obligatorio si es PASAPORTE el ID) -------------------- | F4: -------------------------------------------------------------------------- Datos del documento de compra -------------------------------------------------------------------------- | N4: -------- Datos del documento modificado en la N/C - N/D -------- | U4: ------ Bases Imponibles del documento de COMPRA ------ | AO4: ---------- Informacion de COMPRAS para CONTABILIDAD ----------- | AS4: ----------------- Bases Imponibles para Formulario 104 ------------------ | AZ4: ------------------------------ Informacion del documento de Retencion --------------------------------- | BF4: ---------- Valores Retenidos - Codigo Ret. #1 ---------- | BJ4: --- Datos del Dividendo retenido - Ret. #1 --- | BM4: -- Cajas de Banano - Ret. #1 -- | BO4: ---------- Valores Retenidos - Codigo Ret. #2 ---------- | BS4: --- Datos del Dividendo retenido - Ret. #2 --- | BV4: -- Cajas de Banano - Ret. #2 -- | BX4: Valores Retenidos - Codigo Ret. #3 | CC4: ----------------------------------- Datos de Retenciones IVA en Compras ----------------------------------- | CK4: solo copie | CL4: ------ Informacion de RETENCIONES para CONTABILIDAD ------ | CP4: ------------------------ Datos de Pagos de Facturas Compras ---------------------------------- | CT4: (segun columna CP = 01) | CU4: (segun columna CP= 02) | CV4: (segun columna CP= 03) | CW4: (segun columna CM= 02-PAGO A NO RESIDENTE) | DB4: solo copie | DC4: solo copie | DD4: solo copie | DE4: solo copie | DF4: solo copie | DG4: solo copie | DH4: solo copie | DI4: solo copie | DJ4: solo copie | DK4: solo copie | DL4: solo copie | DM4: solo copie | DN4: solo copie | EG4: PARA CxPAGAR | EI4: solo copie
A5: No. de Identificacion | B5: Tipo Identif. | C5: Razon Social Contribuyente | D5: Tipo Proveedor | E5: Parte Relacionada | F5: Tipo de Emision del Comprobante (opcional) | G5: Comprobante | H5: Establecimiento | I5: Punto Emisión | J5: Numero Secuencial | K5: Numero Autorización S.R.I. | L5: Fecha de Emisión | M5: Fecha de Registro | N5: Comprobante Modificado | O5: Establecimiento | P5: Punto Emisión | Q5: Numero Secuencial Modificado | R5: Numero Autorización S.R.I. Modificado | S5: (Opcional) | T5: Codigo Sustento | U5: =SUBTOTAL(9,U$6:U1012) -> 0 | V5: =SUBTOTAL(9,V$6:V1012) -> 0 | W5: =SUBTOTAL(9,W$6:W1012) -> 76.76 | X5: =SUBTOTAL(9,X$6:X1012) -> 33770.64 | Y5: Tarifa1 de IVA aplicada | Z5: =SUBTOTAL(9,Z$6:Z1012) -> 5065.61 | AA5: =SUBTOTAL(9,AA$6:AA1012) -> 2702.18 | AB5: Tarifa2 de IVA aplicada | AC5: =SUBTOTAL(9,AC$6:AC1012) -> 135.11 | AD5: =SUBTOTAL(9,AD$6:AD1012) -> 0 | AE5: Tarifa3 de IVA aplicada | AF5: =SUBTOTAL(9,AF$6:AF1012) -> 0 | AG5: =SUBTOTAL(9,AG$6:AG1012) -> 0 | AH5: =SUBTOTAL(9,AH$6:AH1012) -> 0 | AI5: =SUBTOTAL(9,AI$6:AI1012) -> 0 | AJ5: =SUBTOTAL(9,AJ$6:AJ1012) -> 0 | AK5: =SUBTOTAL(9,AK$6:AK1012) -> 41750.3 | AL5: =SUBTOTAL(9,AL$6:AL1012) -> 0 | AN5: Autocodigo COMPRAS | AO5: Contabilizacion de la COMPRA | AR5: Tipo de ACTIVIDAD (Opcional) | AS5: Código Form. (104) 1 | AT5: =SUBTOTAL(9,AT$6:AT1012) -> 33770.64 | AU5: Código Form. (104) 2 | AV5: =SUBTOTAL(9,AV$6:AV1012) -> 0 | AW5: Código Form. (104) 3 | AX5: =SUBTOTAL(9,AX$6:AX1012) -> 0 | AZ5: Tipo de Emision de la Retencion | BA5: Establecimiento Ret. | BB5: Punto Emisión Ret. | BC5: Numero Secuencial Ret. | BD5: Numero Autorización S.R.I. Retención | BE5: Fecha de Emisión Ret.1 | BF5: Código Retención 1 | BG5: =SUBTOTAL(9,BG$6:BG756) -> 36549.58 | BH5: Porcentaje Retención 1 | BI5: =SUBTOTAL(9,BI$6:BI756) -> 353.92 | BJ5: Fecha de Pago Dividendos Ret1 | BK5: =SUBTOTAL(9,BK$6:BK756) -> 0 | BL5: Anio de utilidades generadas | BM5: Cantidad de Cajas de Banano | BN5: Precio de la Caja de Banano | BO5: Código Retención 2 | BP5: =SUBTOTAL(9,BP$6:BP756) -> 0 | BQ5: Porcentaje Retención 2 | BR5: =SUBTOTAL(9,BR$6:BR756) -> 0 | BS5: Fecha de Pago Dividendos Ret2 | BT5: =SUBTOTAL(9,BT$6:BT756) -> 0 | BU5: Anio de utilidades generadas | BV5: Cantidad de Cajas de Banano | BW5: Precio de la Caja de Banano | BX5: Código Retención 3 | BY5: =SUBTOTAL(9,BY$6:BY756) -> 0 | BZ5: Porcentaje Retención 3 | CA5: =SUBTOTAL(9,CA$6:CA756) -> 0 | CC5: =SUBTOTAL(9,CC$6:CC756) -> 0 | CD5: =SUBTOTAL(9,CD$6:CD756) -> 0 | CE5: =SUBTOTAL(9,CE$6:CE756) -> 182.47 | CF5: =SUBTOTAL(9,CF$6:CF756) -> 0 | CG5: =SUBTOTAL(9,CG$6:CG756) -> 848.88 | CH5: =SUBTOTAL(9,CH$6:CH756) -> 0 | CI5: =SUBTOTAL(9,CI$6:CI756) -> 0 | CJ5: =SUBTOTAL(9,CJ$6:CJ756) -> 0 | CK5: =SUBTOTAL(9,CK$6:CK756) -> 1385.27 | CL5: Contabilizacion de la RETENCION EMITIDA | CP5: Tipo de Pago | CQ5: Forma de PAGO 1 | CR5: Forma de PAGO 2 | CS5: Tipo de Regimen fiscal del Exterior | CT5: 01-Paises de residencia a quien se efectua el PAGO | CU5: 02-Paises de residencia a quien se efectua el PAGO en PARAISO FISCAL | CV5: 03-Denominacion del Regimen fiscal Preferente | CW5: Pais de residencia a quien se efectua el PAGO en EXTERIOR | CX5: Aplica Convenio Doble Tributacion | CY5: Pago al Exterior sujeto a Retencion | CZ5: Pago al Exterior en Regimen de Menor Imposicion | DB5: Mes declarado | DC5: Periodo Declarado Form104 | DD5: Periodo Declarado en 103 | DE5: Form.104_a | DF5: Form.104_b | DG5: Form.104_c | DH5: Liq.Imp. Base_NOgrav/Exenta | DI5: Liq.Imp. IVA Reembolso 545 | DJ5: Liq.Imp. IVA Gastos 512 | DK5: Liq.Imp. IVA Credito Tributario | DL5: Liq. Imp. Sumatoria Ret_IVA | DM5: Liq. Imp. Ret_IVA 100% Sector Publico | DN5: Liq. Imp. Ret_FTE | DP5: INFORMACION DE LA RETENCION ELECTRONICA EMITIDA | DW5: INFORMACION DE LA LIQUIDACION DE COMPRA BIENES Y SERVICIOS ELECTRONICA EMITIDA | EE5: Valor Descuentos (2) | EF5: Otros Valores | EG5: Suma de Devoluciones | EH5: CAMPO BUSQUEDA | EI5: validacion Identificacion | EK5: OBSERVACIONES
S6: Concepto de la Compra | U6: Base Imponible NO Objeto de IVA | V6: Base Imponible EXENTA | W6: Base Imponible Tarifa 0% | X6: Base Imp. 1 Gravable IVA diferente de cero | Z6: Monto-1 de I.V.A. | AA6: Base Imp. 2 Gravable IVA Construcción | AC6: Monto-2 de I.V.A. | AD6: Base Imp. 3 Gravable IVA Especial | AF6: Monto-3 de I.V.A. | AG6: Monto de I.C.E. NO incluido en Base Imp. | AH6: Monto de Propina | AI6: Monto de IRBPNR | AJ6: Monto de OTROS | AK6: Total del Documento | AL6: Monto de I.C.E. incluido en Base Imp. | AO6: Concepto Contable | AP6: Numero de Asiento | AQ6: Estado | AT6: Valor de Base Imponible | AV6: Valor de Base Imponible | AX6: Valor de Base Imponible | BG6: Base Imponible - Ret1 | BI6: Valor Retenido 1 | BK6: Impto. Renta Sociedades Ret.1 | BP6: Base Imponible - Ret2 | BR6: Valor Retenido 2 | BT6: Impto. Renta Sociedades Ret.2 | BY6: Base Imponible - Ret3 | CA6: Valor Retenido 3 | CC6: Valor Retención IVA 10% | CD6: Valor Retención IVA 20% | CE6: Valor Retención IVA 30% | CF6: Valor Retención IVA 50% | CG6: Valor Retención IVA 70% | CH6: Valor Retención IVA 100% | CI6: Valor Retención IVA 100% Sector Publico | CJ6: Valor Retencion IVA en NC | CK6: Total Retención IVA+Fte. | CL6: Concepto Contable | CM6: Numero de Asiento | CN6: Estado | DP6: DATOS CONFIGURACION ESTABLECIMIENTOS | DQ6: Codigo Docto. | DR6: Estado Documento Electronico(1) | DS6: DATOS SRI (1) | DT6: DATOS CONTRIBUYENTE (1) | DU6: DATOS INFORMACION ADICIONAL (1) | DV6: OTROS DATOS(1) | DW6: DATOS CONFIGURACION ESTABLECIMIENTOS | DX6: Codigo Documento(2) | DY6: Clase Documento(2) | DZ6: Estado Documento Electronico(2) | EA6: DATOS SRI (2) | EB6: DATOS CONTRIBUYENTE (2) | EC6: DATOS INFORMACION ADICIONAL (2) | ED6: OTROS DATOS(2)
A7: 1790978303001 | B7: R-Ruc | C7: Corporacion Proauto S.A | D7: 02-Sociedad | E7: NO | G7: 01-Factura | H7: 031 | I7: 203 | J7: 000018357 | K7: 0104202601179097830300120312030000183578736215411 | L7: 46113 | M7: 46113 | T7: 02- Costo o Gasto para declaración de IR (servicios y bienes distintos de inventarios y activos fijos) | U7: 0 | V7: 0 | W7: 0 | X7: 36 | Y7: 15 | Z7: =ROUND(X7*Y7%,2) -> 5.4 | AA7: 0 | AB7: 5 | AC7: =ROUND(AA7*AB7%,2) -> 0 | AE7: 8 | AF7: =ROUND(AD7*AE7%,2) -> 0 | AG7: 0 | AH7: 0 | AI7: 0 | AJ7: 0 | AK7: =ROUND(SUM(U7:X7)+SUM(Z7:AA7)+SUM(AC7:AD7)+SUM(AF7:AJ7),2) -> 41.4 | AL7: 0 | AR7: ACT. EMPRESARIALES CON REGISTRO DE INGRESOS Y EGRESOS | AS7: 510 | AT7: =IF(OR(AS7=545, AS7=518),($AK7-$Z7-$AC7-$AF7),IF(AND(AS7>515,AS7<518),($W7),IF(AND(AS7>509,AS7<516),$X7,IF(AS7=541,$U7,IF(AS7=542,$V7+SUM($AG7:$AJ7),IF(AS7=533,$AD7,IF(AS7=550,$AA7,0))))))) -> 36 | AU7: 0 | AV7: =IF(OR(AU7=545, AU7=518),($AK7-$Z7-$AC7-$AF7),IF(AND(AU7>515,AU7<518),($W7),IF(AND(AU7>509,AU7<516),$X7,IF(AU7=541,$U7,IF(AU7=542,$V7+SUM($AG7:$AJ7),IF(AU7=533,$AD7,IF(AU7=550,$AA7,0))))))) -> 0 | AW7: 542 | AX7: =IF(OR(AW7=545, AW7=518),($AK7-$Z7-$AC7-$AF7),IF(AND(AW7>515,AW7<518),($W7),IF(AND(AW7>509,AW7<516),$X7,IF(AW7=541,$U7,IF(AW7=542,$V7+SUM($AG7:$AJ7),IF(AW7=533,$AD7,IF(AW7=550,$AA7,0))))))) -> 0 | BF7: 332 | BG7: =SUM(U7:X7)-V7+AA7+AD7 -> 36 | BH7: =IF(ISERROR(VLOOKUP(BF7,Parametros!$C:$J,8,0)),0,VLOOKUP(BF7,Parametros!$C:$J,8,0)) -> 0 | BI7: =IF(ISERROR(ROUND((BG7*BH7),2)),0,ROUND((BG7*BH7),2)) -> 0 | BK7: 0 | BM7: 0 | BN7: 0 | BP7: =SUM(U7:X7)-V7+AA7+AD7-BG7 -> 0 | BQ7: =IF(ISERROR(VLOOKUP(BO7,Parametros!$C:$J,8,0)),0,VLOOKUP(BO7,Parametros!$C:$J,8,0)) -> 0 | BR7: =IF(ISERROR(ROUND((BP7*BQ7),2)),0,ROUND((BP7*BQ7),2)) -> 0 | BT7: 0 | BV7: 0 | BW7: 0 | BY7: =SUM(U7:X7)-V7+AA7+AD7-BG7-BP7 -> 0 | BZ7: =IF(ISERROR(VLOOKUP(BX7,Parametros!$C:$J,8,0)),0,VLOOKUP(BX7,Parametros!$C:$J,8,0)) -> 0 | CA7: =IF(ISERROR(ROUND((BY7*BZ7),2)),0,ROUND((BY7*BZ7),2)) -> 0 | CC7: 0 | CD7: 0 | CE7: 0 | CF7: 0 | CG7: 0 | CH7: 0 | CI7: 0 | CJ7: 0 | CK7: =+BI7+BR7+CA7+SUM(CC7:CJ7) -> 0 | CP7: 01-PAGO A RESIDENTE | CQ7: 01-SIN UTILIZACION DEL SISTEMA FINANCIERO | CS7: 01-REGIMEN GENERAL | DB7: =IF(ISNUMBER(M7),MONTH(M7),0) -> 4 | DC7: =IF(ISNUMBER(M7),IF(ISERROR(HLOOKUP(MONTH(M7),meses_104,1,0)),"NO","SI"),"NO") -> SI | DD7: =IF(ISNUMBER(M7),IF(ISERROR(HLOOKUP(MONTH(M7),meses_103,1,0)),"NO","SI"),"NO") -> SI | DE7: =IF(ISBLANK(G7),0,IF(VALUE(LEFT(G7,2))=4,0,AT7)) -> 36 | DF7: =IF(ISBLANK(G7),0,IF(VALUE(LEFT(G7,2))=4,0,AV7)) -> 0 | DG7: =IF(ISBLANK(G7),0,IF(VALUE(LEFT(G7,2))=4,0,AX7)) -> 0 | DH7: =SUM(U7:W7)+SUM(AG7:AJ7) -> 0 | DI7: =ROUND((IF(AS7=545,(Z7+AC7+AF7),0)+IF(AU7=545,(Z7+AC7+AF7),0)+IF(AW7=545,(Z7+AC7+AF7),0)),2) -> 0 | DJ7: =ROUND((IF(AS7=512,Z7,0)+IF(AU7=512,Z7,0)+IF(AW7=512,Z7,0)),2) -> 0 | DK7: =Z7+AC7+AF7-DI7-DJ7 -> 5.4 | DL7: =SUM(CC7:CH7)+CJ7 -> 0 | DM7: =CI7 -> 0 | DN7: =BI7+BR7+CA7 -> 0 | DQ7: 07 | DR7: PENDIENTE | DX7: OTROS | DY7: NORMAL | EE7: 0 | EF7: 0 | EG7: 0
A8: 0992182326001 | B8: R-Ruc | C8: Negocios y Telefonia Nedetel SA+ | D8: 02-Sociedad | E8: NO | G8: 01-Factura | H8: 001 | I8: 001 | J8: 000140895 | K8: 0104202601099218232600120010010001408953754682116 | L8: 46113 | M8: 46113 | T8: 02- Costo o Gasto para declaración de IR (servicios y bienes distintos de inventarios y activos fijos) | U8: 0 | V8: 0 | W8: 0 | X8: 500 | Y8: 15 | Z8: =ROUND(X8*Y8%,2) -> 75 | AA8: 0 | AB8: 5 | AC8: =ROUND(AA8*AB8%,2) -> 0 | AE8: 8 | AF8: =ROUND(AD8*AE8%,2) -> 0 | AG8: 0 | AH8: 0 | AI8: 0 | AJ8: 0 | AK8: =ROUND(SUM(U8:X8)+SUM(Z8:AA8)+SUM(AC8:AD8)+SUM(AF8:AJ8),2) -> 575 | AL8: 0 | AR8: ACT. EMPRESARIALES CON REGISTRO DE INGRESOS Y EGRESOS | AS8: 510 | AT8: =IF(OR(AS8=545, AS8=518),($AK8-$Z8-$AC8-$AF8),IF(AND(AS8>515,AS8<518),($W8),IF(AND(AS8>509,AS8<516),$X8,IF(AS8=541,$U8,IF(AS8=542,$V8+SUM($AG8:$AJ8),IF(AS8=533,$AD8,IF(AS8=550,$AA8,0))))))) -> 500 | AU8: 0 | AV8: =IF(OR(AU8=545, AU8=518),($AK8-$Z8-$AC8-$AF8),IF(AND(AU8>515,AU8<518),($W8),IF(AND(AU8>509,AU8<516),$X8,IF(AU8=541,$U8,IF(AU8=542,$V8+SUM($AG8:$AJ8),IF(AU8=533,$AD8,IF(AU8=550,$AA8,0))))))) -> 0 | AW8: 542 | AX8: =IF(OR(AW8=545, AW8=518),($AK8-$Z8-$AC8-$AF8),IF(AND(AW8>515,AW8<518),($W8),IF(AND(AW8>509,AW8<516),$X8,IF(AW8=541,$U8,IF(AW8=542,$V8+SUM($AG8:$AJ8),IF(AW8=533,$AD8,IF(AW8=550,$AA8,0))))))) -> 0 | AZ8: E-Electronico(v1.0) | BA8: 003 | BB8: 001 | BC8: 000000081 | BD8: 0104202607091780945100120030010000000811670216113 | BE8: 46113 | BF8: 332 | BG8: =SUM(U8:X8)-V8+AA8+AD8 -> 500 | BH8: =IF(ISERROR(VLOOKUP(BF8,Parametros!$C:$J,8,0)),0,VLOOKUP(BF8,Parametros!$C:$J,8,0)) -> 0 | BI8: =IF(ISERROR(ROUND((BG8*BH8),2)),0,ROUND((BG8*BH8),2)) -> 0 | BK8: 0 | BM8: 0 | BN8: 0 | BP8: =SUM(U8:X8)-V8+AA8+AD8-BG8 -> 0 | BQ8: =IF(ISERROR(VLOOKUP(BO8,Parametros!$C:$J,8,0)),0,VLOOKUP(BO8,Parametros!$C:$J,8,0)) -> 0 | BR8: =IF(ISERROR(ROUND((BP8*BQ8),2)),0,ROUND((BP8*BQ8),2)) -> 0 | BT8: 0 | BV8: 0 | BW8: 0 | BY8: =SUM(U8:X8)-V8+AA8+AD8-BG8-BP8 -> 0 | BZ8: =IF(ISERROR(VLOOKUP(BX8,Parametros!$C:$J,8,0)),0,VLOOKUP(BX8,Parametros!$C:$J,8,0)) -> 0 | CA8: =IF(ISERROR(ROUND((BY8*BZ8),2)),0,ROUND((BY8*BZ8),2)) -> 0 | CC8: 0 | CD8: 0 | CE8: 0 | CF8: 0 | CG8: 52.5 | CH8: 0 | CI8: 0 | CJ8: 0 | CK8: =+BI8+BR8+CA8+SUM(CC8:CJ8) -> 52.5 | CP8: 01-PAGO A RESIDENTE | CQ8: 20-OTROS CON UTILIZACION DEL SISTEMA FINANCIERO | CS8: 01-REGIMEN GENERAL | DB8: =IF(ISNUMBER(M8),MONTH(M8),0) -> 4 | DC8: =IF(ISNUMBER(M8),IF(ISERROR(HLOOKUP(MONTH(M8),meses_104,1,0)),"NO","SI"),"NO") -> SI | DD8: =IF(ISNUMBER(M8),IF(ISERROR(HLOOKUP(MONTH(M8),meses_103,1,0)),"NO","SI"),"NO") -> SI | DE8: =IF(ISBLANK(G8),0,IF(VALUE(LEFT(G8,2))=4,0,AT8)) -> 500 | DF8: =IF(ISBLANK(G8),0,IF(VALUE(LEFT(G8,2))=4,0,AV8)) -> 0 | DG8: =IF(ISBLANK(G8),0,IF(VALUE(LEFT(G8,2))=4,0,AX8)) -> 0 | DH8: =SUM(U8:W8)+SUM(AG8:AJ8) -> 0 | DI8: =ROUND((IF(AS8=545,(Z8+AC8+AF8),0)+IF(AU8=545,(Z8+AC8+AF8),0)+IF(AW8=545,(Z8+AC8+AF8),0)),2) -> 0 | DJ8: =ROUND((IF(AS8=512,Z8,0)+IF(AU8=512,Z8,0)+IF(AW8=512,Z8,0)),2) -> 0 | DK8: =Z8+AC8+AF8-DI8-DJ8 -> 75 | DL8: =SUM(CC8:CH8)+CJ8 -> 52.5 | DM8: =CI8 -> 0 | DN8: =BI8+BR8+CA8 -> 0 | DQ8: 07 | DR8: PENDIENTE | DX8: OTROS | DY8: NORMAL | EE8: 0 | EF8: 0 | EG8: 0
A9: 0992182326001 | B9: R-Ruc | C9: Negocios y Telefonia Nedetel SA+ | D9: 02-Sociedad | E9: NO | G9: 01-Factura | H9: 001 | I9: 001 | J9: 000141523 | K9: 0104202601099218232600120010010001415234681237519 | L9: 46113 | M9: 46113 | T9: 02- Costo o Gasto para declaración de IR (servicios y bienes distintos de inventarios y activos fijos) | U9: 0 | V9: 0 | W9: 0 | X9: 1599.5 | Y9: 15 | Z9: =ROUND(X9*Y9%,2) -> 239.93 | AA9: 0 | AB9: 5 | AC9: =ROUND(AA9*AB9%,2) -> 0 | AE9: 8 | AF9: =ROUND(AD9*AE9%,2) -> 0 | AG9: 0 | AH9: 0 | AI9: 0 | AJ9: 0 | AK9: =ROUND(SUM(U9:X9)+SUM(Z9:AA9)+SUM(AC9:AD9)+SUM(AF9:AJ9),2) -> 1839.43 | AL9: 0 | AR9: ACT. EMPRESARIALES CON REGISTRO DE INGRESOS Y EGRESOS | AS9: 510 | AT9: =IF(OR(AS9=545, AS9=518),($AK9-$Z9-$AC9-$AF9),IF(AND(AS9>515,AS9<518),($W9),IF(AND(AS9>509,AS9<516),$X9,IF(AS9=541,$U9,IF(AS9=542,$V9+SUM($AG9:$AJ9),IF(AS9=533,$AD9,IF(AS9=550,$AA9,0))))))) -> 1599.5 | AU9: 0 | AV9: =IF(OR(AU9=545, AU9=518),($AK9-$Z9-$AC9-$AF9),IF(AND(AU9>515,AU9<518),($W9),IF(AND(AU9>509,AU9<516),$X9,IF(AU9=541,$U9,IF(AU9=542,$V9+SUM($AG9:$AJ9),IF(AU9=533,$AD9,IF(AU9=550,$AA9,0))))))) -> 0 | AW9: 542 | AX9: =IF(OR(AW9=545, AW9=518),($AK9-$Z9-$AC9-$AF9),IF(AND(AW9>515,AW9<518),($W9),IF(AND(AW9>509,AW9<516),$X9,IF(AW9=541,$U9,IF(AW9=542,$V9+SUM($AG9:$AJ9),IF(AW9=533,$AD9,IF(AW9=550,$AA9,0))))))) -> 0 | AZ9: E-Electronico(v1.0) | BA9: 003 | BB9: 001 | BC9: 000000084 | BD9: 0104202607091780945100120030010000000842392808619 | BE9: 46113 | BF9: 332 | BG9: =SUM(U9:X9)-V9+AA9+AD9 -> 1599.5 | BH9: =IF(ISERROR(VLOOKUP(BF9,Parametros!$C:$J,8,0)),0,VLOOKUP(BF9,Parametros!$C:$J,8,0)) -> 0 | BI9: =IF(ISERROR(ROUND((BG9*BH9),2)),0,ROUND((BG9*BH9),2)) -> 0 | BK9: 0 | BM9: 0 | BN9: 0 | BP9: =SUM(U9:X9)-V9+AA9+AD9-BG9 -> 0 | BQ9: =IF(ISERROR(VLOOKUP(BO9,Parametros!$C:$J,8,0)),0,VLOOKUP(BO9,Parametros!$C:$J,8,0)) -> 0 | BR9: =IF(ISERROR(ROUND((BP9*BQ9),2)),0,ROUND((BP9*BQ9),2)) -> 0 | BT9: 0 | BV9: 0 | BW9: 0 | BY9: =SUM(U9:X9)-V9+AA9+AD9-BG9-BP9 -> 0 | BZ9: =IF(ISERROR(VLOOKUP(BX9,Parametros!$C:$J,8,0)),0,VLOOKUP(BX9,Parametros!$C:$J,8,0)) -> 0 | CA9: =IF(ISERROR(ROUND((BY9*BZ9),2)),0,ROUND((BY9*BZ9),2)) -> 0 | CC9: 0 | CD9: 0 | CE9: 0 | CF9: 0 | CG9: 167.95 | CH9: 0 | CI9: 0 | CJ9: 0 | CK9: =+BI9+BR9+CA9+SUM(CC9:CJ9) -> 167.95 | CP9: 01-PAGO A RESIDENTE | CQ9: 20-OTROS CON UTILIZACION DEL SISTEMA FINANCIERO | CS9: 01-REGIMEN GENERAL | DB9: =IF(ISNUMBER(M9),MONTH(M9),0) -> 4 | DC9: =IF(ISNUMBER(M9),IF(ISERROR(HLOOKUP(MONTH(M9),meses_104,1,0)),"NO","SI"),"NO") -> SI | DD9: =IF(ISNUMBER(M9),IF(ISERROR(HLOOKUP(MONTH(M9),meses_103,1,0)),"NO","SI"),"NO") -> SI | DE9: =IF(ISBLANK(G9),0,IF(VALUE(LEFT(G9,2))=4,0,AT9)) -> 1599.5 | DF9: =IF(ISBLANK(G9),0,IF(VALUE(LEFT(G9,2))=4,0,AV9)) -> 0 | DG9: =IF(ISBLANK(G9),0,IF(VALUE(LEFT(G9,2))=4,0,AX9)) -> 0 | DH9: =SUM(U9:W9)+SUM(AG9:AJ9) -> 0 | DI9: =ROUND((IF(AS9=545,(Z9+AC9+AF9),0)+IF(AU9=545,(Z9+AC9+AF9),0)+IF(AW9=545,(Z9+AC9+AF9),0)),2) -> 0 | DJ9: =ROUND((IF(AS9=512,Z9,0)+IF(AU9=512,Z9,0)+IF(AW9=512,Z9,0)),2) -> 0 | DK9: =Z9+AC9+AF9-DI9-DJ9 -> 239.93 | DL9: =SUM(CC9:CH9)+CJ9 -> 167.95 | DM9: =CI9 -> 0 | DN9: =BI9+BR9+CA9 -> 0 | DQ9: 07 | DR9: PENDIENTE | DX9: OTROS | DY9: NORMAL | EE9: 0 | EF9: 0 | EG9: 0
A10: 0992182326001 | B10: R-Ruc | C10: Negocios y Telefonia Nedetel SA+ | D10: 02-Sociedad | E10: NO | G10: 01-Factura | H10: 001 | I10: 001 | J10: 000142299 | K10: 0104202601099218232600120010010001422995874216312 | L10: 46113 | M10: 46113 | T10: 02- Costo o Gasto para declaración de IR (servicios y bienes distintos de inventarios y activos fijos) | U10: 0 | V10: 0 | W10: 0 | X10: 910 | Y10: 15 | Z10: =ROUND(X10*Y10%,2) -> 136.5 | AA10: 0 | AB10: 5 | AC10: =ROUND(AA10*AB10%,2) -> 0 | AE10: 8 | AF10: =ROUND(AD10*AE10%,2) -> 0 | AG10: 0 | AH10: 0 | AI10: 0 | AJ10: 0 | AK10: =ROUND(SUM(U10:X10)+SUM(Z10:AA10)+SUM(AC10:AD10)+SUM(AF10:AJ10),2) -> 1046.5 | AL10: 0 | AR10: ACT. EMPRESARIALES CON REGISTRO DE INGRESOS Y EGRESOS | AS10: 510 | AT10: =IF(OR(AS10=545, AS10=518),($AK10-$Z10-$AC10-$AF10),IF(AND(AS10>515,AS10<518),($W10),IF(AND(AS10>509,AS10<516),$X10,IF(AS10=541,$U10,IF(AS10=542,$V10+SUM($AG10:$AJ10),IF(AS10=533,$AD10,IF(AS10=550,$AA10,0))))))) -> 910 | AU10: 0 | AV10: =IF(OR(AU10=545, AU10=518),($AK10-$Z10-$AC10-$AF10),IF(AND(AU10>515,AU10<518),($W10),IF(AND(AU10>509,AU10<516),$X10,IF(AU10=541,$U10,IF(AU10=542,$V10+SUM($AG10:$AJ10),IF(AU10=533,$AD10,IF(AU10=550,$AA10,0))))))) -> 0 | AW10: 542 | AX10: =IF(OR(AW10=545, AW10=518),($AK10-$Z10-$AC10-$AF10),IF(AND(AW10>515,AW10<518),($W10),IF(AND(AW10>509,AW10<516),$X10,IF(AW10=541,$U10,IF(AW10=542,$V10+SUM($AG10:$AJ10),IF(AW10=533,$AD10,IF(AW10=550,$AA10,0))))))) -> 0 | AZ10: E-Electronico(v1.0) | BA10: 003 | BB10: 001 | BC10: 000000085 | BD10: 0104202607091780945100120030010000000852406965610 | BE10: 46113 | BF10: 332 | BG10: =SUM(U10:X10)-V10+AA10+AD10 -> 910 | BH10: =IF(ISERROR(VLOOKUP(BF10,Parametros!$C:$J,8,0)),0,VLOOKUP(BF10,Parametros!$C:$J,8,0)) -> 0 | BI10: =IF(ISERROR(ROUND((BG10*BH10),2)),0,ROUND((BG10*BH10),2)) -> 0 | BK10: 0 | BM10: 0 | BN10: 0 | BP10: =SUM(U10:X10)-V10+AA10+AD10-BG10 -> 0 | BQ10: =IF(ISERROR(VLOOKUP(BO10,Parametros!$C:$J,8,0)),0,VLOOKUP(BO10,Parametros!$C:$J,8,0)) -> 0 | BR10: =IF(ISERROR(ROUND((BP10*BQ10),2)),0,ROUND((BP10*BQ10),2)) -> 0 | BT10: 0 | BV10: 0 | BW10: 0 | BY10: =SUM(U10:X10)-V10+AA10+AD10-BG10-BP10 -> 0 | BZ10: =IF(ISERROR(VLOOKUP(BX10,Parametros!$C:$J,8,0)),0,VLOOKUP(BX10,Parametros!$C:$J,8,0)) -> 0 | CA10: =IF(ISERROR(ROUND((BY10*BZ10),2)),0,ROUND((BY10*BZ10),2)) -> 0 | CC10: 0 | CD10: 0 | CE10: 0 | CF10: 0 | CG10: 95.55 | CH10: 0 | CI10: 0 | CJ10: 0 | CK10: =+BI10+BR10+CA10+SUM(CC10:CJ10) -> 95.55 | CP10: 01-PAGO A RESIDENTE | CQ10: 20-OTROS CON UTILIZACION DEL SISTEMA FINANCIERO | CS10: 01-REGIMEN GENERAL | DB10: =IF(ISNUMBER(M10),MONTH(M10),0) -> 4 | DC10: =IF(ISNUMBER(M10),IF(ISERROR(HLOOKUP(MONTH(M10),meses_104,1,0)),"NO","SI"),"NO") -> SI | DD10: =IF(ISNUMBER(M10),IF(ISERROR(HLOOKUP(MONTH(M10),meses_103,1,0)),"NO","SI"),"NO") -> SI | DE10: =IF(ISBLANK(G10),0,IF(VALUE(LEFT(G10,2))=4,0,AT10)) -> 910 | DF10: =IF(ISBLANK(G10),0,IF(VALUE(LEFT(G10,2))=4,0,AV10)) -> 0 | DG10: =IF(ISBLANK(G10),0,IF(VALUE(LEFT(G10,2))=4,0,AX10)) -> 0 | DH10: =SUM(U10:W10)+SUM(AG10:AJ10) -> 0 | DI10: =ROUND((IF(AS10=545,(Z10+AC10+AF10),0)+IF(AU10=545,(Z10+AC10+AF10),0)+IF(AW10=545,(Z10+AC10+AF10),0)),2) -> 0 | DJ10: =ROUND((IF(AS10=512,Z10,0)+IF(AU10=512,Z10,0)+IF(AW10=512,Z10,0)),2) -> 0 | DK10: =Z10+AC10+AF10-DI10-DJ10 -> 136.5 | DL10: =SUM(CC10:CH10)+CJ10 -> 95.55 | DM10: =CI10 -> 0 | DN10: =BI10+BR10+CA10 -> 0 | DQ10: 07 | DR10: PENDIENTE | DX10: OTROS | DY10: NORMAL | EE10: 0 | EF10: 0 | EG10: 0
A11: 0992182326001 | B11: R-Ruc | C11: Negocios y Telefonia Nedetel SA+ | D11: 02-Sociedad | E11: NO | G11: 01-Factura | H11: 001 | I11: 001 | J11: 000141459 | K11: 0104202601099218232600120010010001414591823465712 | L11: 46113 | M11: 46113 | T11: 02- Costo o Gasto para declaración de IR (servicios y bienes distintos de inventarios y activos fijos) | U11: 0 | V11: 0 | W11: 0 | X11: 3675 | Y11: 15 | Z11: =ROUND(X11*Y11%,2) -> 551.25 | AA11: 0 | AB11: 5 | AC11: =ROUND(AA11*AB11%,2) -> 0 | AE11: 8 | AF11: =ROUND(AD11*AE11%,2) -> 0 | AG11: 0 | AH11: 0 | AI11: 0 | AJ11: 0 | AK11: =ROUND(SUM(U11:X11)+SUM(Z11:AA11)+SUM(AC11:AD11)+SUM(AF11:AJ11),2) -> 4226.25 | AL11: 0 | AR11: ACT. EMPRESARIALES CON REGISTRO DE INGRESOS Y EGRESOS | AS11: 510 | AT11: =IF(OR(AS11=545, AS11=518),($AK11-$Z11-$AC11-$AF11),IF(AND(AS11>515,AS11<518),($W11),IF(AND(AS11>509,AS11<516),$X11,IF(AS11=541,$U11,IF(AS11=542,$V11+SUM($AG11:$AJ11),IF(AS11=533,$AD11,IF(AS11=550,$AA11,0))))))) -> 3675 | AU11: 0 | AV11: =IF(OR(AU11=545, AU11=518),($AK11-$Z11-$AC11-$AF11),IF(AND(AU11>515,AU11<518),($W11),IF(AND(AU11>509,AU11<516),$X11,IF(AU11=541,$U11,IF(AU11=542,$V11+SUM($AG11:$AJ11),IF(AU11=533,$AD11,IF(AU11=550,$AA11,0))))))) -> 0 | AW11: 542 | AX11: =IF(OR(AW11=545, AW11=518),($AK11-$Z11-$AC11-$AF11),IF(AND(AW11>515,AW11<518),($W11),IF(AND(AW11>509,AW11<516),$X11,IF(AW11=541,$U11,IF(AW11=542,$V11+SUM($AG11:$AJ11),IF(AW11=533,$AD11,IF(AW11=550,$AA11,0))))))) -> 0 | AZ11: E-Electronico(v1.0) | BA11: 003 | BB11: 001 | BC11: 000000083 | BD11: 0104202607091780945100120030010000000835503379112 | BE11: 46113 | BF11: 332 | BG11: =SUM(U11:X11)-V11+AA11+AD11 -> 3675 | BH11: =IF(ISERROR(VLOOKUP(BF11,Parametros!$C:$J,8,0)),0,VLOOKUP(BF11,Parametros!$C:$J,8,0)) -> 0 | BI11: =IF(ISERROR(ROUND((BG11*BH11),2)),0,ROUND((BG11*BH11),2)) -> 0 | BK11: 0 | BM11: 0 | BN11: 0 | BP11: =SUM(U11:X11)-V11+AA11+AD11-BG11 -> 0 | BQ11: =IF(ISERROR(VLOOKUP(BO11,Parametros!$C:$J,8,0)),0,VLOOKUP(BO11,Parametros!$C:$J,8,0)) -> 0 | BR11: =IF(ISERROR(ROUND((BP11*BQ11),2)),0,ROUND((BP11*BQ11),2)) -> 0 | BT11: 0 | BV11: 0 | BW11: 0 | BY11: =SUM(U11:X11)-V11+AA11+AD11-BG11-BP11 -> 0 | BZ11: =IF(ISERROR(VLOOKUP(BX11,Parametros!$C:$J,8,0)),0,VLOOKUP(BX11,Parametros!$C:$J,8,0)) -> 0 | CA11: =IF(ISERROR(ROUND((BY11*BZ11),2)),0,ROUND((BY11*BZ11),2)) -> 0 | CC11: 0 | CD11: 0 | CE11: 0 | CF11: 0 | CG11: 385.88 | CH11: 0 | CI11: 0 | CJ11: 0 | CK11: =+BI11+BR11+CA11+SUM(CC11:CJ11) -> 385.88 | CP11: 01-PAGO A RESIDENTE | CQ11: 20-OTROS CON UTILIZACION DEL SISTEMA FINANCIERO | CS11: 01-REGIMEN GENERAL | DB11: =IF(ISNUMBER(M11),MONTH(M11),0) -> 4 | DC11: =IF(ISNUMBER(M11),IF(ISERROR(HLOOKUP(MONTH(M11),meses_104,1,0)),"NO","SI"),"NO") -> SI | DD11: =IF(ISNUMBER(M11),IF(ISERROR(HLOOKUP(MONTH(M11),meses_103,1,0)),"NO","SI"),"NO") -> SI | DE11: =IF(ISBLANK(G11),0,IF(VALUE(LEFT(G11,2))=4,0,AT11)) -> 3675 | DF11: =IF(ISBLANK(G11),0,IF(VALUE(LEFT(G11,2))=4,0,AV11)) -> 0 | DG11: =IF(ISBLANK(G11),0,IF(VALUE(LEFT(G11,2))=4,0,AX11)) -> 0 | DH11: =SUM(U11:W11)+SUM(AG11:AJ11) -> 0 | DI11: =ROUND((IF(AS11=545,(Z11+AC11+AF11),0)+IF(AU11=545,(Z11+AC11+AF11),0)+IF(AW11=545,(Z11+AC11+AF11),0)),2) -> 0 | DJ11: =ROUND((IF(AS11=512,Z11,0)+IF(AU11=512,Z11,0)+IF(AW11=512,Z11,0)),2) -> 0 | DK11: =Z11+AC11+AF11-DI11-DJ11 -> 551.25 | DL11: =SUM(CC11:CH11)+CJ11 -> 385.88 | DM11: =CI11 -> 0 | DN11: =BI11+BR11+CA11 -> 0 | DQ11: 07 | DR11: PENDIENTE | DX11: OTROS | DY11: NORMAL | EE11: 0 | EF11: 0 | EG11: 0
A12: 0992560754001 | B12: R-Ruc | C12: CONTIFICO | D12: 02-Sociedad | E12: NO | G12: 01-Factura | H12: 001 | I12: 001 | J12: 000920632 | K12: 0104202601099256075400120010010009206325547597912 | L12: 46113 | M12: 46113 | T12: 02- Costo o Gasto para declaración de IR (servicios y bienes distintos de inventarios y activos fijos) | U12: 0 | V12: 0 | W12: 0 | X12: 92.6 | Y12: 15 | Z12: =ROUND(X12*Y12%,2) -> 13.89 | AA12: 0 | AB12: 5 | AC12: =ROUND(AA12*AB12%,2) -> 0 | AE12: 8 | AF12: =ROUND(AD12*AE12%,2) -> 0 | AG12: 0 | AH12: 0 | AI12: 0 | AJ12: 0 | AK12: =ROUND(SUM(U12:X12)+SUM(Z12:AA12)+SUM(AC12:AD12)+SUM(AF12:AJ12),2) -> 106.49 | AL12: 0 | AR12: ACT. EMPRESARIALES CON REGISTRO DE INGRESOS Y EGRESOS | AS12: 510 | AT12: =IF(OR(AS12=545, AS12=518),($AK12-$Z12-$AC12-$AF12),IF(AND(AS12>515,AS12<518),($W12),IF(AND(AS12>509,AS12<516),$X12,IF(AS12=541,$U12,IF(AS12=542,$V12+SUM($AG12:$AJ12),IF(AS12=533,$AD12,IF(AS12=550,$AA12,0))))))) -> 92.6 | AU12: 0 | AV12: =IF(OR(AU12=545, AU12=518),($AK12-$Z12-$AC12-$AF12),IF(AND(AU12>515,AU12<518),($W12),IF(AND(AU12>509,AU12<516),$X12,IF(AU12=541,$U12,IF(AU12=542,$V12+SUM($AG12:$AJ12),IF(AU12=533,$AD12,IF(AU12=550,$AA12,0))))))) -> 0 | AW12: 542 | AX12: =IF(OR(AW12=545, AW12=518),($AK12-$Z12-$AC12-$AF12),IF(AND(AW12>515,AW12<518),($W12),IF(AND(AW12>509,AW12<516),$X12,IF(AW12=541,$U12,IF(AW12=542,$V12+SUM($AG12:$AJ12),IF(AW12=533,$AD12,IF(AW12=550,$AA12,0))))))) -> 0 | BF12: 332 | BG12: =SUM(U12:X12)-V12+AA12+AD12 -> 92.6 | BH12: =IF(ISERROR(VLOOKUP(BF12,Parametros!$C:$J,8,0)),0,VLOOKUP(BF12,Parametros!$C:$J,8,0)) -> 0 | BI12: =IF(ISERROR(ROUND((BG12*BH12),2)),0,ROUND((BG12*BH12),2)) -> 0 | BK12: 0 | BM12: 0 | BN12: 0 | BP12: =SUM(U12:X12)-V12+AA12+AD12-BG12 -> 0 | BQ12: =IF(ISERROR(VLOOKUP(BO12,Parametros!$C:$J,8,0)),0,VLOOKUP(BO12,Parametros!$C:$J,8,0)) -> 0 | BR12: =IF(ISERROR(ROUND((BP12*BQ12),2)),0,ROUND((BP12*BQ12),2)) -> 0 | BT12: 0 | BV12: 0 | BW12: 0 | BY12: =SUM(U12:X12)-V12+AA12+AD12-BG12-BP12 -> 0 | BZ12: =IF(ISERROR(VLOOKUP(BX12,Parametros!$C:$J,8,0)),0,VLOOKUP(BX12,Parametros!$C:$J,8,0)) -> 0 | CA12: =IF(ISERROR(ROUND((BY12*BZ12),2)),0,ROUND((BY12*BZ12),2)) -> 0 | CC12: 0 | CD12: 0 | CE12: 0 | CF12: 0 | CG12: 0 | CH12: 0 | CI12: 0 | CJ12: 0 | CK12: =+BI12+BR12+CA12+SUM(CC12:CJ12) -> 0 | CP12: 01-PAGO A RESIDENTE | CQ12: 01-SIN UTILIZACION DEL SISTEMA FINANCIERO | CS12: 01-REGIMEN GENERAL | DB12: =IF(ISNUMBER(M12),MONTH(M12),0) -> 4 | DC12: =IF(ISNUMBER(M12),IF(ISERROR(HLOOKUP(MONTH(M12),meses_104,1,0)),"NO","SI"),"NO") -> SI | DD12: =IF(ISNUMBER(M12),IF(ISERROR(HLOOKUP(MONTH(M12),meses_103,1,0)),"NO","SI"),"NO") -> SI | DE12: =IF(ISBLANK(G12),0,IF(VALUE(LEFT(G12,2))=4,0,AT12)) -> 92.6 | DF12: =IF(ISBLANK(G12),0,IF(VALUE(LEFT(G12,2))=4,0,AV12)) -> 0 | DG12: =IF(ISBLANK(G12),0,IF(VALUE(LEFT(G12,2))=4,0,AX12)) -> 0 | DH12: =SUM(U12:W12)+SUM(AG12:AJ12) -> 0 | DI12: =ROUND((IF(AS12=545,(Z12+AC12+AF12),0)+IF(AU12=545,(Z12+AC12+AF12),0)+IF(AW12=545,(Z12+AC12+AF12),0)),2) -> 0 | DJ12: =ROUND((IF(AS12=512,Z12,0)+IF(AU12=512,Z12,0)+IF(AW12=512,Z12,0)),2) -> 0 | DK12: =Z12+AC12+AF12-DI12-DJ12 -> 13.89 | DL12: =SUM(CC12:CH12)+CJ12 -> 0 | DM12: =CI12 -> 0 | DN12: =BI12+BR12+CA12 -> 0 | DQ12: 07 | DR12: PENDIENTE | DX12: OTROS | DY12: NORMAL | EE12: 0 | EF12: 0 | EG12: 0
A13: 0992182326001 | B13: R-Ruc | C13: Negocios y Telefonia Nedetel SA+ | D13: 02-Sociedad | E13: NO | G13: 01-Factura | H13: 001 | I13: 001 | J13: 000141214 | K13: 0104202601099218232600120010010001412147218653413 | L13: 46113 | M13: 46113 | T13: 02- Costo o Gasto para declaración de IR (servicios y bienes distintos de inventarios y activos fijos) | U13: 0 | V13: 0 | W13: 0 | X13: 1400 | Y13: 15 | Z13: =ROUND(X13*Y13%,2) -> 210 | AA13: 0 | AB13: 5 | AC13: =ROUND(AA13*AB13%,2) -> 0 | AE13: 8 | AF13: =ROUND(AD13*AE13%,2) -> 0 | AG13: 0 | AH13: 0 | AI13: 0 | AJ13: 0 | AK13: =ROUND(SUM(U13:X13)+SUM(Z13:AA13)+SUM(AC13:AD13)+SUM(AF13:AJ13),2) -> 1610 | AL13: 0 | AR13: ACT. EMPRESARIALES CON REGISTRO DE INGRESOS Y EGRESOS | AS13: 510 | AT13: =IF(OR(AS13=545, AS13=518),($AK13-$Z13-$AC13-$AF13),IF(AND(AS13>515,AS13<518),($W13),IF(AND(AS13>509,AS13<516),$X13,IF(AS13=541,$U13,IF(AS13=542,$V13+SUM($AG13:$AJ13),IF(AS13=533,$AD13,IF(AS13=550,$AA13,0))))))) -> 1400 | AU13: 0 | AV13: =IF(OR(AU13=545, AU13=518),($AK13-$Z13-$AC13-$AF13),IF(AND(AU13>515,AU13<518),($W13),IF(AND(AU13>509,AU13<516),$X13,IF(AU13=541,$U13,IF(AU13=542,$V13+SUM($AG13:$AJ13),IF(AU13=533,$AD13,IF(AU13=550,$AA13,0))))))) -> 0 | AW13: 542 | AX13: =IF(OR(AW13=545, AW13=518),($AK13-$Z13-$AC13-$AF13),IF(AND(AW13>515,AW13<518),($W13),IF(AND(AW13>509,AW13<516),$X13,IF(AW13=541,$U13,IF(AW13=542,$V13+SUM($AG13:$AJ13),IF(AW13=533,$AD13,IF(AW13=550,$AA13,0))))))) -> 0 | AZ13: E-Electronico(v1.0) | BA13: 003 | BB13: 001 | BC13: 000000082 | BD13: 0104202607091780945100120030010000000828602612019 | BE13: 46113 | BF13: 332 | BG13: =SUM(U13:X13)-V13+AA13+AD13 -> 1400 | BH13: =IF(ISERROR(VLOOKUP(BF13,Parametros!$C:$J,8,0)),0,VLOOKUP(BF13,Parametros!$C:$J,8,0)) -> 0 | BI13: =IF(ISERROR(ROUND((BG13*BH13),2)),0,ROUND((BG13*BH13),2)) -> 0 | BK13: 0 | BM13: 0 | BN13: 0 | BP13: =SUM(U13:X13)-V13+AA13+AD13-BG13 -> 0 | BQ13: =IF(ISERROR(VLOOKUP(BO13,Parametros!$C:$J,8,0)),0,VLOOKUP(BO13,Parametros!$C:$J,8,0)) -> 0 | BR13: =IF(ISERROR(ROUND((BP13*BQ13),2)),0,ROUND((BP13*BQ13),2)) -> 0 | BT13: 0 | BV13: 0 | BW13: 0 | BY13: =SUM(U13:X13)-V13+AA13+AD13-BG13-BP13 -> 0 | BZ13: =IF(ISERROR(VLOOKUP(BX13,Parametros!$C:$J,8,0)),0,VLOOKUP(BX13,Parametros!$C:$J,8,0)) -> 0 | CA13: =IF(ISERROR(ROUND((BY13*BZ13),2)),0,ROUND((BY13*BZ13),2)) -> 0 | CC13: 0 | CD13: 0 | CE13: 0 | CF13: 0 | CG13: 147 | CH13: 0 | CI13: 0 | CJ13: 0 | CK13: =+BI13+BR13+CA13+SUM(CC13:CJ13) -> 147 | CP13: 01-PAGO A RESIDENTE | CQ13: 20-OTROS CON UTILIZACION DEL SISTEMA FINANCIERO | CS13: 01-REGIMEN GENERAL | DB13: =IF(ISNUMBER(M13),MONTH(M13),0) -> 4 | DC13: =IF(ISNUMBER(M13),IF(ISERROR(HLOOKUP(MONTH(M13),meses_104,1,0)),"NO","SI"),"NO") -> SI | DD13: =IF(ISNUMBER(M13),IF(ISERROR(HLOOKUP(MONTH(M13),meses_103,1,0)),"NO","SI"),"NO") -> SI | DE13: =IF(ISBLANK(G13),0,IF(VALUE(LEFT(G13,2))=4,0,AT13)) -> 1400 | DF13: =IF(ISBLANK(G13),0,IF(VALUE(LEFT(G13,2))=4,0,AV13)) -> 0 | DG13: =IF(ISBLANK(G13),0,IF(VALUE(LEFT(G13,2))=4,0,AX13)) -> 0 | DH13: =SUM(U13:W13)+SUM(AG13:AJ13) -> 0 | DI13: =ROUND((IF(AS13=545,(Z13+AC13+AF13),0)+IF(AU13=545,(Z13+AC13+AF13),0)+IF(AW13=545,(Z13+AC13+AF13),0)),2) -> 0 | DJ13: =ROUND((IF(AS13=512,Z13,0)+IF(AU13=512,Z13,0)+IF(AW13=512,Z13,0)),2) -> 0 | DK13: =Z13+AC13+AF13-DI13-DJ13 -> 210 | DL13: =SUM(CC13:CH13)+CJ13 -> 147 | DM13: =CI13 -> 0 | DN13: =BI13+BR13+CA13 -> 0 | DQ13: 07 | DR13: PENDIENTE | DX13: OTROS | DY13: NORMAL | EE13: 0 | EF13: 0 | EG13: 0
A14: 1791310063001 | B14: R-Ruc | C14: DATAFAST S A | D14: 02-Sociedad | E14: NO | G14: 01-Factura | H14: 001 | I14: 003 | J14: 001625097 | K14: 0504202601179131006300120010030016250971804581210 | L14: 46117 | M14: 46117 | T14: 02- Costo o Gasto para declaración de IR (servicios y bienes distintos de inventarios y activos fijos) | U14: 0 | V14: 0 | W14: 0 | X14: 12.5 | Y14: 15 | Z14: =ROUND(X14*Y14%,2) -> 1.88 | AA14: 0 | AB14: 5 | AC14: =ROUND(AA14*AB14%,2) -> 0 | AE14: 8 | AF14: =ROUND(AD14*AE14%,2) -> 0 | AG14: 0 | AH14: 0 | AI14: 0 | AJ14: 0 | AK14: =ROUND(SUM(U14:X14)+SUM(Z14:AA14)+SUM(AC14:AD14)+SUM(AF14:AJ14),2) -> 14.38 | AL14: 0 | AR14: ACT. EMPRESARIALES CON REGISTRO DE INGRESOS Y EGRESOS | AS14: 510 | AT14: =IF(OR(AS14=545, AS14=518),($AK14-$Z14-$AC14-$AF14),IF(AND(AS14>515,AS14<518),($W14),IF(AND(AS14>509,AS14<516),$X14,IF(AS14=541,$U14,IF(AS14=542,$V14+SUM($AG14:$AJ14),IF(AS14=533,$AD14,IF(AS14=550,$AA14,0))))))) -> 12.5 | AU14: 0 | AV14: =IF(OR(AU14=545, AU14=518),($AK14-$Z14-$AC14-$AF14),IF(AND(AU14>515,AU14<518),($W14),IF(AND(AU14>509,AU14<516),$X14,IF(AU14=541,$U14,IF(AU14=542,$V14+SUM($AG14:$AJ14),IF(AU14=533,$AD14,IF(AU14=550,$AA14,0))))))) -> 0 | AW14: 542 | AX14: =IF(OR(AW14=545, AW14=518),($AK14-$Z14-$AC14-$AF14),IF(AND(AW14>515,AW14<518),($W14),IF(AND(AW14>509,AW14<516),$X14,IF(AW14=541,$U14,IF(AW14=542,$V14+SUM($AG14:$AJ14),IF(AW14=533,$AD14,IF(AW14=550,$AA14,0))))))) -> 0 | BF14: 332 | BG14: =SUM(U14:X14)-V14+AA14+AD14 -> 12.5 | BH14: =IF(ISERROR(VLOOKUP(BF14,Parametros!$C:$J,8,0)),0,VLOOKUP(BF14,Parametros!$C:$J,8,0)) -> 0 | BI14: =IF(ISERROR(ROUND((BG14*BH14),2)),0,ROUND((BG14*BH14),2)) -> 0 | BK14: 0 | BM14: 0 | BN14: 0 | BP14: =SUM(U14:X14)-V14+AA14+AD14-BG14 -> 0 | BQ14: =IF(ISERROR(VLOOKUP(BO14,Parametros!$C:$J,8,0)),0,VLOOKUP(BO14,Parametros!$C:$J,8,0)) -> 0 | BR14: =IF(ISERROR(ROUND((BP14*BQ14),2)),0,ROUND((BP14*BQ14),2)) -> 0 | BT14: 0 | BV14: 0 | BW14: 0 | BY14: =SUM(U14:X14)-V14+AA14+AD14-BG14-BP14 -> 0 | BZ14: =IF(ISERROR(VLOOKUP(BX14,Parametros!$C:$J,8,0)),0,VLOOKUP(BX14,Parametros!$C:$J,8,0)) -> 0 | CA14: =IF(ISERROR(ROUND((BY14*BZ14),2)),0,ROUND((BY14*BZ14),2)) -> 0 | CC14: 0 | CD14: 0 | CE14: 0 | CF14: 0 | CG14: 0 | CH14: 0 | CI14: 0 | CJ14: 0 | CK14: =+BI14+BR14+CA14+SUM(CC14:CJ14) -> 0 | CP14: 01-PAGO A RESIDENTE | CQ14: 01-SIN UTILIZACION DEL SISTEMA FINANCIERO | CS14: 01-REGIMEN GENERAL | DB14: =IF(ISNUMBER(M14),MONTH(M14),0) -> 4 | DC14: =IF(ISNUMBER(M14),IF(ISERROR(HLOOKUP(MONTH(M14),meses_104,1,0)),"NO","SI"),"NO") -> SI | DD14: =IF(ISNUMBER(M14),IF(ISERROR(HLOOKUP(MONTH(M14),meses_103,1,0)),"NO","SI"),"NO") -> SI | DE14: =IF(ISBLANK(G14),0,IF(VALUE(LEFT(G14,2))=4,0,AT14)) -> 12.5 | DF14: =IF(ISBLANK(G14),0,IF(VALUE(LEFT(G14,2))=4,0,AV14)) -> 0 | DG14: =IF(ISBLANK(G14),0,IF(VALUE(LEFT(G14,2))=4,0,AX14)) -> 0 | DH14: =SUM(U14:W14)+SUM(AG14:AJ14) -> 0 | DI14: =ROUND((IF(AS14=545,(Z14+AC14+AF14),0)+IF(AU14=545,(Z14+AC14+AF14),0)+IF(AW14=545,(Z14+AC14+AF14),0)),2) -> 0 | DJ14: =ROUND((IF(AS14=512,Z14,0)+IF(AU14=512,Z14,0)+IF(AW14=512,Z14,0)),2) -> 0 | DK14: =Z14+AC14+AF14-DI14-DJ14 -> 1.88 | DL14: =SUM(CC14:CH14)+CJ14 -> 0 | DM14: =CI14 -> 0 | DN14: =BI14+BR14+CA14 -> 0 | DQ14: 07 | DR14: PENDIENTE | DX14: OTROS | DY14: NORMAL | EE14: 0 | EF14: 0 | EG14: 0
A15: 0993013730001 | B15: R-Ruc | C15: Telepuerto Internacional Del Ecuador CABLERED S.A. | D15: 02-Sociedad | E15: NO | G15: 01-Factura | H15: 001 | I15: 002 | J15: 000000140 | K15: 0604202601099301373000120010020000001408058553819 | L15: 46118 | M15: 46118 | T15: 02- Costo o Gasto para declaración de IR (servicios y bienes distintos de inventarios y activos fijos) | U15: 0 | V15: 0 | W15: 0 | X15: 795 | Y15: 15 | Z15: =ROUND(X15*Y15%,2) -> 119.25 | AA15: 0 | AB15: 5 | AC15: =ROUND(AA15*AB15%,2) -> 0 | AE15: 8 | AF15: =ROUND(AD15*AE15%,2) -> 0 | AG15: 0 | AH15: 0 | AI15: 0 | AJ15: 0 | AK15: =ROUND(SUM(U15:X15)+SUM(Z15:AA15)+SUM(AC15:AD15)+SUM(AF15:AJ15),2) -> 914.25 | AL15: 0 | AR15: ACT. EMPRESARIALES CON REGISTRO DE INGRESOS Y EGRESOS | AS15: 510 | AT15: =IF(OR(AS15=545, AS15=518),($AK15-$Z15-$AC15-$AF15),IF(AND(AS15>515,AS15<518),($W15),IF(AND(AS15>509,AS15<516),$X15,IF(AS15=541,$U15,IF(AS15=542,$V15+SUM($AG15:$AJ15),IF(AS15=533,$AD15,IF(AS15=550,$AA15,0))))))) -> 795 | AU15: 0 | AV15: =IF(OR(AU15=545, AU15=518),($AK15-$Z15-$AC15-$AF15),IF(AND(AU15>515,AU15<518),($W15),IF(AND(AU15>509,AU15<516),$X15,IF(AU15=541,$U15,IF(AU15=542,$V15+SUM($AG15:$AJ15),IF(AU15=533,$AD15,IF(AU15=550,$AA15,0))))))) -> 0 | AW15: 542 | AX15: =IF(OR(AW15=545, AW15=518),($AK15-$Z15-$AC15-$AF15),IF(AND(AW15>515,AW15<518),($W15),IF(AND(AW15>509,AW15<516),$X15,IF(AW15=541,$U15,IF(AW15=542,$V15+SUM($AG15:$AJ15),IF(AW15=533,$AD15,IF(AW15=550,$AA15,0))))))) -> 0 | AZ15: E-Electronico(v1.0) | BA15: 003 | BB15: 001 | BC15: 000000090 | BD15: 1604202607091780945100120030010000000907817582610 | BE15: 46128 | BF15: 309 | BG15: =SUM(U15:X15)-V15+AA15+AD15 -> 795 | BH15: 0.03 | BI15: =IF(ISERROR(ROUND((BG15*BH15),2)),0,ROUND((BG15*BH15),2)) -> 23.85 | BK15: 0 | BM15: 0 | BN15: 0 | BP15: =SUM(U15:X15)-V15+AA15+AD15-BG15 -> 0 | BQ15: =IF(ISERROR(VLOOKUP(BO15,Parametros!$C:$J,8,0)),0,VLOOKUP(BO15,Parametros!$C:$J,8,0)) -> 0 | BR15: =IF(ISERROR(ROUND((BP15*BQ15),2)),0,ROUND((BP15*BQ15),2)) -> 0 | BT15: 0 | BV15: 0 | BW15: 0 | BY15: =SUM(U15:X15)-V15+AA15+AD15-BG15-BP15 -> 0 | BZ15: =IF(ISERROR(VLOOKUP(BX15,Parametros!$C:$J,8,0)),0,VLOOKUP(BX15,Parametros!$C:$J,8,0)) -> 0 | CA15: =IF(ISERROR(ROUND((BY15*BZ15),2)),0,ROUND((BY15*BZ15),2)) -> 0 | CC15: 0 | CD15: 0 | CE15: 0 | CF15: 0 | CG15: 0 | CH15: 0 | CI15: 0 | CJ15: 0 | CK15: =+BI15+BR15+CA15+SUM(CC15:CJ15) -> 23.85 | CP15: 01-PAGO A RESIDENTE | CQ15: 20-OTROS CON UTILIZACION DEL SISTEMA FINANCIERO | CS15: 01-REGIMEN GENERAL | DB15: =IF(ISNUMBER(M15),MONTH(M15),0) -> 4 | DC15: =IF(ISNUMBER(M15),IF(ISERROR(HLOOKUP(MONTH(M15),meses_104,1,0)),"NO","SI"),"NO") -> SI | DD15: =IF(ISNUMBER(M15),IF(ISERROR(HLOOKUP(MONTH(M15),meses_103,1,0)),"NO","SI"),"NO") -> SI | DE15: =IF(ISBLANK(G15),0,IF(VALUE(LEFT(G15,2))=4,0,AT15)) -> 795 | DF15: =IF(ISBLANK(G15),0,IF(VALUE(LEFT(G15,2))=4,0,AV15)) -> 0 | DG15: =IF(ISBLANK(G15),0,IF(VALUE(LEFT(G15,2))=4,0,AX15)) -> 0 | DH15: =SUM(U15:W15)+SUM(AG15:AJ15) -> 0 | DI15: =ROUND((IF(AS15=545,(Z15+AC15+AF15),0)+IF(AU15=545,(Z15+AC15+AF15),0)+IF(AW15=545,(Z15+AC15+AF15),0)),2) -> 0 | DJ15: =ROUND((IF(AS15=512,Z15,0)+IF(AU15=512,Z15,0)+IF(AW15=512,Z15,0)),2) -> 0 | DK15: =Z15+AC15+AF15-DI15-DJ15 -> 119.25 | DL15: =SUM(CC15:CH15)+CJ15 -> 0 | DM15: =CI15 -> 0 | DN15: =BI15+BR15+CA15 -> 23.85 | DQ15: 07 | DR15: PENDIENTE | DX15: OTROS | DY15: NORMAL | EE15: 0 | EF15: 0 | EG15: 0
A16: 0915235246001 | B16: R-Ruc | C16: SILVA MERA DAVID ALEXANDER | D16: 01-Persona Natural | E16: NO | G16: 01-Factura | H16: 003 | I16: 006 | J16: 000078449 | K16: 0604202601091523524600120030060000784491234567817 | L16: 46118 | M16: 46118 | T16: 02- Costo o Gasto para declaración de IR (servicios y bienes distintos de inventarios y activos fijos) | U16: 0 | V16: 0 | W16: 0 | X16: 29.14 | Y16: 15 | Z16: =ROUND(X16*Y16%,2) -> 4.37 | AA16: 0 | AB16: 5 | AC16: =ROUND(AA16*AB16%,2) -> 0 | AE16: 8 | AF16: =ROUND(AD16*AE16%,2) -> 0 | AG16: 0 | AH16: 0 | AI16: 0 | AJ16: 0 | AK16: =ROUND(SUM(U16:X16)+SUM(Z16:AA16)+SUM(AC16:AD16)+SUM(AF16:AJ16),2) -> 33.51 | AL16: 0 | AR16: ACT. EMPRESARIALES CON REGISTRO DE INGRESOS Y EGRESOS | AS16: 510 | AT16: =IF(OR(AS16=545, AS16=518),($AK16-$Z16-$AC16-$AF16),IF(AND(AS16>515,AS16<518),($W16),IF(AND(AS16>509,AS16<516),$X16,IF(AS16=541,$U16,IF(AS16=542,$V16+SUM($AG16:$AJ16),IF(AS16=533,$AD16,IF(AS16=550,$AA16,0))))))) -> 29.14 | AU16: 0 | AV16: =IF(OR(AU16=545, AU16=518),($AK16-$Z16-$AC16-$AF16),IF(AND(AU16>515,AU16<518),($W16),IF(AND(AU16>509,AU16<516),$X16,IF(AU16=541,$U16,IF(AU16=542,$V16+SUM($AG16:$AJ16),IF(AU16=533,$AD16,IF(AU16=550,$AA16,0))))))) -> 0 | AW16: 542 | AX16: =IF(OR(AW16=545, AW16=518),($AK16-$Z16-$AC16-$AF16),IF(AND(AW16>515,AW16<518),($W16),IF(AND(AW16>509,AW16<516),$X16,IF(AW16=541,$U16,IF(AW16=542,$V16+SUM($AG16:$AJ16),IF(AW16=533,$AD16,IF(AW16=550,$AA16,0))))))) -> 0 | BF16: 332 | BG16: =SUM(U16:X16)-V16+AA16+AD16 -> 29.14 | BH16: =IF(ISERROR(VLOOKUP(BF16,Parametros!$C:$J,8,0)),0,VLOOKUP(BF16,Parametros!$C:$J,8,0)) -> 0 | BI16: =IF(ISERROR(ROUND((BG16*BH16),2)),0,ROUND((BG16*BH16),2)) -> 0 | BK16: 0 | BM16: 0 | BN16: 0 | BP16: =SUM(U16:X16)-V16+AA16+AD16-BG16 -> 0 | BQ16: =IF(ISERROR(VLOOKUP(BO16,Parametros!$C:$J,8,0)),0,VLOOKUP(BO16,Parametros!$C:$J,8,0)) -> 0 | BR16: =IF(ISERROR(ROUND((BP16*BQ16),2)),0,ROUND((BP16*BQ16),2)) -> 0 | BT16: 0 | BV16: 0 | BW16: 0 | BY16: =SUM(U16:X16)-V16+AA16+AD16-BG16-BP16 -> 0 | BZ16: =IF(ISERROR(VLOOKUP(BX16,Parametros!$C:$J,8,0)),0,VLOOKUP(BX16,Parametros!$C:$J,8,0)) -> 0 | CA16: =IF(ISERROR(ROUND((BY16*BZ16),2)),0,ROUND((BY16*BZ16),2)) -> 0 | CC16: 0 | CD16: 0 | CE16: 0 | CF16: 0 | CG16: 0 | CH16: 0 | CI16: 0 | CJ16: 0 | CK16: =+BI16+BR16+CA16+SUM(CC16:CJ16) -> 0 | CP16: 01-PAGO A RESIDENTE | CQ16: 01-SIN UTILIZACION DEL SISTEMA FINANCIERO | CS16: 01-REGIMEN GENERAL | DB16: =IF(ISNUMBER(M16),MONTH(M16),0) -> 4 | DC16: =IF(ISNUMBER(M16),IF(ISERROR(HLOOKUP(MONTH(M16),meses_104,1,0)),"NO","SI"),"NO") -> SI | DD16: =IF(ISNUMBER(M16),IF(ISERROR(HLOOKUP(MONTH(M16),meses_103,1,0)),"NO","SI"),"NO") -> SI | DE16: =IF(ISBLANK(G16),0,IF(VALUE(LEFT(G16,2))=4,0,AT16)) -> 29.14 | DF16: =IF(ISBLANK(G16),0,IF(VALUE(LEFT(G16,2))=4,0,AV16)) -> 0 | DG16: =IF(ISBLANK(G16),0,IF(VALUE(LEFT(G16,2))=4,0,AX16)) -> 0 | DH16: =SUM(U16:W16)+SUM(AG16:AJ16) -> 0 | DI16: =ROUND((IF(AS16=545,(Z16+AC16+AF16),0)+IF(AU16=545,(Z16+AC16+AF16),0)+IF(AW16=545,(Z16+AC16+AF16),0)),2) -> 0 | DJ16: =ROUND((IF(AS16=512,Z16,0)+IF(AU16=512,Z16,0)+IF(AW16=512,Z16,0)),2) -> 0 | DK16: =Z16+AC16+AF16-DI16-DJ16 -> 4.37 | DL16: =SUM(CC16:CH16)+CJ16 -> 0 | DM16: =CI16 -> 0 | DN16: =BI16+BR16+CA16 -> 0 | DQ16: 07 | DR16: PENDIENTE | DX16: OTROS | DY16: NORMAL | EE16: 0 | EF16: 0 | EG16: 0
A17: 0921638813001 | B17: R-Ruc | C17: LITUMA RAMIREZ RUTH ELSA | D17: 01-Persona Natural | E17: NO | G17: 01-Factura | H17: 001 | I17: 100 | J17: 000748621 | K17: 0704202601092163881300120011000007486210704202611 | L17: 46119 | M17: 46119 | T17: 02- Costo o Gasto para declaración de IR (servicios y bienes distintos de inventarios y activos fijos) | U17: 0 | V17: 0 | W17: 0 | X17: 9.03 | Y17: 15 | Z17: =ROUND(X17*Y17%,2) -> 1.35 | AA17: 0 | AB17: 5 | AC17: =ROUND(AA17*AB17%,2) -> 0 | AE17: 8 | AF17: =ROUND(AD17*AE17%,2) -> 0 | AG17: 0 | AH17: 0 | AI17: 0 | AJ17: 0 | AK17: =ROUND(SUM(U17:X17)+SUM(Z17:AA17)+SUM(AC17:AD17)+SUM(AF17:AJ17),2) -> 10.38 | AL17: 0 | AR17: ACT. EMPRESARIALES CON REGISTRO DE INGRESOS Y EGRESOS | AS17: 510 | AT17: =IF(OR(AS17=545, AS17=518),($AK17-$Z17-$AC17-$AF17),IF(AND(AS17>515,AS17<518),($W17),IF(AND(AS17>509,AS17<516),$X17,IF(AS17=541,$U17,IF(AS17=542,$V17+SUM($AG17:$AJ17),IF(AS17=533,$AD17,IF(AS17=550,$AA17,0))))))) -> 9.03 | AU17: 0 | AV17: =IF(OR(AU17=545, AU17=518),($AK17-$Z17-$AC17-$AF17),IF(AND(AU17>515,AU17<518),($W17),IF(AND(AU17>509,AU17<516),$X17,IF(AU17=541,$U17,IF(AU17=542,$V17+SUM($AG17:$AJ17),IF(AU17=533,$AD17,IF(AU17=550,$AA17,0))))))) -> 0 | AW17: 542 | AX17: =IF(OR(AW17=545, AW17=518),($AK17-$Z17-$AC17-$AF17),IF(AND(AW17>515,AW17<518),($W17),IF(AND(AW17>509,AW17<516),$X17,IF(AW17=541,$U17,IF(AW17=542,$V17+SUM($AG17:$AJ17),IF(AW17=533,$AD17,IF(AW17=550,$AA17,0))))))) -> 0 | BF17: 332 | BG17: =SUM(U17:X17)-V17+AA17+AD17 -> 9.03 | BH17: =IF(ISERROR(VLOOKUP(BF17,Parametros!$C:$J,8,0)),0,VLOOKUP(BF17,Parametros!$C:$J,8,0)) -> 0 | BI17: =IF(ISERROR(ROUND((BG17*BH17),2)),0,ROUND((BG17*BH17),2)) -> 0 | BK17: 0 | BM17: 0 | BN17: 0 | BP17: =SUM(U17:X17)-V17+AA17+AD17-BG17 -> 0 | BQ17: =IF(ISERROR(VLOOKUP(BO17,Parametros!$C:$J,8,0)),0,VLOOKUP(BO17,Parametros!$C:$J,8,0)) -> 0 | BR17: =IF(ISERROR(ROUND((BP17*BQ17),2)),0,ROUND((BP17*BQ17),2)) -> 0 | BT17: 0 | BV17: 0 | BW17: 0 | BY17: =SUM(U17:X17)-V17+AA17+AD17-BG17-BP17 -> 0 | BZ17: =IF(ISERROR(VLOOKUP(BX17,Parametros!$C:$J,8,0)),0,VLOOKUP(BX17,Parametros!$C:$J,8,0)) -> 0 | CA17: =IF(ISERROR(ROUND((BY17*BZ17),2)),0,ROUND((BY17*BZ17),2)) -> 0 | CC17: 0 | CD17: 0 | CE17: 0 | CF17: 0 | CG17: 0 | CH17: 0 | CI17: 0 | CJ17: 0 | CK17: =+BI17+BR17+CA17+SUM(CC17:CJ17) -> 0 | CP17: 01-PAGO A RESIDENTE | CQ17: 01-SIN UTILIZACION DEL SISTEMA FINANCIERO | CS17: 01-REGIMEN GENERAL | DB17: =IF(ISNUMBER(M17),MONTH(M17),0) -> 4 | DC17: =IF(ISNUMBER(M17),IF(ISERROR(HLOOKUP(MONTH(M17),meses_104,1,0)),"NO","SI"),"NO") -> SI | DD17: =IF(ISNUMBER(M17),IF(ISERROR(HLOOKUP(MONTH(M17),meses_103,1,0)),"NO","SI"),"NO") -> SI | DE17: =IF(ISBLANK(G17),0,IF(VALUE(LEFT(G17,2))=4,0,AT17)) -> 9.03 | DF17: =IF(ISBLANK(G17),0,IF(VALUE(LEFT(G17,2))=4,0,AV17)) -> 0 | DG17: =IF(ISBLANK(G17),0,IF(VALUE(LEFT(G17,2))=4,0,AX17)) -> 0 | DH17: =SUM(U17:W17)+SUM(AG17:AJ17) -> 0 | DI17: =ROUND((IF(AS17=545,(Z17+AC17+AF17),0)+IF(AU17=545,(Z17+AC17+AF17),0)+IF(AW17=545,(Z17+AC17+AF17),0)),2) -> 0 | DJ17: =ROUND((IF(AS17=512,Z17,0)+IF(AU17=512,Z17,0)+IF(AW17=512,Z17,0)),2) -> 0 | DK17: =Z17+AC17+AF17-DI17-DJ17 -> 1.35 | DL17: =SUM(CC17:CH17)+CJ17 -> 0 | DM17: =CI17 -> 0 | DN17: =BI17+BR17+CA17 -> 0 | DQ17: 07 | DR17: PENDIENTE | DX17: OTROS | DY17: NORMAL | EE17: 0 | EF17: 0 | EG17: 0
A18: 1002074019001 | B18: R-Ruc | C18: SANTACRUZ TERAN JANNETH EULALIA | D18: 01-Persona Natural | E18: NO | G18: 01-Factura | H18: 001 | I18: 005 | J18: 000026071 | K18: 0704202601100207401900120010050000260711234567815 | L18: 46119 | M18: 46119 | T18: 02- Costo o Gasto para declaración de IR (servicios y bienes distintos de inventarios y activos fijos) | U18: 0 | V18: 0 | W18: 0 | X18: 10.35 | Y18: 15 | Z18: =ROUND(X18*Y18%,2) -> 1.55 | AA18: 0 | AB18: 5 | AC18: =ROUND(AA18*AB18%,2) -> 0 | AE18: 8 | AF18: =ROUND(AD18*AE18%,2) -> 0 | AG18: 0 | AH18: 0 | AI18: 0 | AJ18: 0 | AK18: =ROUND(SUM(U18:X18)+SUM(Z18:AA18)+SUM(AC18:AD18)+SUM(AF18:AJ18),2) -> 11.9 | AL18: 0 | AR18: ACT. EMPRESARIALES CON REGISTRO DE INGRESOS Y EGRESOS | AS18: 510 | AT18: =IF(OR(AS18=545, AS18=518),($AK18-$Z18-$AC18-$AF18),IF(AND(AS18>515,AS18<518),($W18),IF(AND(AS18>509,AS18<516),$X18,IF(AS18=541,$U18,IF(AS18=542,$V18+SUM($AG18:$AJ18),IF(AS18=533,$AD18,IF(AS18=550,$AA18,0))))))) -> 10.35 | AU18: 0 | AV18: =IF(OR(AU18=545, AU18=518),($AK18-$Z18-$AC18-$AF18),IF(AND(AU18>515,AU18<518),($W18),IF(AND(AU18>509,AU18<516),$X18,IF(AU18=541,$U18,IF(AU18=542,$V18+SUM($AG18:$AJ18),IF(AU18=533,$AD18,IF(AU18=550,$AA18,0))))))) -> 0 | AW18: 542 | AX18: =IF(OR(AW18=545, AW18=518),($AK18-$Z18-$AC18-$AF18),IF(AND(AW18>515,AW18<518),($W18),IF(AND(AW18>509,AW18<516),$X18,IF(AW18=541,$U18,IF(AW18=542,$V18+SUM($AG18:$AJ18),IF(AW18=533,$AD18,IF(AW18=550,$AA18,0))))))) -> 0 | BF18: 332 | BG18: =SUM(U18:X18)-V18+AA18+AD18 -> 10.35 | BH18: =IF(ISERROR(VLOOKUP(BF18,Parametros!$C:$J,8,0)),0,VLOOKUP(BF18,Parametros!$C:$J,8,0)) -> 0 | BI18: =IF(ISERROR(ROUND((BG18*BH18),2)),0,ROUND((BG18*BH18),2)) -> 0 | BK18: 0 | BM18: 0 | BN18: 0 | BP18: =SUM(U18:X18)-V18+AA18+AD18-BG18 -> 0 | BQ18: =IF(ISERROR(VLOOKUP(BO18,Parametros!$C:$J,8,0)),0,VLOOKUP(BO18,Parametros!$C:$J,8,0)) -> 0 | BR18: =IF(ISERROR(ROUND((BP18*BQ18),2)),0,ROUND((BP18*BQ18),2)) -> 0 | BT18: 0 | BV18: 0 | BW18: 0 | BY18: =SUM(U18:X18)-V18+AA18+AD18-BG18-BP18 -> 0 | BZ18: =IF(ISERROR(VLOOKUP(BX18,Parametros!$C:$J,8,0)),0,VLOOKUP(BX18,Parametros!$C:$J,8,0)) -> 0 | CA18: =IF(ISERROR(ROUND((BY18*BZ18),2)),0,ROUND((BY18*BZ18),2)) -> 0 | CC18: 0 | CD18: 0 | CE18: 0 | CF18: 0 | CG18: 0 | CH18: 0 | CI18: 0 | CJ18: 0 | CK18: =+BI18+BR18+CA18+SUM(CC18:CJ18) -> 0 | CP18: 01-PAGO A RESIDENTE | CQ18: 01-SIN UTILIZACION DEL SISTEMA FINANCIERO | CS18: 01-REGIMEN GENERAL | DB18: =IF(ISNUMBER(M18),MONTH(M18),0) -> 4 | DC18: =IF(ISNUMBER(M18),IF(ISERROR(HLOOKUP(MONTH(M18),meses_104,1,0)),"NO","SI"),"NO") -> SI | DD18: =IF(ISNUMBER(M18),IF(ISERROR(HLOOKUP(MONTH(M18),meses_103,1,0)),"NO","SI"),"NO") -> SI | DE18: =IF(ISBLANK(G18),0,IF(VALUE(LEFT(G18,2))=4,0,AT18)) -> 10.35 | DF18: =IF(ISBLANK(G18),0,IF(VALUE(LEFT(G18,2))=4,0,AV18)) -> 0 | DG18: =IF(ISBLANK(G18),0,IF(VALUE(LEFT(G18,2))=4,0,AX18)) -> 0 | DH18: =SUM(U18:W18)+SUM(AG18:AJ18) -> 0 | DI18: =ROUND((IF(AS18=545,(Z18+AC18+AF18),0)+IF(AU18=545,(Z18+AC18+AF18),0)+IF(AW18=545,(Z18+AC18+AF18),0)),2) -> 0 | DJ18: =ROUND((IF(AS18=512,Z18,0)+IF(AU18=512,Z18,0)+IF(AW18=512,Z18,0)),2) -> 0 | DK18: =Z18+AC18+AF18-DI18-DJ18 -> 1.55 | DL18: =SUM(CC18:CH18)+CJ18 -> 0 | DM18: =CI18 -> 0 | DN18: =BI18+BR18+CA18 -> 0 | DQ18: 07 | DR18: PENDIENTE | DX18: OTROS | DY18: NORMAL | EE18: 0 | EF18: 0 | EG18: 0
A19: 0993369027001 | B19: R-Ruc | C19: VUELATECHNOLOGY SAS | D19: 02-Sociedad | E19: NO | G19: 01-Factura | H19: 001 | I19: 002 | J19: 000067092 | K19: 0804202601099336902700120010020000670921234567811 | L19: 46120 | M19: 46120 | T19: 02- Costo o Gasto para declaración de IR (servicios y bienes distintos de inventarios y activos fijos) | U19: 0 | V19: 0 | W19: 0 | X19: 21.74 | Y19: 15 | Z19: =ROUND(X19*Y19%,2) -> 3.26 | AA19: 0 | AB19: 5 | AC19: =ROUND(AA19*AB19%,2) -> 0 | AE19: 8 | AF19: =ROUND(AD19*AE19%,2) -> 0 | AG19: 0 | AH19: 0 | AI19: 0 | AJ19: 0 | AK19: =ROUND(SUM(U19:X19)+SUM(Z19:AA19)+SUM(AC19:AD19)+SUM(AF19:AJ19),2) -> 25 | AL19: 0 | AR19: ACT. EMPRESARIALES CON REGISTRO DE INGRESOS Y EGRESOS | AS19: 510 | AT19: =IF(OR(AS19=545, AS19=518),($AK19-$Z19-$AC19-$AF19),IF(AND(AS19>515,AS19<518),($W19),IF(AND(AS19>509,AS19<516),$X19,IF(AS19=541,$U19,IF(AS19=542,$V19+SUM($AG19:$AJ19),IF(AS19=533,$AD19,IF(AS19=550,$AA19,0))))))) -> 21.74 | AU19: 0 | AV19: =IF(OR(AU19=545, AU19=518),($AK19-$Z19-$AC19-$AF19),IF(AND(AU19>515,AU19<518),($W19),IF(AND(AU19>509,AU19<516),$X19,IF(AU19=541,$U19,IF(AU19=542,$V19+SUM($AG19:$AJ19),IF(AU19=533,$AD19,IF(AU19=550,$AA19,0))))))) -> 0 | AW19: 542 | AX19: =IF(OR(AW19=545, AW19=518),($AK19-$Z19-$AC19-$AF19),IF(AND(AW19>515,AW19<518),($W19),IF(AND(AW19>509,AW19<516),$X19,IF(AW19=541,$U19,IF(AW19=542,$V19+SUM($AG19:$AJ19),IF(AW19=533,$AD19,IF(AW19=550,$AA19,0))))))) -> 0 | BF19: 332 | BG19: =SUM(U19:X19)-V19+AA19+AD19 -> 21.74 | BH19: =IF(ISERROR(VLOOKUP(BF19,Parametros!$C:$J,8,0)),0,VLOOKUP(BF19,Parametros!$C:$J,8,0)) -> 0 | BI19: =IF(ISERROR(ROUND((BG19*BH19),2)),0,ROUND((BG19*BH19),2)) -> 0 | BK19: 0 | BM19: 0 | BN19: 0 | BP19: =SUM(U19:X19)-V19+AA19+AD19-BG19 -> 0 | BQ19: =IF(ISERROR(VLOOKUP(BO19,Parametros!$C:$J,8,0)),0,VLOOKUP(BO19,Parametros!$C:$J,8,0)) -> 0 | BR19: =IF(ISERROR(ROUND((BP19*BQ19),2)),0,ROUND((BP19*BQ19),2)) -> 0 | BT19: 0 | BV19: 0 | BW19: 0 | BY19: =SUM(U19:X19)-V19+AA19+AD19-BG19-BP19 -> 0 | BZ19: =IF(ISERROR(VLOOKUP(BX19,Parametros!$C:$J,8,0)),0,VLOOKUP(BX19,Parametros!$C:$J,8,0)) -> 0 | CA19: =IF(ISERROR(ROUND((BY19*BZ19),2)),0,ROUND((BY19*BZ19),2)) -> 0 | CC19: 0 | CD19: 0 | CE19: 0 | CF19: 0 | CG19: 0 | CH19: 0 | CI19: 0 | CJ19: 0 | CK19: =+BI19+BR19+CA19+SUM(CC19:CJ19) -> 0 | CP19: 01-PAGO A RESIDENTE | CQ19: 01-SIN UTILIZACION DEL SISTEMA FINANCIERO | CS19: 01-REGIMEN GENERAL | DB19: =IF(ISNUMBER(M19),MONTH(M19),0) -> 4 | DC19: =IF(ISNUMBER(M19),IF(ISERROR(HLOOKUP(MONTH(M19),meses_104,1,0)),"NO","SI"),"NO") -> SI | DD19: =IF(ISNUMBER(M19),IF(ISERROR(HLOOKUP(MONTH(M19),meses_103,1,0)),"NO","SI"),"NO") -> SI | DE19: =IF(ISBLANK(G19),0,IF(VALUE(LEFT(G19,2))=4,0,AT19)) -> 21.74 | DF19: =IF(ISBLANK(G19),0,IF(VALUE(LEFT(G19,2))=4,0,AV19)) -> 0 | DG19: =IF(ISBLANK(G19),0,IF(VALUE(LEFT(G19,2))=4,0,AX19)) -> 0 | DH19: =SUM(U19:W19)+SUM(AG19:AJ19) -> 0 | DI19: =ROUND((IF(AS19=545,(Z19+AC19+AF19),0)+IF(AU19=545,(Z19+AC19+AF19),0)+IF(AW19=545,(Z19+AC19+AF19),0)),2) -> 0 | DJ19: =ROUND((IF(AS19=512,Z19,0)+IF(AU19=512,Z19,0)+IF(AW19=512,Z19,0)),2) -> 0 | DK19: =Z19+AC19+AF19-DI19-DJ19 -> 3.26 | DL19: =SUM(CC19:CH19)+CJ19 -> 0 | DM19: =CI19 -> 0 | DN19: =BI19+BR19+CA19 -> 0 | DQ19: 07 | DR19: PENDIENTE | DX19: OTROS | DY19: NORMAL | EE19: 0 | EF19: 0 | EG19: 0
A20: 0993129496001 | B20: R-Ruc | C20: DIGICENTER S.A. | D20: 02-Sociedad | E20: NO | G20: 01-Factura | H20: 003 | I20: 901 | J20: 000081115 | K20: 0804202601099312949600120039010000811150079182010 | L20: 46120 | M20: 46120 | T20: 02- Costo o Gasto para declaración de IR (servicios y bienes distintos de inventarios y activos fijos) | U20: 0 | V20: 0 | W20: 0 | X20: 29.52 | Y20: 15 | Z20: =ROUND(X20*Y20%,2) -> 4.43 | AA20: 0 | AB20: 5 | AC20: =ROUND(AA20*AB20%,2) -> 0 | AE20: 8 | AF20: =ROUND(AD20*AE20%,2) -> 0 | AG20: 0 | AH20: 0 | AI20: 0 | AJ20: 0 | AK20: =ROUND(SUM(U20:X20)+SUM(Z20:AA20)+SUM(AC20:AD20)+SUM(AF20:AJ20),2) -> 33.95 | AL20: 0 | AR20: ACT. EMPRESARIALES CON REGISTRO DE INGRESOS Y EGRESOS | AS20: 510 | AT20: =IF(OR(AS20=545, AS20=518),($AK20-$Z20-$AC20-$AF20),IF(AND(AS20>515,AS20<518),($W20),IF(AND(AS20>509,AS20<516),$X20,IF(AS20=541,$U20,IF(AS20=542,$V20+SUM($AG20:$AJ20),IF(AS20=533,$AD20,IF(AS20=550,$AA20,0))))))) -> 29.52 | AU20: 0 | AV20: =IF(OR(AU20=545, AU20=518),($AK20-$Z20-$AC20-$AF20),IF(AND(AU20>515,AU20<518),($W20),IF(AND(AU20>509,AU20<516),$X20,IF(AU20=541,$U20,IF(AU20=542,$V20+SUM($AG20:$AJ20),IF(AU20=533,$AD20,IF(AU20=550,$AA20,0))))))) -> 0 | AW20: 542 | AX20: =IF(OR(AW20=545, AW20=518),($AK20-$Z20-$AC20-$AF20),IF(AND(AW20>515,AW20<518),($W20),IF(AND(AW20>509,AW20<516),$X20,IF(AW20=541,$U20,IF(AW20=542,$V20+SUM($AG20:$AJ20),IF(AW20=533,$AD20,IF(AW20=550,$AA20,0))))))) -> 0 | BF20: 332 | BG20: =SUM(U20:X20)-V20+AA20+AD20 -> 29.52 | BH20: =IF(ISERROR(VLOOKUP(BF20,Parametros!$C:$J,8,0)),0,VLOOKUP(BF20,Parametros!$C:$J,8,0)) -> 0 | BI20: =IF(ISERROR(ROUND((BG20*BH20),2)),0,ROUND((BG20*BH20),2)) -> 0 | BK20: 0 | BM20: 0 | BN20: 0 | BP20: =SUM(U20:X20)-V20+AA20+AD20-BG20 -> 0 | BQ20: =IF(ISERROR(VLOOKUP(BO20,Parametros!$C:$J,8,0)),0,VLOOKUP(BO20,Parametros!$C:$J,8,0)) -> 0 | BR20: =IF(ISERROR(ROUND((BP20*BQ20),2)),0,ROUND((BP20*BQ20),2)) -> 0 | BT20: 0 | BV20: 0 | BW20: 0 | BY20: =SUM(U20:X20)-V20+AA20+AD20-BG20-BP20 -> 0 | BZ20: =IF(ISERROR(VLOOKUP(BX20,Parametros!$C:$J,8,0)),0,VLOOKUP(BX20,Parametros!$C:$J,8,0)) -> 0 | CA20: =IF(ISERROR(ROUND((BY20*BZ20),2)),0,ROUND((BY20*BZ20),2)) -> 0 | CC20: 0 | CD20: 0 | CE20: 0 | CF20: 0 | CG20: 0 | CH20: 0 | CI20: 0 | CJ20: 0 | CK20: =+BI20+BR20+CA20+SUM(CC20:CJ20) -> 0 | CP20: 01-PAGO A RESIDENTE | CQ20: 01-SIN UTILIZACION DEL SISTEMA FINANCIERO | CS20: 01-REGIMEN GENERAL | DB20: =IF(ISNUMBER(M20),MONTH(M20),0) -> 4 | DC20: =IF(ISNUMBER(M20),IF(ISERROR(HLOOKUP(MONTH(M20),meses_104,1,0)),"NO","SI"),"NO") -> SI | DD20: =IF(ISNUMBER(M20),IF(ISERROR(HLOOKUP(MONTH(M20),meses_103,1,0)),"NO","SI"),"NO") -> SI | DE20: =IF(ISBLANK(G20),0,IF(VALUE(LEFT(G20,2))=4,0,AT20)) -> 29.52 | DF20: =IF(ISBLANK(G20),0,IF(VALUE(LEFT(G20,2))=4,0,AV20)) -> 0 | DG20: =IF(ISBLANK(G20),0,IF(VALUE(LEFT(G20,2))=4,0,AX20)) -> 0 | DH20: =SUM(U20:W20)+SUM(AG20:AJ20) -> 0 | DI20: =ROUND((IF(AS20=545,(Z20+AC20+AF20),0)+IF(AU20=545,(Z20+AC20+AF20),0)+IF(AW20=545,(Z20+AC20+AF20),0)),2) -> 0 | DJ20: =ROUND((IF(AS20=512,Z20,0)+IF(AU20=512,Z20,0)+IF(AW20=512,Z20,0)),2) -> 0 | DK20: =Z20+AC20+AF20-DI20-DJ20 -> 4.43 | DL20: =SUM(CC20:CH20)+CJ20 -> 0 | DM20: =CI20 -> 0 | DN20: =BI20+BR20+CA20 -> 0 | DQ20: 07 | DR20: PENDIENTE | DX20: OTROS | DY20: NORMAL | EE20: 0 | EF20: 0 | EG20: 0
A21: 1791413237001 | B21: R-Ruc | C21: SUPERDEPORTE S.A | D21: 02-Sociedad | E21: NO | G21: 01-Factura | H21: 113 | I21: 031 | J21: 000029271 | K21: 0804202601179141323700121130310000292710000000018 | L21: 46120 | M21: 46120 | T21: 02- Costo o Gasto para declaración de IR (servicios y bienes distintos de inventarios y activos fijos) | U21: 0 | V21: 0 | W21: 0 | X21: 145.11 | Y21: 15 | Z21: =ROUND(X21*Y21%,2) -> 21.77 | AA21: 0 | AB21: 5 | AC21: =ROUND(AA21*AB21%,2) -> 0 | AE21: 8 | AF21: =ROUND(AD21*AE21%,2) -> 0 | AG21: 0 | AH21: 0 | AI21: 0 | AJ21: 0 | AK21: =ROUND(SUM(U21:X21)+SUM(Z21:AA21)+SUM(AC21:AD21)+SUM(AF21:AJ21),2) -> 166.88 | AL21: 0 | AR21: ACT. EMPRESARIALES CON REGISTRO DE INGRESOS Y EGRESOS | AS21: 510 | AT21: =IF(OR(AS21=545, AS21=518),($AK21-$Z21-$AC21-$AF21),IF(AND(AS21>515,AS21<518),($W21),IF(AND(AS21>509,AS21<516),$X21,IF(AS21=541,$U21,IF(AS21=542,$V21+SUM($AG21:$AJ21),IF(AS21=533,$AD21,IF(AS21=550,$AA21,0))))))) -> 145.11 | AU21: 0 | AV21: =IF(OR(AU21=545, AU21=518),($AK21-$Z21-$AC21-$AF21),IF(AND(AU21>515,AU21<518),($W21),IF(AND(AU21>509,AU21<516),$X21,IF(AU21=541,$U21,IF(AU21=542,$V21+SUM($AG21:$AJ21),IF(AU21=533,$AD21,IF(AU21=550,$AA21,0))))))) -> 0 | AW21: 542 | AX21: =IF(OR(AW21=545, AW21=518),($AK21-$Z21-$AC21-$AF21),IF(AND(AW21>515,AW21<518),($W21),IF(AND(AW21>509,AW21<516),$X21,IF(AW21=541,$U21,IF(AW21=542,$V21+SUM($AG21:$AJ21),IF(AW21=533,$AD21,IF(AW21=550,$AA21,0))))))) -> 0 | BF21: 332 | BG21: =SUM(U21:X21)-V21+AA21+AD21 -> 145.11 | BH21: =IF(ISERROR(VLOOKUP(BF21,Parametros!$C:$J,8,0)),0,VLOOKUP(BF21,Parametros!$C:$J,8,0)) -> 0 | BI21: =IF(ISERROR(ROUND((BG21*BH21),2)),0,ROUND((BG21*BH21),2)) -> 0 | BK21: 0 | BM21: 0 | BN21: 0 | BP21: =SUM(U21:X21)-V21+AA21+AD21-BG21 -> 0 | BQ21: =IF(ISERROR(VLOOKUP(BO21,Parametros!$C:$J,8,0)),0,VLOOKUP(BO21,Parametros!$C:$J,8,0)) -> 0 | BR21: =IF(ISERROR(ROUND((BP21*BQ21),2)),0,ROUND((BP21*BQ21),2)) -> 0 | BT21: 0 | BV21: 0 | BW21: 0 | BY21: =SUM(U21:X21)-V21+AA21+AD21-BG21-BP21 -> 0 | BZ21: =IF(ISERROR(VLOOKUP(BX21,Parametros!$C:$J,8,0)),0,VLOOKUP(BX21,Parametros!$C:$J,8,0)) -> 0 | CA21: =IF(ISERROR(ROUND((BY21*BZ21),2)),0,ROUND((BY21*BZ21),2)) -> 0 | CC21: 0 | CD21: 0 | CE21: 0 | CF21: 0 | CG21: 0 | CH21: 0 | CI21: 0 | CJ21: 0 | CK21: =+BI21+BR21+CA21+SUM(CC21:CJ21) -> 0 | CP21: 01-PAGO A RESIDENTE | CQ21: 01-SIN UTILIZACION DEL SISTEMA FINANCIERO | CS21: 01-REGIMEN GENERAL | DB21: =IF(ISNUMBER(M21),MONTH(M21),0) -> 4 | DC21: =IF(ISNUMBER(M21),IF(ISERROR(HLOOKUP(MONTH(M21),meses_104,1,0)),"NO","SI"),"NO") -> SI | DD21: =IF(ISNUMBER(M21),IF(ISERROR(HLOOKUP(MONTH(M21),meses_103,1,0)),"NO","SI"),"NO") -> SI | DE21: =IF(ISBLANK(G21),0,IF(VALUE(LEFT(G21,2))=4,0,AT21)) -> 145.11 | DF21: =IF(ISBLANK(G21),0,IF(VALUE(LEFT(G21,2))=4,0,AV21)) -> 0 | DG21: =IF(ISBLANK(G21),0,IF(VALUE(LEFT(G21,2))=4,0,AX21)) -> 0 | DH21: =SUM(U21:W21)+SUM(AG21:AJ21) -> 0 | DI21: =ROUND((IF(AS21=545,(Z21+AC21+AF21),0)+IF(AU21=545,(Z21+AC21+AF21),0)+IF(AW21=545,(Z21+AC21+AF21),0)),2) -> 0 | DJ21: =ROUND((IF(AS21=512,Z21,0)+IF(AU21=512,Z21,0)+IF(AW21=512,Z21,0)),2) -> 0 | DK21: =Z21+AC21+AF21-DI21-DJ21 -> 21.77 | DL21: =SUM(CC21:CH21)+CJ21 -> 0 | DM21: =CI21 -> 0 | DN21: =BI21+BR21+CA21 -> 0 | DQ21: 07 | DR21: PENDIENTE | DX21: OTROS | DY21: NORMAL | EE21: 0 | EF21: 0 | EG21: 0
A22: 1791413237001 | B22: R-Ruc | C22: SUPERDEPORTE S.A. | D22: 02-Sociedad | E22: NO | G22: 01-Factura | H22: 016 | I22: 031 | J22: 000214576 | K22: 0804202601179141323700120160310002145760000000013 | L22: 46120 | M22: 46120 | T22: 02- Costo o Gasto para declaración de IR (servicios y bienes distintos de inventarios y activos fijos) | U22: 0 | V22: 0 | W22: 0 | X22: 75.7 | Y22: 15 | Z22: =ROUND(X22*Y22%,2) -> 11.36 | AA22: 0 | AB22: 5 | AC22: =ROUND(AA22*AB22%,2) -> 0 | AE22: 8 | AF22: =ROUND(AD22*AE22%,2) -> 0 | AG22: 0 | AH22: 0 | AI22: 0 | AJ22: 0 | AK22: =ROUND(SUM(U22:X22)+SUM(Z22:AA22)+SUM(AC22:AD22)+SUM(AF22:AJ22),2) -> 87.06 | AL22: 0 | AR22: ACT. EMPRESARIALES CON REGISTRO DE INGRESOS Y EGRESOS | AS22: 510 | AT22: =IF(OR(AS22=545, AS22=518),($AK22-$Z22-$AC22-$AF22),IF(AND(AS22>515,AS22<518),($W22),IF(AND(AS22>509,AS22<516),$X22,IF(AS22=541,$U22,IF(AS22=542,$V22+SUM($AG22:$AJ22),IF(AS22=533,$AD22,IF(AS22=550,$AA22,0))))))) -> 75.7 | AU22: 0 | AV22: =IF(OR(AU22=545, AU22=518),($AK22-$Z22-$AC22-$AF22),IF(AND(AU22>515,AU22<518),($W22),IF(AND(AU22>509,AU22<516),$X22,IF(AU22=541,$U22,IF(AU22=542,$V22+SUM($AG22:$AJ22),IF(AU22=533,$AD22,IF(AU22=550,$AA22,0))))))) -> 0 | AW22: 542 | AX22: =IF(OR(AW22=545, AW22=518),($AK22-$Z22-$AC22-$AF22),IF(AND(AW22>515,AW22<518),($W22),IF(AND(AW22>509,AW22<516),$X22,IF(AW22=541,$U22,IF(AW22=542,$V22+SUM($AG22:$AJ22),IF(AW22=533,$AD22,IF(AW22=550,$AA22,0))))))) -> 0 | BF22: 332 | BG22: =SUM(U22:X22)-V22+AA22+AD22 -> 75.7 | BH22: =IF(ISERROR(VLOOKUP(BF22,Parametros!$C:$J,8,0)),0,VLOOKUP(BF22,Parametros!$C:$J,8,0)) -> 0 | BI22: =IF(ISERROR(ROUND((BG22*BH22),2)),0,ROUND((BG22*BH22),2)) -> 0 | BK22: 0 | BM22: 0 | BN22: 0 | BP22: =SUM(U22:X22)-V22+AA22+AD22-BG22 -> 0 | BQ22: =IF(ISERROR(VLOOKUP(BO22,Parametros!$C:$J,8,0)),0,VLOOKUP(BO22,Parametros!$C:$J,8,0)) -> 0 | BR22: =IF(ISERROR(ROUND((BP22*BQ22),2)),0,ROUND((BP22*BQ22),2)) -> 0 | BT22: 0 | BV22: 0 | BW22: 0 | BY22: =SUM(U22:X22)-V22+AA22+AD22-BG22-BP22 -> 0 | BZ22: =IF(ISERROR(VLOOKUP(BX22,Parametros!$C:$J,8,0)),0,VLOOKUP(BX22,Parametros!$C:$J,8,0)) -> 0 | CA22: =IF(ISERROR(ROUND((BY22*BZ22),2)),0,ROUND((BY22*BZ22),2)) -> 0 | CC22: 0 | CD22: 0 | CE22: 0 | CF22: 0 | CG22: 0 | CH22: 0 | CI22: 0 | CJ22: 0 | CK22: =+BI22+BR22+CA22+SUM(CC22:CJ22) -> 0 | CP22: 01-PAGO A RESIDENTE | CQ22: 01-SIN UTILIZACION DEL SISTEMA FINANCIERO | CS22: 01-REGIMEN GENERAL | DB22: =IF(ISNUMBER(M22),MONTH(M22),0) -> 4 | DC22: =IF(ISNUMBER(M22),IF(ISERROR(HLOOKUP(MONTH(M22),meses_104,1,0)),"NO","SI"),"NO") -> SI | DD22: =IF(ISNUMBER(M22),IF(ISERROR(HLOOKUP(MONTH(M22),meses_103,1,0)),"NO","SI"),"NO") -> SI | DE22: =IF(ISBLANK(G22),0,IF(VALUE(LEFT(G22,2))=4,0,AT22)) -> 75.7 | DF22: =IF(ISBLANK(G22),0,IF(VALUE(LEFT(G22,2))=4,0,AV22)) -> 0 | DG22: =IF(ISBLANK(G22),0,IF(VALUE(LEFT(G22,2))=4,0,AX22)) -> 0 | DH22: =SUM(U22:W22)+SUM(AG22:AJ22) -> 0 | DI22: =ROUND((IF(AS22=545,(Z22+AC22+AF22),0)+IF(AU22=545,(Z22+AC22+AF22),0)+IF(AW22=545,(Z22+AC22+AF22),0)),2) -> 0 | DJ22: =ROUND((IF(AS22=512,Z22,0)+IF(AU22=512,Z22,0)+IF(AW22=512,Z22,0)),2) -> 0 | DK22: =Z22+AC22+AF22-DI22-DJ22 -> 11.36 | DL22: =SUM(CC22:CH22)+CJ22 -> 0 | DM22: =CI22 -> 0 | DN22: =BI22+BR22+CA22 -> 0 | DQ22: 07 | DR22: PENDIENTE | DX22: OTROS | DY22: NORMAL | EE22: 0 | EF22: 0 | EG22: 0
A23: 0990004196001 | B23: R-Ruc | C23: CORPORACION EL ROSADO S.A. | D23: 02-Sociedad | E23: NO | G23: 01-Factura | H23: 021 | I23: 010 | J23: 000824108 | K23: 0804202601099000419600120210100008241080082410815 | L23: 46120 | M23: 46120 | T23: 02- Costo o Gasto para declaración de IR (servicios y bienes distintos de inventarios y activos fijos) | U23: 0 | V23: 0 | W23: 0 | X23: 17.55 | Y23: 15 | Z23: =ROUND(X23*Y23%,2) -> 2.63 | AA23: 0 | AB23: 5 | AC23: =ROUND(AA23*AB23%,2) -> 0 | AE23: 8 | AF23: =ROUND(AD23*AE23%,2) -> 0 | AG23: 0 | AH23: 0 | AI23: 0 | AJ23: 0 | AK23: =ROUND(SUM(U23:X23)+SUM(Z23:AA23)+SUM(AC23:AD23)+SUM(AF23:AJ23),2) -> 20.18 | AL23: 0 | AR23: ACT. EMPRESARIALES CON REGISTRO DE INGRESOS Y EGRESOS | AS23: 510 | AT23: =IF(OR(AS23=545, AS23=518),($AK23-$Z23-$AC23-$AF23),IF(AND(AS23>515,AS23<518),($W23),IF(AND(AS23>509,AS23<516),$X23,IF(AS23=541,$U23,IF(AS23=542,$V23+SUM($AG23:$AJ23),IF(AS23=533,$AD23,IF(AS23=550,$AA23,0))))))) -> 17.55 | AU23: 0 | AV23: =IF(OR(AU23=545, AU23=518),($AK23-$Z23-$AC23-$AF23),IF(AND(AU23>515,AU23<518),($W23),IF(AND(AU23>509,AU23<516),$X23,IF(AU23=541,$U23,IF(AU23=542,$V23+SUM($AG23:$AJ23),IF(AU23=533,$AD23,IF(AU23=550,$AA23,0))))))) -> 0 | AW23: 542 | AX23: =IF(OR(AW23=545, AW23=518),($AK23-$Z23-$AC23-$AF23),IF(AND(AW23>515,AW23<518),($W23),IF(AND(AW23>509,AW23<516),$X23,IF(AW23=541,$U23,IF(AW23=542,$V23+SUM($AG23:$AJ23),IF(AW23=533,$AD23,IF(AW23=550,$AA23,0))))))) -> 0 | BF23: 332 | BG23: =SUM(U23:X23)-V23+AA23+AD23 -> 17.55 | BH23: =IF(ISERROR(VLOOKUP(BF23,Parametros!$C:$J,8,0)),0,VLOOKUP(BF23,Parametros!$C:$J,8,0)) -> 0 | BI23: =IF(ISERROR(ROUND((BG23*BH23),2)),0,ROUND((BG23*BH23),2)) -> 0 | BK23: 0 | BM23: 0 | BN23: 0 | BP23: =SUM(U23:X23)-V23+AA23+AD23-BG23 -> 0 | BQ23: =IF(ISERROR(VLOOKUP(BO23,Parametros!$C:$J,8,0)),0,VLOOKUP(BO23,Parametros!$C:$J,8,0)) -> 0 | BR23: =IF(ISERROR(ROUND((BP23*BQ23),2)),0,ROUND((BP23*BQ23),2)) -> 0 | BT23: 0 | BV23: 0 | BW23: 0 | BY23: =SUM(U23:X23)-V23+AA23+AD23-BG23-BP23 -> 0 | BZ23: =IF(ISERROR(VLOOKUP(BX23,Parametros!$C:$J,8,0)),0,VLOOKUP(BX23,Parametros!$C:$J,8,0)) -> 0 | CA23: =IF(ISERROR(ROUND((BY23*BZ23),2)),0,ROUND((BY23*BZ23),2)) -> 0 | CC23: 0 | CD23: 0 | CE23: 0 | CF23: 0 | CG23: 0 | CH23: 0 | CI23: 0 | CJ23: 0 | CK23: =+BI23+BR23+CA23+SUM(CC23:CJ23) -> 0 | CP23: 01-PAGO A RESIDENTE | CQ23: 01-SIN UTILIZACION DEL SISTEMA FINANCIERO | CS23: 01-REGIMEN GENERAL | DB23: =IF(ISNUMBER(M23),MONTH(M23),0) -> 4 | DC23: =IF(ISNUMBER(M23),IF(ISERROR(HLOOKUP(MONTH(M23),meses_104,1,0)),"NO","SI"),"NO") -> SI | DD23: =IF(ISNUMBER(M23),IF(ISERROR(HLOOKUP(MONTH(M23),meses_103,1,0)),"NO","SI"),"NO") -> SI | DE23: =IF(ISBLANK(G23),0,IF(VALUE(LEFT(G23,2))=4,0,AT23)) -> 17.55 | DF23: =IF(ISBLANK(G23),0,IF(VALUE(LEFT(G23,2))=4,0,AV23)) -> 0 | DG23: =IF(ISBLANK(G23),0,IF(VALUE(LEFT(G23,2))=4,0,AX23)) -> 0 | DH23: =SUM(U23:W23)+SUM(AG23:AJ23) -> 0 | DI23: =ROUND((IF(AS23=545,(Z23+AC23+AF23),0)+IF(AU23=545,(Z23+AC23+AF23),0)+IF(AW23=545,(Z23+AC23+AF23),0)),2) -> 0 | DJ23: =ROUND((IF(AS23=512,Z23,0)+IF(AU23=512,Z23,0)+IF(AW23=512,Z23,0)),2) -> 0 | DK23: =Z23+AC23+AF23-DI23-DJ23 -> 2.63 | DL23: =SUM(CC23:CH23)+CJ23 -> 0 | DM23: =CI23 -> 0 | DN23: =BI23+BR23+CA23 -> 0 | DQ23: 07 | DR23: PENDIENTE | DX23: OTROS | DY23: NORMAL | EE23: 0 | EF23: 0 | EG23: 0
A24: 0992146818001 | B24: R-Ruc | C24: ZC MAYORISTAS S.A. | D24: 02-Sociedad | E24: NO | G24: 01-Factura | H24: 006 | I24: 001 | J24: 000049309 | K24: 0904202601099214681800120060010000493099846951115 | L24: 46121 | M24: 46121 | T24: 02- Costo o Gasto para declaración de IR (servicios y bienes distintos de inventarios y activos fijos) | U24: 0 | V24: 0 | W24: 0 | X24: 8760 | Y24: 15 | Z24: =ROUND(X24*Y24%,2) -> 1314 | AA24: 0 | AB24: 5 | AC24: =ROUND(AA24*AB24%,2) -> 0 | AE24: 8 | AF24: =ROUND(AD24*AE24%,2) -> 0 | AG24: 0 | AH24: 0 | AI24: 0 | AJ24: 0 | AK24: =ROUND(SUM(U24:X24)+SUM(Z24:AA24)+SUM(AC24:AD24)+SUM(AF24:AJ24),2) -> 10074 | AL24: 0 | AR24: ACT. EMPRESARIALES CON REGISTRO DE INGRESOS Y EGRESOS | AS24: 510 | AT24: =IF(OR(AS24=545, AS24=518),($AK24-$Z24-$AC24-$AF24),IF(AND(AS24>515,AS24<518),($W24),IF(AND(AS24>509,AS24<516),$X24,IF(AS24=541,$U24,IF(AS24=542,$V24+SUM($AG24:$AJ24),IF(AS24=533,$AD24,IF(AS24=550,$AA24,0))))))) -> 8760 | AU24: 0 | AV24: =IF(OR(AU24=545, AU24=518),($AK24-$Z24-$AC24-$AF24),IF(AND(AU24>515,AU24<518),($W24),IF(AND(AU24>509,AU24<516),$X24,IF(AU24=541,$U24,IF(AU24=542,$V24+SUM($AG24:$AJ24),IF(AU24=533,$AD24,IF(AU24=550,$AA24,0))))))) -> 0 | AW24: 542 | AX24: =IF(OR(AW24=545, AW24=518),($AK24-$Z24-$AC24-$AF24),IF(AND(AW24>515,AW24<518),($W24),IF(AND(AW24>509,AW24<516),$X24,IF(AW24=541,$U24,IF(AW24=542,$V24+SUM($AG24:$AJ24),IF(AW24=533,$AD24,IF(AW24=550,$AA24,0))))))) -> 0 | BF24: 332 | BG24: =SUM(U24:X24)-V24+AA24+AD24 -> 8760 | BH24: =IF(ISERROR(VLOOKUP(BF24,Parametros!$C:$J,8,0)),0,VLOOKUP(BF24,Parametros!$C:$J,8,0)) -> 0 | BI24: =IF(ISERROR(ROUND((BG24*BH24),2)),0,ROUND((BG24*BH24),2)) -> 0 | BK24: 0 | BM24: 0 | BN24: 0 | BP24: =SUM(U24:X24)-V24+AA24+AD24-BG24 -> 0 | BQ24: =IF(ISERROR(VLOOKUP(BO24,Parametros!$C:$J,8,0)),0,VLOOKUP(BO24,Parametros!$C:$J,8,0)) -> 0 | BR24: =IF(ISERROR(ROUND((BP24*BQ24),2)),0,ROUND((BP24*BQ24),2)) -> 0 | BT24: 0 | BV24: 0 | BW24: 0 | BY24: =SUM(U24:X24)-V24+AA24+AD24-BG24-BP24 -> 0 | BZ24: =IF(ISERROR(VLOOKUP(BX24,Parametros!$C:$J,8,0)),0,VLOOKUP(BX24,Parametros!$C:$J,8,0)) -> 0 | CA24: =IF(ISERROR(ROUND((BY24*BZ24),2)),0,ROUND((BY24*BZ24),2)) -> 0 | CC24: 0 | CD24: 0 | CE24: 0 | CF24: 0 | CG24: 0 | CH24: 0 | CI24: 0 | CJ24: 0 | CK24: =+BI24+BR24+CA24+SUM(CC24:CJ24) -> 0 | CP24: 01-PAGO A RESIDENTE | CQ24: 20-OTROS CON UTILIZACION DEL SISTEMA FINANCIERO | CS24: 01-REGIMEN GENERAL | DB24: =IF(ISNUMBER(M24),MONTH(M24),0) -> 4 | DC24: =IF(ISNUMBER(M24),IF(ISERROR(HLOOKUP(MONTH(M24),meses_104,1,0)),"NO","SI"),"NO") -> SI | DD24: =IF(ISNUMBER(M24),IF(ISERROR(HLOOKUP(MONTH(M24),meses_103,1,0)),"NO","SI"),"NO") -> SI | DE24: =IF(ISBLANK(G24),0,IF(VALUE(LEFT(G24,2))=4,0,AT24)) -> 8760 | DF24: =IF(ISBLANK(G24),0,IF(VALUE(LEFT(G24,2))=4,0,AV24)) -> 0 | DG24: =IF(ISBLANK(G24),0,IF(VALUE(LEFT(G24,2))=4,0,AX24)) -> 0 | DH24: =SUM(U24:W24)+SUM(AG24:AJ24) -> 0 | DI24: =ROUND((IF(AS24=545,(Z24+AC24+AF24),0)+IF(AU24=545,(Z24+AC24+AF24),0)+IF(AW24=545,(Z24+AC24+AF24),0)),2) -> 0 | DJ24: =ROUND((IF(AS24=512,Z24,0)+IF(AU24=512,Z24,0)+IF(AW24=512,Z24,0)),2) -> 0 | DK24: =Z24+AC24+AF24-DI24-DJ24 -> 1314 | DL24: =SUM(CC24:CH24)+CJ24 -> 0 | DM24: =CI24 -> 0 | DN24: =BI24+BR24+CA24 -> 0 | DQ24: 07 | DR24: PENDIENTE | DX24: OTROS | DY24: NORMAL | EE24: 0 | EF24: 0 | EG24: 0
A25: 1793102972001 | B25: R-Ruc | C25: CLARYSTEL S.A.S. | D25: 02-Sociedad | E25: NO | G25: 01-Factura | H25: 001 | I25: 002 | J25: 000016940 | K25: 0904202601179310297200120010020000169401234567810 | L25: 46121 | M25: 46121 | T25: 02- Costo o Gasto para declaración de IR (servicios y bienes distintos de inventarios y activos fijos) | U25: 0 | V25: 0 | W25: 0 | X25: 219 | Y25: 15 | Z25: =ROUND(X25*Y25%,2) -> 32.85 | AA25: 0 | AB25: 5 | AC25: =ROUND(AA25*AB25%,2) -> 0 | AE25: 8 | AF25: =ROUND(AD25*AE25%,2) -> 0 | AG25: 0 | AH25: 0 | AI25: 0 | AJ25: 0 | AK25: =ROUND(SUM(U25:X25)+SUM(Z25:AA25)+SUM(AC25:AD25)+SUM(AF25:AJ25),2) -> 251.85 | AL25: 0 | AR25: ACT. EMPRESARIALES CON REGISTRO DE INGRESOS Y EGRESOS | AS25: 510 | AT25: =IF(OR(AS25=545, AS25=518),($AK25-$Z25-$AC25-$AF25),IF(AND(AS25>515,AS25<518),($W25),IF(AND(AS25>509,AS25<516),$X25,IF(AS25=541,$U25,IF(AS25=542,$V25+SUM($AG25:$AJ25),IF(AS25=533,$AD25,IF(AS25=550,$AA25,0))))))) -> 219 | AU25: 0 | AV25: =IF(OR(AU25=545, AU25=518),($AK25-$Z25-$AC25-$AF25),IF(AND(AU25>515,AU25<518),($W25),IF(AND(AU25>509,AU25<516),$X25,IF(AU25=541,$U25,IF(AU25=542,$V25+SUM($AG25:$AJ25),IF(AU25=533,$AD25,IF(AU25=550,$AA25,0))))))) -> 0 | AW25: 542 | AX25: =IF(OR(AW25=545, AW25=518),($AK25-$Z25-$AC25-$AF25),IF(AND(AW25>515,AW25<518),($W25),IF(AND(AW25>509,AW25<516),$X25,IF(AW25=541,$U25,IF(AW25=542,$V25+SUM($AG25:$AJ25),IF(AW25=533,$AD25,IF(AW25=550,$AA25,0))))))) -> 0 | AZ25: E-Electronico(v1.0) | BA25: 003 | BB25: 001 | BC25: 000000087 | BD25: 0904202607091780945100120030010000000875603404813 | BE25: 46121 | BF25: 312 | BG25: =SUM(U25:X25)-V25+AA25+AD25 -> 219 | BH25: =IF(ISERROR(VLOOKUP(BF25,Parametros!$C:$J,8,0)),0,VLOOKUP(BF25,Parametros!$C:$J,8,0)) -> 0.02 | BI25: =IF(ISERROR(ROUND((BG25*BH25),2)),0,ROUND((BG25*BH25),2)) -> 4.38 | BK25: 0 | BM25: 0 | BN25: 0 | BP25: =SUM(U25:X25)-V25+AA25+AD25-BG25 -> 0 | BQ25: =IF(ISERROR(VLOOKUP(BO25,Parametros!$C:$J,8,0)),0,VLOOKUP(BO25,Parametros!$C:$J,8,0)) -> 0 | BR25: =IF(ISERROR(ROUND((BP25*BQ25),2)),0,ROUND((BP25*BQ25),2)) -> 0 | BT25: 0 | BV25: 0 | BW25: 0 | BY25: =SUM(U25:X25)-V25+AA25+AD25-BG25-BP25 -> 0 | BZ25: =IF(ISERROR(VLOOKUP(BX25,Parametros!$C:$J,8,0)),0,VLOOKUP(BX25,Parametros!$C:$J,8,0)) -> 0 | CA25: =IF(ISERROR(ROUND((BY25*BZ25),2)),0,ROUND((BY25*BZ25),2)) -> 0 | CC25: 0 | CD25: 0 | CE25: 0 | CF25: 0 | CG25: 0 | CH25: 0 | CI25: 0 | CJ25: 0 | CK25: =+BI25+BR25+CA25+SUM(CC25:CJ25) -> 4.38 | CP25: 01-PAGO A RESIDENTE | CQ25: 01-SIN UTILIZACION DEL SISTEMA FINANCIERO | CS25: 01-REGIMEN GENERAL | DB25: =IF(ISNUMBER(M25),MONTH(M25),0) -> 4 | DC25: =IF(ISNUMBER(M25),IF(ISERROR(HLOOKUP(MONTH(M25),meses_104,1,0)),"NO","SI"),"NO") -> SI | DD25: =IF(ISNUMBER(M25),IF(ISERROR(HLOOKUP(MONTH(M25),meses_103,1,0)),"NO","SI"),"NO") -> SI | DE25: =IF(ISBLANK(G25),0,IF(VALUE(LEFT(G25,2))=4,0,AT25)) -> 219 | DF25: =IF(ISBLANK(G25),0,IF(VALUE(LEFT(G25,2))=4,0,AV25)) -> 0 | DG25: =IF(ISBLANK(G25),0,IF(VALUE(LEFT(G25,2))=4,0,AX25)) -> 0 | DH25: =SUM(U25:W25)+SUM(AG25:AJ25) -> 0 | DI25: =ROUND((IF(AS25=545,(Z25+AC25+AF25),0)+IF(AU25=545,(Z25+AC25+AF25),0)+IF(AW25=545,(Z25+AC25+AF25),0)),2) -> 0 | DJ25: =ROUND((IF(AS25=512,Z25,0)+IF(AU25=512,Z25,0)+IF(AW25=512,Z25,0)),2) -> 0 | DK25: =Z25+AC25+AF25-DI25-DJ25 -> 32.85 | DL25: =SUM(CC25:CH25)+CJ25 -> 0 | DM25: =CI25 -> 0 | DN25: =BI25+BR25+CA25 -> 4.38 | DQ25: 07 | DR25: PENDIENTE | DX25: OTROS | DY25: NORMAL | EE25: 0 | EF25: 0 | EG25: 0
